Workbook
Name סכומים: #REF!

Sheet Prop ID
A1: Prop ID | B1: client | C1: Address | D1: Key
A2: 3 | B2: Lisac | D2: 14 | F2: *
A3: 5 | B3: Jacobson | D3: 20 | F3: *
A4: 6 | B4: Wurtman | D4: 25 | F4: *
A5: 17 | B5: sommer | D5: 31
A6: 22 | B6: Fischer | D6: 1 | F6: *
A7: 23 | B7: Frank
A8: 95 | B8: Greenstone | D8: 44 | F8: *
A9: 120 | B9: Schindler | D9: 26 | F9: *
A10: 162 | B10: Aboudi | D10: * | F10: *
A11: 183 | B11: Netanel | D11: 13 | F11: *
A12: 210
A13: 225 | B13: Kaplan | D13: 6
A14: 257 | B14: Pollack/Rotenberg | D14: 27,28,29 | F14: *
A15: 258 | B15: Mayerfeld | D15: 15 | F15: *
A16: 265 | B16: Hainey | D16: 4 | F16: *
A17: 273 | B17: Licht | D17: 18 | F17: *
A18: 277 | B18: Hockstein | D18: 10 | F18: *
A19: 555 | B19: Rosenberg | D19: *
A20: 535 | B20: Fruchter
A21: 618 | B21: Silver + master | D21: 7 | F21: *
A22: 619 | B22: silver | D22: 8 | F22: *
A23: 707 | B23: Cohen | D23: 47 | F23: *
A24: 801 | B24: silver | D24: 9 | F24: *
A25: 280 | B25: edson | D25: 2 | F25: *
B26: turner | D26: 38
A27: 77 | B27: charles | D27: *
A28: Sale/ rental
B29: meizner | D29: 37
B30: lee hod | D30: 40
B31: Epstien | D31: 42
B32: Frank | D32: 45

Sheet Dashboard
A1: Property | B1: Expenses | C1: Inflow | D1: Balance | E1: tikun cash | F1: Client Name | G1: דוח אחרון | H1: מספר לקוח | J1: ת.ז סנדי 317179455 | M1: אם אי פי מקרקעין ג.ר בע"מ
A2: 3 | B2: =SUM('03 EX'!F:F) -> 182931.32 | C2: =SUM('03 EX'!G:G) -> 183057.31 | D2: =C2-B2 -> 125.99 | F2: ליסאק | G2: 44602 | H2: 3 | J2: טלפון סנדי: 054-4910603
A3: 4 | B3: =SUM('04 EX'!F:F) -> 1632 | C3: =SUM('04 EX'!G:G) -> 1435 | D3: =C3-B3 -> -197 | F3: פנטנוביץ | H3: 4
A4: 5 | B4: =SUM('05 ex'!F:F) -> 325834.34 | C4: =SUM('05 ex'!G:G) -> 326338.33 | D4: =C4-B4 -> 503.99 | G4: 11/06/20525 | H4: 5
A5: 8 | B5: =SUM('08 ex'!F:F) -> 30505.04 | C5: =SUM('08 ex'!G:G) -> 31087.2 | D5: =C5-B5 -> 582.16 | G5: 45652 | H5: 8
A6: 12 | B6: =SUM('12 ex'!F:F) -> 46626.64 | C6: =SUM('12 ex'!G:G) -> 46626.64 | D6: =C6-B6 -> 0 | G6: 45496 | H6: 12
A7: 13 | B7: =SUM('13'!F:F) -> 103617.5 | C7: =SUM('13'!G:G) -> 106999.8 | D7: =C7-B7 -> 3382.3 | G7: 45543 | H7: 13
A8: 9 | B8: =SUM('09 ex'!F:F) -> 2253.34 | C8: =SUM('09 ex'!G:G) -> 2253.34 | D8: =C8-B8 -> 0 | H8: 9
A9: 17 | B9: =SUM('17'!F:F) -> 72341.84 | C9: =SUM('17'!G:G) -> 72341.95 | D9: =C9-B9 -> 0.11 | G9: 45898 | H9: 17
A10: 25 | B10: =SUM('25'!F:F) -> 27851.2 | C10: =SUM('25'!G:G) -> 27792 | D10: =C10-B10 -> -59.2 | G10: 45714 | H10: 25
A11: 30 | B11: =SUM('30'!F:F) -> 40000 | C11: =SUM('30'!G:G) -> 40000 | D11: =C11-B11 -> 0 | G11: 45508 | H11: 30
A12: 36 | B12: =SUM('36'!F:F) -> 12975.29 | C12: =SUM('36'!G:G) -> 19227.43 | D12: =C12-B12 -> 6252.14 | G12: 45898 | H12: 36
A13: 84 | B13: =SUM('84'!F:F) -> 88428.08 | C13: =SUM('84'!G:G) -> 147000 | D13: =C13-B13 -> 58571.92 | G13: 45774 | H13: 84 | I13: *
A14: 106 | B14: =SUM('106'!F:F) -> 11000 | C14: =SUM('106'!G:G) -> 11000 | D14: =C14-B14 -> 0 | G14: 45552 | H14: 106
A15: 111 | B15: =SUM('111'!F:F) -> 20807 | C15: =SUM('111'!G:G) -> 23815 | D15: =C15-B15 -> 3008 | G15: 45898 | H15: 111
A16: 120 | B16: =SUM('120 EX'!F:F) -> 90636.41 | C16: =SUM('120 EX'!G:G) -> 90636.25 | D16: =C16-B16 -> -0.16 | G16: 45076 | H16: 120
A17: 131 | B17: =SUM('131'!F:F) -> 33608.06 | C17: =SUM('131'!G:G) -> 33000 | D17: =C17-B17 -> -608.06 | G17: 45672 | H17: 131
A18: 149 | B18: =SUM('149'!F:F) -> 11895.96 | C18: =SUM('149'!G:G) -> 17025.6 | D18: =C18-B18 -> 5129.64 | H18: 149
A19: 301 | B19: =SUM('301'!F:F) -> 5097.58 | C19: =SUM('301'!G:G) -> 7943.86 | D19: =C19-B19 -> 2846.28 | H19: 301
A20: 1210 | B20: =SUM('1210'!F:F) -> 3567.05 | C20: =SUM('1210'!G:G) -> 4400 | D20: =C20-B20 -> 832.95 | H20: 1210
A21: 1301 | B21: =SUM('1301'!F:F) -> 5762 | C21: =SUM('1301'!G:G) -> 5762 | D21: =C21-B21 -> 0 | H21: 1301
A22: 183 | B22: =SUM('183 ex'!F:F) -> 89118.633 | C22: =SUM('183 ex'!G:G) -> 92935.4 | D22: =C22-B22 -> 3816.7665 | E22: 1017.6 | G22: 45774 | H22: 183 | I22: ***
A23: 210 | B23: =SUM('210'!F:F) -> 480.1 | C23: =SUM('210'!G:G) -> 480.1 | D23: =C23-B23 -> 0 | H23: 210
A24: 257 | B24: =SUM('257 Ex'!F:F) -> 889845.93 | C24: =SUM('257 Ex'!G:G) -> 894321.61 | D24: =C24-B24 -> 4475.68 | G24: 45708 | H24: 257
A25: 273 | B25: =SUM('273 EX'!F:F) -> 404803.26 | C25: =SUM('273 EX'!G:G) -> 403303.81 | D25: =C25-B25 -> -1499.4535 | E25: 800 | G25: 45774 | H25: 273
A26: H003/H111 | B26: =SUM('H111'!F:F) -> 93056.015 | C26: =SUM('H111'!G:G) -> 93056.02 | D26: =C26-B26 -> 0.005 | G26: 44783 | H26: H003/H111
A27: 277 | B27: =SUM('277 EX'!F:F) -> 635594.65 | C27: =SUM('277 EX'!G:G) -> 637025.28 | D27: =C27-B27 -> 1430.63 | E27: 939.5 | G27: 45693 | H27: 277
A28: 535 | B28: =SUM('535'!F:F) -> 34518.345 | C28: =SUM('535'!G:G) -> 34518.2 | D28: =C28-B28 -> -0.145 | G28: 45252 | H28: 535
A29: 707 | B29: =SUM('707 EX'!F:F) -> 469529.13 | C29: =SUM('707 EX'!G:G) -> 469529.13 | D29: =C29-B29 -> 0 | G29: 45643 | H29: 707
A30: 567 | B30: =SUM('567'!F:F) -> 0 | C30: =SUM('567'!G:G) -> 0 | D30: =C30-B30 -> 0 | H30: 567
A31: 618/619/801 | B31: =SUM('801-618- 619'!F:F) -> 49319.46 | C31: =SUM('801-618- 619'!G:G) -> 50706.4 | D31: =C31-B31 -> 1386.94 | G31: 44950 | H31: 618/619/801
A32: C15 | B32: =SUM('C15'!F:F) -> 59679.17 | C32: =SUM('C15'!G:G) -> 58421.54 | D32: =C32-B32 -> -1257.63 | G32: 45564 | H32: C15
A33: c19 | B33: =SUM('c19'!F:F) -> 374137.09 | C33: =SUM('c19'!G:G) -> 378722 | D33: =C33-B33 -> 4584.915 | G33: 45898 | H33: C19 | M33: 516497815
A34: c31 | B34: =SUM('c31'!F:F) -> 169590.66 | C34: =SUM('c31'!G:G) -> 181381.89 | D34: =C34-B34 -> 11791.23 | G34: 45690 | H34: C31
A35: c4 | B35: =SUM('c4 EX'!F:F) -> 311534.22 | C35: =SUM('c4 EX'!G:G) -> 314684 | D35: =C35-B35 -> 3149.7752 | G35: 45894 | H35: C4
A36: C50 | B36: =SUM('C50'!F:F) -> 80582.885 | C36: =SUM('C50'!G:G) -> 80582.89 | D36: =C36-B36 -> 0.005 | G36: 45167 | H36: C50
A37: C6 | B37: =SUM('06 ex'!F:F) -> 356402.04 | C37: =SUM('06 ex'!G:G) -> 353399 | D37: =C37-B37 -> -3003.04 | G37: 25/0/2025 | H37: C6
A38: C8 | B38: =SUM('C8'!F:F) -> 3914.27 | C38: =SUM('C8'!G:G) -> 4189 | D38: =C38-B38 -> 274.73 | H38: C8
A39: N160 | B39: =SUM('N160'!F:F) -> 48443.58 | C39: =SUM('N160'!G:G) -> 46694.56 | D39: =C39-B39 -> -1749.02 | H39: N160
A40: p14 | B40: =SUM('p14'!F:F) -> 104891.46 | C40: =SUM('p14'!G:G) -> 104319.79 | D40: =C40-B40 -> -571.67 | G40: 45574 | H40: P14 | I40: 2500 keep (29/01 goes back zucker)
A41: P40 | B41: =SUM('p40'!F:F) -> 187195.88 | C41: =SUM('p40'!G:G) -> 183494.33 | D41: =C41-B41 -> -3701.55 | G41: 45819 | H41: P40
A42: 209 | B42: =SUM('209'!F:F) -> 400 | C42: =SUM('209'!G:G) -> 400 | D42: =C42-B42 -> 0 | G42: 45657 | H42: 209
A43: Totals | B43: =SUM(B2:B42) -> 5480407.4 | C43: =SUM(C2:C42) -> 5579906.7 | D43: =SUM(D2:D42) -> 99499.228
F44: דשן משאבה
A45: Buffer | B45: =SUM(Buffer!D:D) -> 205212.33 | C45: =SUM(Buffer!E:E) -> 214750.72 | D45: =C45-B45 -> 9538.39
K46: =K47/4 -> 30
K47: =260-K48-K49 -> 120
A48: Running balance | D48: =D43+D45 -> 109037.62 | E48: 39615.16 | F48: =E48-D48 -> -69422.458 | K48: 40
K49: 100
A50: not yet cleared
A51: cc | D51: =B85+B78 -> 0 | E51: משכורות | F51: כרטיסי אשראי בנק לאומי
A52: שקים - עדיין לא ירדו בבנק | D52: =C95 -> 0 | E52: 3848 | G52: 6947 | K52: 3124 | O52: \
D53: =SUM(E53:H53) -> 8875.12 | F53: =300+514.5 -> 814.5 | G53: =2646.56+298.11 -> 2944.67 | H53: =160+244.92+3132.9+81.7+590.05+119+117.24+179.4-5.52+18.4+477.86 -> 5115.95 | K53: 2876
A54: העברה בנקאית | D54: =B68 -> 0 | E54: ביטוח לאומי | K54: =K52+K53 -> 6000
A55: העברה בנקאית | D55: =B69 -> 0 | E55: פנסיה
D56: =D93 -> -3477.86 | E56: אחר
A57: Per sheet (adjusted) | D57: =D48+D51+D52+D53+D54+D55+D56 -> 114434.88 | F57: This takes running balance and adds cc not yet cleared
A59: Per bank | D59: 114434.88
B60: =22.5+49.7+50 -> 122.2
A61: Difference | D61: =D57-D59 -> -0.001754099 | E61: this should be 0
I62: 10םפןם
B66: העברה בנקאית | C66: שק | D66: אשראי | F66: עובד | G66: מעביד | H66: פיצויים | J66: =SUM(J61:J65) -> 0
E68: waiting for
C69: 4.2025 afr | D69: -3000 | E69: שולם למושיקו - אור המיזוג מקדמה עבור עבודה שלא הושלמה בעמל 40 הוא חייב לנו את הסכום הזה בחזרה חשבונית 3396 | F69: ..\Clients\Current Clients\P40 Adele\Receipts\2026\אור בזמיזוג קבלה.pdf | G69: =2167-516 -> 1651
D70: -477.86 | E70: חברת חשמל אשראי 6947 - 25.6.2026 - כנראה 277
H72: =5500-#REF! -> #REF! | M72: טיב
H73: 2835
G79: =D78+#REF!+D79 -> #REF!
A87: =#REF!+#REF!+4861+1600+1700+472+600 -> #REF! | E87: קבלה | H87: =#REF!*18% -> #REF!
E88: C4 | H88: =#REF!*1.18 -> #REF!
E89: הכשרה 707 | H89: =#REF!+H87 -> #REF!
E90: MIP
E91: אלנה
E92: אושר
B93: =SUM(B67:B92) -> 0 | C93: =SUM(C67:C92) -> 0 | D93: =SUM(D67:D92) -> -3477.86 | E93: סה"כ
J110: 22931.47

Sheet Buffer
A1: Prop ID | B1: Date | C1: Type | D1: Amount | E1: Inflow | F1: MIP | G1: Method | H1: Reconciled | I1: Company | J1: reciept | K1: Returned | L1: Balance | M1: Total Amount | N1: Total Inflow
A2: Buffer | B2: 42322 | C2: עמלות בנק | D2: 10 | L2: =N2-M2 -> -3524.85 | M2: =SUM(D$19:$D723) -> 77361.65 | N2: =SUM(E$19:$E723) -> 73836.8
A3: Buffer | B3: 42323 | C3: עמלת בנק | D3: 10 | L3: =N3-M3 -> -3524.85 | M3: =SUM(D$19:$D723) -> 77361.65 | N3: =SUM(E$19:$E723) -> 73836.8
A4: Buffer | B4: 42324 | C4: עמלות בנק | D4: 13.2 | L4: =N4-M4 -> -3524.85 | M4: =SUM(D$19:$D723) -> 77361.65 | N4: =SUM(E$19:$E723) -> 73836.8
A5: Buffer | B5: 42325 | C5: דמי כרטיס אשראי | D5: 13.9 | L5: =N5-M5 -> -3524.85 | M5: =SUM(D$19:$D723) -> 77361.65 | N5: =SUM(E$19:$E723) -> 73836.8
A6: Buffer | B6: 42326 | C6: דמי כרטיס אשראי | D6: 13.9 | L6: =N6-M6 -> -3524.85 | M6: =SUM(D$19:$D723) -> 77361.65 | N6: =SUM(E$19:$E723) -> 73836.8
A7: Buffer | B7: 42327 | C7: חומרי בניין דוד מלכה - לא ידוע | D7: 19 | L7: =N7-M7 -> -3524.85 | M7: =SUM(D$19:$D723) -> 77361.65 | N7: =SUM(E$19:$E723) -> 73836.8
A8: Buffer | B8: 42328 | C8: עמלת בנק | D8: 34.65 | L8: =N8-M8 -> -3524.85 | M8: =SUM(D$19:$D723) -> 77361.65 | N8: =SUM(E$19:$E723) -> 73836.8
A9: Buffer | B9: 42329 | C9: תיקון מים בוריס - סילבר | D9: 52.8 | L9: =N9-M9 -> -3524.85 | M9: =SUM(D$19:$D723) -> 77361.65 | N9: =SUM(E$19:$E723) -> 73836.8
A10: Buffer | B10: 42330 | C10: מים ג'קובסון | D10: 150 | L10: =N10-M10 -> -3524.85 | M10: =SUM(D$19:$D723) -> 77361.65 | N10: =SUM(E$19:$E723) -> 73836.8
A11: Buffer | B11: 42331 | C11: חשמל דייר 277 | D11: 152 | L11: =N11-M11 -> -3524.85 | M11: =SUM(D$19:$D723) -> 77361.65 | N11: =SUM(E$19:$E723) -> 73836.8
A12: Buffer | B12: 42332 | C12: חשמל ג'קובסון | D12: 200 | L12: =N12-M12 -> -3524.85 | M12: =SUM(D$19:$D723) -> 77361.65 | N12: =SUM(E$19:$E723) -> 73836.8
A13: Buffer | B13: 42333 | C13: העברה לסנדי פועלים | D13: 1500 | L13: =N13-M13 -> -3524.85 | M13: =SUM(D$19:$D723) -> 77361.65 | N13: =SUM(E$19:$E723) -> 73836.8
A14: Buffer | B14: 42334 | C14: כסף לבאפר | E14: 3000 | L14: =N14-M14 -> -3524.85 | M14: =SUM(D$19:$D723) -> 77361.65 | N14: =SUM(E$19:$E723) -> 73836.8
A15: Buffer | B15: 42335 | C15: עמלת תיווך גרי | E15: 1500 | L15: =N15-M15 -> -3524.85 | M15: =SUM(D$19:$D723) -> 77361.65 | N15: =SUM(E$19:$E723) -> 73836.8
A16: Buffer | B16: 42336 | C16: תיקון פולק | E16: 250 | L16: =N16-M16 -> -3524.85 | M16: =SUM(D$19:$D723) -> 77361.65 | N16: =SUM(E$19:$E723) -> 73836.8
A17: Buffer | B17: 42337 | C17: הנחה כרטיס אשראי | E17: 5.1 | L17: =N17-M17 -> -3524.85 | M17: =SUM(D$19:$D723) -> 77361.65 | N17: =SUM(E$19:$E723) -> 73836.8
A18: Buffer | B18: 42338 | C18: צבעי 183 | E18: 400 | L18: =N18-M18 -> -3524.85 | M18: =SUM(D$19:$D723) -> 77361.65 | N18: =SUM(E$19:$E723) -> 73836.8
A19: Buffer | B19: 42339 | C19: car insurance | D19: 95 | H19: y | L19: =N19-M19 -> -95 | M19: =SUM($D$19:D19) -> 95 | N19: =SUM($E$19:E19) -> 0
A20: Buffer | B20: 42390 | C20: Kvish 6 | D20: 252.64 | G20: cc | L20: =N20-M20 -> -347.64 | M20: =SUM($D$19:D20) -> 347.64 | N20: =SUM($E$19:E20) -> 0
A21: Buffer | B21: 42401 | C21: bank fee | D21: 10 | G21: t | H21: y | L21: =N21-M21 -> -357.64 | M21: =SUM($D$19:D21) -> 357.64 | N21: =SUM($E$19:E21) -> 0
A22: Buffer | B22: 42417 | C22: credit fee | D22: 1.52 | G22: cc | L22: =N22-M22 -> -359.16 | M22: =SUM($D$19:D22) -> 359.16 | N22: =SUM($E$19:E22) -> 0
A23: Buffer | B23: 42417 | C23: efax | D23: 52.05 | G23: cc | H23: y | L23: =N23-M23 -> -411.21 | M23: =SUM($D$19:D23) -> 411.21 | N23: =SUM($E$19:E23) -> 0
A24: Buffer | B24: 42425 | C24: fees | D24: 1.82 | G24: cc | L24: =N24-M24 -> -413.03 | M24: =SUM($D$19:D24) -> 413.03 | N24: =SUM($E$19:E24) -> 0
A25: Buffer | B25: 42425 | C25: google storage | D25: 7.77 | G25: cc | H25: y | L25: =N25-M25 -> -420.8 | M25: =SUM($D$19:D25) -> 420.8 | N25: =SUM($E$19:E25) -> 0
A26: Buffer | B26: 42425 | C26: credot fee | D26: 13.9 | G26: cc | H26: y | L26: =N26-M26 -> -434.7 | M26: =SUM($D$19:D26) -> 434.7 | N26: =SUM($E$19:E26) -> 0
A27: Buffer | B27: 42430 | C27: bank fee | D27: 10 | G27: t | H27: y | L27: =N27-M27 -> -444.7 | M27: =SUM($D$19:D27) -> 444.7 | N27: =SUM($E$19:E27) -> 0
A28: Buffer | B28: 42436 | C28: clothes | D28: 57 | G28: cc | H28: y | L28: =N28-M28 -> -501.7 | M28: =SUM($D$19:D28) -> 501.7 | N28: =SUM($E$19:E28) -> 0
A29: Buffer | B29: 42436 | C29: clothes | D29: 189.9 | G29: cc | H29: y | L29: =N29-M29 -> -691.6 | M29: =SUM($D$19:D29) -> 691.6 | N29: =SUM($E$19:E29) -> 0
A30: Buffer | B30: 42436 | C30: clothes | D30: 259 | G30: cc | H30: y | L30: =N30-M30 -> -950.6 | M30: =SUM($D$19:D30) -> 950.6 | N30: =SUM($E$19:E30) -> 0
A31: Buffer | B31: 42437 | C31: efax | E31: 98.13 | G31: cc | H31: y | L31: =N31-M31 -> -852.47 | M31: =SUM($D$19:D31) -> 950.6 | N31: =SUM($E$19:E31) -> 98.13
A32: Buffer | B32: 42438 | C32: payment hockstien | E32: 4713 | G32: t | H32: y | L32: =N32-M32 -> 3860.53 | M32: =SUM($D$19:D32) -> 950.6 | N32: =SUM($E$19:E32) -> 4811.13
A33: Buffer | B33: 42439 | C33: payment hockstien | D33: 4713 | G33: t | H33: y | L33: =N33-M33 -> -852.47 | M33: =SUM($D$19:D33) -> 5663.6 | N33: =SUM($E$19:E33) -> 4811.13
A34: Buffer | B34: 42443 | C34: Sandi payment | E34: 10000 | L34: =N34-M34 -> 9147.53 | M34: =SUM($D$19:D34) -> 5663.6 | N34: =SUM($E$19:E34) -> 14811.13
A35: Buffer | B35: 42454 | C35: foreign excahge | D35: 1.78 | G35: cc | H35: y | L35: =N35-M35 -> 9145.75 | M35: =SUM($D$19:D35) -> 5665.38 | N35: =SUM($E$19:E35) -> 14811.13
A36: Buffer | B36: 42454 | C36: google storage | D36: 7.63 | G36: cc | H36: y | L36: =N36-M36 -> 9138.12 | M36: =SUM($D$19:D36) -> 5673.01 | N36: =SUM($E$19:E36) -> 14811.13
A37: Buffer | B37: 42455 | C37: credit fee | D37: 13.9 | G37: cc | H37: y | L37: =N37-M37 -> 9124.22 | M37: =SUM($D$19:D37) -> 5686.91 | N37: =SUM($E$19:E37) -> 14811.13
A38: Buffer | B38: 42461 | C38: bank fee | D38: 3.3 | G38: t | H38: y | L38: =N38-M38 -> 9120.92 | M38: =SUM($D$19:D38) -> 5690.21 | N38: =SUM($E$19:E38) -> 14811.13
A39: Buffer | B39: 42461 | C39: bank fee | D39: 10 | G39: t | L39: =N39-M39 -> 9110.92 | M39: =SUM($D$19:D39) -> 5700.21 | N39: =SUM($E$19:E39) -> 14811.13
A40: Buffer | B40: 42465 | C40: transfer to Leumi | D40: 10000 | H40: y | L40: =N40-M40 -> -889.08 | M40: =SUM($D$19:D40) -> 15700.21 | N40: =SUM($E$19:E40) -> 14811.13
A41: Buffer | B41: 42486 | C41: google storage | D41: 7.7 | H41: y | L41: =N41-M41 -> -896.78 | M41: =SUM($D$19:D41) -> 15707.91 | N41: =SUM($E$19:E41) -> 14811.13
A42: Buffer | B42: 42486 | C42: credit card fee | D42: 13.9 | H42: y | L42: =N42-M42 -> -910.68 | M42: =SUM($D$19:D42) -> 15721.81 | N42: =SUM($E$19:E42) -> 14811.13
A43: Buffer | B43: 42491 | C43: bank fee | D43: 4.95 | G43: t | H43: y | L43: =N43-M43 -> -915.63 | M43: =SUM($D$19:D43) -> 15726.76 | N43: =SUM($E$19:E43) -> 14811.13
A44: Buffer | B44: 42492 | C44: bank fee | D44: 10 | G44: t | H44: y | L44: =N44-M44 -> -925.63 | M44: =SUM($D$19:D44) -> 15736.76 | N44: =SUM($E$19:E44) -> 14811.13
A45: Buffer | B45: 42508 | C45: home center? | D45: 90 | H45: y | L45: =N45-M45 -> -1015.63 | M45: =SUM($D$19:D45) -> 15826.76 | N45: =SUM($E$19:E45) -> 14811.13
A46: Buffer | B46: 42516 | C46: currency transfer fee | D46: 1.78 | H46: y | L46: =N46-M46 -> -1017.41 | M46: =SUM($D$19:D46) -> 15828.54 | N46: =SUM($E$19:E46) -> 14811.13
A47: Buffer | B47: 42516 | C47: google storage | D47: 7.63 | H47: y | L47: =N47-M47 -> -1025.04 | M47: =SUM($D$19:D47) -> 15836.17 | N47: =SUM($E$19:E47) -> 14811.13
A48: Buffer | B48: 42516 | C48: credit card fee | D48: 13.9 | H48: y | L48: =N48-M48 -> -1038.94 | M48: =SUM($D$19:D48) -> 15850.07 | N48: =SUM($E$19:E48) -> 14811.13
A49: Buffer | B49: 42522 | C49: Start | D49: 0 | E49: 2392 | L49: =N49-M49 -> 1353.06 | M49: =SUM($D$19:D49) -> 15850.07 | N49: =SUM($E$19:E49) -> 17203.13
A50: Buffer | B50: 42522 | C50: bank fee | D50: 10 | G50: t | H50: y | L50: =N50-M50 -> 1343.06 | M50: =SUM($D$19:D50) -> 15860.07 | N50: =SUM($E$19:E50) -> 17203.13
A51: Buffer | B51: 42523 | C51: Adjustment | D51: 18.21 | L51: =N51-M51 -> 1324.85 | M51: =SUM($D$19:D51) -> 15878.28 | N51: =SUM($E$19:E51) -> 17203.13
A52: Buffer | B52: 42532 | C52: bekek | D52: 38.9 | H52: y | L52: =N52-M52 -> 1285.95 | M52: =SUM($D$19:D52) -> 15917.18 | N52: =SUM($E$19:E52) -> 17203.13
A53: Buffer | B53: 42533 | C53: took out cash of 1300 to cover cash expenses of 479, 120,180, | D53: 1300 | L53: =N53-M53 -> -14.05 | M53: =SUM($D$19:D53) -> 17217.18 | N53: =SUM($E$19:E53) -> 17203.13
A54: Buffer | B54: 42536 | C54: cash for clients | D54: 200 | H54: y | L54: =N54-M54 -> -214.05 | M54: =SUM($D$19:D54) -> 17417.18 | N54: =SUM($E$19:E54) -> 17203.13
A55: Buffer | B55: 42546 | C55: google storage | D55: 7.94 | H55: y | L55: =N55-M55 -> -221.99 | M55: =SUM($D$19:D55) -> 17425.12 | N55: =SUM($E$19:E55) -> 17203.13
A56: Buffer | B56: 42546 | C56: credit fee | D56: 13.9 | H56: y | L56: =N56-M56 -> -235.89 | M56: =SUM($D$19:D56) -> 17439.02 | N56: =SUM($E$19:E56) -> 17203.13
A57: Buffer | B57: 42548 | C57: bank fee | D57: 24 | G57: t | H57: y | L57: =N57-M57 -> -259.89 | M57: =SUM($D$19:D57) -> 17463.02 | N57: =SUM($E$19:E57) -> 17203.13
A58: Buffer | B58: 42552 | C58: bank fee | D58: 9.9 | G58: t | H58: y | L58: =N58-M58 -> -269.79 | M58: =SUM($D$19:D58) -> 17472.92 | N58: =SUM($E$19:E58) -> 17203.13
A59: Buffer | B59: 42552 | C59: bank fee | D59: 10 | G59: t | H59: y | L59: =N59-M59 -> -279.79 | M59: =SUM($D$19:D59) -> 17482.92 | N59: =SUM($E$19:E59) -> 17203.13
A60: Buffer | B60: 42583 | C60: bank fee | D60: 9.9 | G60: t | H60: y | L60: =N60-M60 -> -289.69 | M60: =SUM($D$19:D60) -> 17492.82 | N60: =SUM($E$19:E60) -> 17203.13
A61: Buffer | B61: 42583 | C61: bank fee | D61: 10 | G61: t | H61: y | L61: =N61-M61 -> -299.69 | M61: =SUM($D$19:D61) -> 17502.82 | N61: =SUM($E$19:E61) -> 17203.13
A62: Buffer | B62: 42598 | C62: clal insurance? | D62: 50 | L62: =N62-M62 -> -349.69 | M62: =SUM($D$19:D62) -> 17552.82 | N62: =SUM($E$19:E62) -> 17203.13
A63: Buffer | B63: 42607 | C63: google fee | D63: 7.69 | H63: y | L63: =N63-M63 -> -357.38 | M63: =SUM($D$19:D63) -> 17560.51 | N63: =SUM($E$19:E63) -> 17203.13
A64: Buffer | B64: 42607 | C64: credit fee | D64: 13.9 | H64: y | L64: =N64-M64 -> -371.28 | M64: =SUM($D$19:D64) -> 17574.41 | N64: =SUM($E$19:E64) -> 17203.13
A65: Buffer | B65: 42614 | C65: bank fee | D65: 10 | G65: t | H65: y | L65: =N65-M65 -> -381.28 | M65: =SUM($D$19:D65) -> 17584.41 | N65: =SUM($E$19:E65) -> 17203.13
A66: Buffer | B66: 42614 | C66: car insuarnce | D66: 95 | H66: y | L66: =N66-M66 -> -476.28 | M66: =SUM($D$19:D66) -> 17679.41 | N66: =SUM($E$19:E66) -> 17203.13
A67: Buffer | B67: 42635 | C67: mattress delievry fisher | E67: 200 | H67: y | L67: =N67-M67 -> -276.28 | M67: =SUM($D$19:D67) -> 17679.41 | N67: =SUM($E$19:E67) -> 17403.13
A68: Buffer | B68: 42638 | C68: cc fee | D68: 13.9 | H68: y | L68: =N68-M68 -> -290.18 | M68: =SUM($D$19:D68) -> 17693.31 | N68: =SUM($E$19:E68) -> 17403.13
A69: Buffer | B69: 42644 | C69: car insurnace | D69: 95 | H69: y | L69: =N69-M69 -> -385.18 | M69: =SUM($D$19:D69) -> 17788.31 | N69: =SUM($E$19:E69) -> 17403.13
A70: Buffer | B70: 42645 | C70: bank fee | D70: 10 | G70: t | L70: =N70-M70 -> -395.18 | M70: =SUM($D$19:D70) -> 17798.31 | N70: =SUM($E$19:E70) -> 17403.13
A71: Buffer | B71: 42645 | C71: bank fee | D71: 18.15 | G71: t | L71: =N71-M71 -> -413.33 | M71: =SUM($D$19:D71) -> 17816.46 | N71: =SUM($E$19:E71) -> 17403.13
A72: Buffer | B72: 42668 | C72: cc fee | D72: 13.9 | H72: y | L72: =N72-M72 -> -427.23 | M72: =SUM($D$19:D72) -> 17830.36 | N72: =SUM($E$19:E72) -> 17403.13
A73: Buffer | B73: 42669 | C73: tim Edson | E73: 106.9 | L73: =N73-M73 -> -320.33 | M73: =SUM($D$19:D73) -> 17830.36 | N73: =SUM($E$19:E73) -> 17510.03
A74: Buffer | B74: 42675 | C74: bank fee | D74: 10 | G74: t | H74: y | L74: =N74-M74 -> -330.33 | M74: =SUM($D$19:D74) -> 17840.36 | N74: =SUM($E$19:E74) -> 17510.03
A75: Buffer | B75: 42675 | C75: car insurance | D75: 95 | H75: y | L75: =N75-M75 -> -425.33 | M75: =SUM($D$19:D75) -> 17935.36 | N75: =SUM($E$19:E75) -> 17510.03
A76: Buffer | B76: 42679 | C76: bank fee | D76: 11.32 | G76: t | H76: y | L76: =N76-M76 -> -436.65 | M76: =SUM($D$19:D76) -> 17946.68 | N76: =SUM($E$19:E76) -> 17510.03
A77: Buffer | B77: 42679 | C77: dropbox | D77: 377.38 | H77: y | L77: =N77-M77 -> -814.03 | M77: =SUM($D$19:D77) -> 18324.06 | N77: =SUM($E$19:E77) -> 17510.03
A78: Buffer | B78: 42700 | C78: cc fee | D78: 13.9 | H78: y | L78: =N78-M78 -> -827.93 | M78: =SUM($D$19:D78) -> 18337.96 | N78: =SUM($E$19:E78) -> 17510.03
A79: Buffer | B79: 42705 | C79: bank fee | D79: 10 | G79: t | H79: y | L79: =N79-M79 -> -837.93 | M79: =SUM($D$19:D79) -> 18347.96 | N79: =SUM($E$19:E79) -> 17510.03
A80: Buffer | B80: 42711 | C80: cash from esdon roof | E80: 280 | H80: y | L80: =N80-M80 -> -557.93 | M80: =SUM($D$19:D80) -> 18347.96 | N80: =SUM($E$19:E80) -> 17790.03
A81: Buffer | B81: 42736 | C81: car insurance | D81: 95 | H81: y | L81: =N81-M81 -> -652.93 | M81: =SUM($D$19:D81) -> 18442.96 | N81: =SUM($E$19:E81) -> 17790.03
A82: Buffer | B82: 42754 | C82: check book | D82: 17.64 | H82: y | L82: =N82-M82 -> -670.57 | M82: =SUM($D$19:D82) -> 18460.6 | N82: =SUM($E$19:E82) -> 17790.03
A83: Buffer | B83: 42760 | C83: cc fee | D83: 13.9 | H83: y | L83: =N83-M83 -> -684.47 | M83: =SUM($D$19:D83) -> 18474.5 | N83: =SUM($E$19:E83) -> 17790.03
A84: Buffer | B84: 42768 | C84: Handyman cohen | E84: 350 | H84: y | L84: =N84-M84 -> -334.47 | M84: =SUM($D$19:D84) -> 18474.5 | N84: =SUM($E$19:E84) -> 18140.03
A85: Buffer | B85: 42788 | C85: bed delivery kalan | E85: 50 | L85: =N85-M85 -> -284.47 | M85: =SUM($D$19:D85) -> 18474.5 | N85: =SUM($E$19:E85) -> 18190.03
A86: Buffer | B86: 42795 | C86: bank fee | D86: 1.65 | G86: t | H86: y | L86: =N86-M86 -> -286.12 | M86: =SUM($D$19:D86) -> 18476.15 | N86: =SUM($E$19:E86) -> 18190.03
A87: Buffer | B87: 42795 | C87: bank fee | D87: 10 | G87: t | H87: y | L87: =N87-M87 -> -296.12 | M87: =SUM($D$19:D87) -> 18486.15 | N87: =SUM($E$19:E87) -> 18190.03
A88: Buffer | B88: 42796 | C88: cleaner zach refunt | E88: 112 | L88: =N88-M88 -> -184.12 | M88: =SUM($D$19:D88) -> 18486.15 | N88: =SUM($E$19:E88) -> 18302.03
A89: Buffer | B89: 42803 | C89: supplies fishcer | E89: 53.9 | L89: =N89-M89 -> -130.22 | M89: =SUM($D$19:D89) -> 18486.15 | N89: =SUM($E$19:E89) -> 18355.93
A90: Buffer | B90: 42804 | C90: car insurance | D90: 95 | L90: =N90-M90 -> -225.22 | M90: =SUM($D$19:D90) -> 18581.15 | N90: =SUM($E$19:E90) -> 18355.93
A91: Buffer | B91: 42809 | C91: cleaning ben netanel | E91: 40 | L91: =N91-M91 -> -185.22 | M91: =SUM($D$19:D91) -> 18581.15 | N91: =SUM($E$19:E91) -> 18395.93
A92: Buffer | B92: 42816 | C92: toilet paper pollace | E92: 64 | L92: =N92-M92 -> -121.22 | M92: =SUM($D$19:D92) -> 18581.15 | N92: =SUM($E$19:E92) -> 18459.93
A93: Buffer | B93: 42819 | C93: cc fee | D93: 13.9 | L93: =N93-M93 -> -135.12 | M93: =SUM($D$19:D93) -> 18595.05 | N93: =SUM($E$19:E93) -> 18459.93
A94: Buffer | B94: 42819 | C94: hainey cleaning | E94: 160 | L94: =N94-M94 -> 24.88 | M94: =SUM($D$19:D94) -> 18595.05 | N94: =SUM($E$19:E94) -> 18619.93
A95: Buffer | B95: 42824 | C95: handy man fischer | E95: 50 | H95: y | L95: =N95-M95 -> 74.88 | M95: =SUM($D$19:D95) -> 18595.05 | N95: =SUM($E$19:E95) -> 18669.93
A96: Buffer | B96: 42825 | C96: ben window cleaning | E96: 40 | L96: =N96-M96 -> 114.88 | M96: =SUM($D$19:D96) -> 18595.05 | N96: =SUM($E$19:E96) -> 18709.93
A97: Buffer | B97: 42827 | C97: bank fee | D97: 10 | G97: t | H97: y | L97: =N97-M97 -> 104.88 | M97: =SUM($D$19:D97) -> 18605.05 | N97: =SUM($E$19:E97) -> 18709.93
A98: Buffer | B98: 42827 | C98: bank fee | D98: 14.85 | G98: t | H98: y | L98: =N98-M98 -> 90.03 | M98: =SUM($D$19:D98) -> 18619.9 | N98: =SUM($E$19:E98) -> 18709.93
A99: Buffer | B99: 42827 | C99: ben kashering pollac | E99: 100 | H99: y | L99: =N99-M99 -> 190.03 | M99: =SUM($D$19:D99) -> 18619.9 | N99: =SUM($E$19:E99) -> 18809.93
A100: Buffer | B100: 42832 | C100: ben kashering cohen | E100: 160 | L100: =N100-M100 -> 350.03 | M100: =SUM($D$19:D100) -> 18619.9 | N100: =SUM($E$19:E100) -> 18969.93
...

Sheet expenses
A1: Prop ID | B1: Date | C1: Type | D1: Amount | E1: Balance | F1: Method | G1: Company | H1: reciept | I1: return | J1: reported
A14: 618 | C14: Starting balance | E14: 5000
A15: 618 | B15: 42327 | C15: renovation | D15: -1680 | G15: שש תיקונים
A16: 618 | B16: 42328 | C16: key/mail lock | D16: -19
A17: 618 | B17: 42334 | C17: chip for building | D17: -25
A18: 618 | B18: 40876 | C18: cleaner | D18: -200
A19: 619 | B19: 42327 | C19: renovation | D19: -3120
A20: 619 | B20: 42328 | C20: cleaning supplies | D20: -13.5
A21: 619 | B21: 42328 | C21: Cleaner | D21: -400
A22: 619 | B22: 42328 | C22: cleaning supplies | D22: -84.7
A23: 619 | B23: 42335 | C23: key | D23: -19
A24: 619 | B24: 42337 | C24: Electrican | D24: -450
A25: 619 | B25: 42348 | C25: Finders fee | D25: -2047.5 | F25: transfer | G25: MIP | H25: 223
A26: 618 | B26: 42348 | C26: Finders fee | D26: -468 | F26: transfer | G26: MIP | H26: 223
A27: 618 | B27: 42348 | C27: management fee Oct | D27: -333.45 | F27: transfer | G27: MIP | H27: 223
A28: 619 | B28: 42348 | C28: management fee Oct | D28: -315.9 | F28: transfer | G28: MIP | H28: 223
A29: 801 | B29: 42348 | C29: management fee Oct- Dec | D29: -684.45 | F29: transfer | G29: MIP | H29: 223
A30: 618 | B30: 42348 | C30: management fee Dec | D30: -351 | F30: transfer | G30: MIP | H30: 223
A31: 619 | B31: 42348 | C31: management fee Dec | D31: -306.54 | F31: transfer | G31: MIP | H31: 223
A32: 618 | B32: 42353 | C32: fees | E32: 4507
A33: 618 | B33: 42353 | C33: prepaid expenses | E33: 3911.2 | F33: transfer | H33: 12
A34: 619 | C34: a/c | D34: -2800

Sheet bills
A1: Prop ID | B1: Date | C1: Type | D1: Amount | E1: Balance | F1: Method | G1: Company | H1: reciept
A2: 257 | B2: 42296 | C2: Pool July August sept | D2: 5499 | F2: Josaiah | G2: Maman Eyal | H2: 366 | I2: salt barmod and pump
A3: 257 | B3: 42354 | C3: Pool Oct, Nov | D3: 1404 | F3: Josaiah | G3: Maman Eyal
A4: 257 | B4: 42354 | C4: Mazger electic gate and driveway phone | D4: 4563 | F4: Josaiah | G4: Tal Matechet
A5: 257 | C5: glass work | D5: 18206 | F5: Josaiah | G5: נחמני מוטי | I5: glass work for pool bathroom kids bathrom, fence around jacuzzi and mirror
A6: 257 | B6: 42367 | C6: cleaning | D6: 1111.5 | F6: Josaiah | G6: ניקיון אחר
A7: 257 | B7: 42380 | C7: pool dec- pool pump | D7: 2106 | F7: Josaiah | G7: Maman Eyal

Sheet OldBuffer
A1: Prop ID | B1: Date | C1: Date | D1: Type | E1: Amount | F1: Inflow | G1: Method | H1: Reconciled | I1: Company | J1: reciept | K1: Returned
B2: 42339 | C2: 42339 | D2: car insuance | E2: 95 | H2: y
B3: 42390 | C3: 42390 | D3: Kvish 6 | E3: 252.64 | G3: credit
B4: 42401 | C4: 42401 | D4: bank fee | E4: 10 | G4: bank fee | H4: y
B5: 42417 | C5: 42417 | D5: credit fee | E5: 1.52 | G5: credit
B6: 42417 | C6: 42417 | D6: efax | E6: 52.05 | G6: credit | H6: y
B7: 42425 | C7: 42425 | D7: fees | E7: 1.82 | G7: credit
B8: 42425 | C8: 42425 | D8: google storage | E8: 7.77 | G8: credit | H8: y
B9: 42425 | C9: 42425 | D9: credot fee | E9: 13.9 | G9: credit | H9: y
B10: 42430 | C10: 42430 | D10: bank fee | E10: 10 | G10: bank | H10: y
B11: 42436 | C11: 42436 | D11: clothes | E11: 189.9 | G11: credit | H11: y
B12: 42436 | C12: 42436 | D12: clothes | E12: 57 | G12: credit | H12: y
B13: 42436 | C13: 42436 | D13: clothes | E13: 259 | G13: credit | H13: y
B14: 42437 | C14: 42437 | D14: efax | F14: 98.13 | G14: credit | H14: y
B15: 42438 | C15: 42438 | D15: payment hockstien | F15: 4713 | G15: transfer | H15: y
B16: 42439 | C16: 42439 | D16: payment hockstien | E16: 4713 | G16: transfer | H16: y
B17: 42443 | C17: 42443 | D17: Sandi payment | F17: 10000
B18: 42454 | C18: 42454 | D18: foreign excahge | E18: 1.78 | G18: credit fee | H18: y
B19: 42454 | C19: 42454 | D19: google storage | E19: 7.63 | G19: credit | H19: y
B20: 42455 | C20: 42455 | D20: credit fee | E20: 13.9 | G20: credit | H20: y
B21: 42461 | C21: 42461 | D21: bank fee | E21: 3.3 | G21: bank fee | H21: y
B22: 42461 | C22: 42461 | D22: bank fee | E22: 10
B23: 42465 | C23: 42465 | D23: transfer to Leumi | E23: 10000 | H23: y
B24: 42486 | C24: 42486 | D24: credit card fee | E24: 13.9 | H24: y
B25: 42486 | C25: 42486 | D25: google storage | E25: 7.7 | H25: y
B26: 42491 | C26: 42491 | D26: bank fee | E26: 4.95 | H26: y
B27: 42492 | C27: 42492 | D27: bank fee | E27: 10 | H27: y
B28: 42508 | C28: 42508 | D28: home center? | E28: 90 | H28: y
B29: 42516 | C29: 42516 | D29: currency transfer fee | E29: 1.78 | H29: y
B30: 42516 | C30: 42516 | D30: credit card fee | E30: 13.9 | H30: y
B31: 42516 | C31: 42516 | D31: google storage | E31: 7.63 | H31: y
B32: 42522 | C32: 42522 | D32: Start | E32: 0 | F32: 2392
B33: 42522 | C33: 42522 | D33: bank fee | E33: 10 | H33: y
B34: 42523 | C34: 42523 | D34: Adjustment | E34: 18.21
B35: 42532 | C35: 42532 | D35: bekek | E35: 38.9 | H35: y
B36: 42533 | C36: 42533 | D36: took out cash of 1300 to cover cash expenses of 479, 120,180, | E36: 1300
B37: 42536 | C37: 42536 | D37: cash for clients | E37: 200 | H37: y
B38: 42546 | C38: 42546 | D38: credit fee | E38: 13.9 | H38: y
B39: 42546 | C39: 42546 | D39: google storage | E39: 7.94 | H39: y
B40: 42548 | C40: 42548 | D40: bank fee | E40: 24 | H40: y
B41: 42552 | C41: 42552 | D41: bank fee | E41: 10 | H41: y
B42: 42552 | C42: 42552 | D42: bank fee | E42: 9.9 | H42: y
B43: 42583 | C43: 42583 | D43: bank fee | E43: 9.9 | H43: y
B44: 42583 | C44: 42583 | D44: bank fee | E44: 10 | H44: y
B45: 42598 | C45: 42598 | D45: clal insurance? | E45: 50
B46: 42607 | C46: 42607 | D46: credit fee | E46: 13.9 | H46: y
B47: 42607 | C47: 42607 | D47: google fee | E47: 7.69 | H47: y
B48: 42614 | C48: 42614 | D48: bank fee | E48: 10 | H48: y
B49: 42614 | C49: 42614 | D49: car insuarnce | E49: 95 | H49: y
B50: 42635 | C50: 42635 | D50: mattress delievry fisher | F50: 200 | H50: y
B51: 42638 | C51: 42638 | D51: cc fee | E51: 13.9 | H51: y
B52: 42644 | C52: 42644 | D52: car insurnace | E52: 95 | H52: y
B53: 42645 | C53: 42645 | D53: bank fee | E53: 18.15
B54: 42645 | C54: 42645 | D54: bank fee | E54: 10
B55: 42668 | C55: 42668 | D55: cc fee | E55: 13.9 | H55: y
B56: 42669 | C56: 42669 | D56: tim Edson | F56: 106.9
B57: 42675 | C57: 42675 | D57: bank fee | E57: 10 | H57: y
B58: 42675 | C58: 42675 | D58: car insuranc | E58: 95 | H58: y
B59: 42679 | C59: 42679 | D59: dropbox | E59: 377.38 | H59: y
B60: 42679 | C60: 42679 | D60: bank fee | E60: 11.32 | H60: y
B61: 42700 | C61: 42700 | D61: cc fee | E61: 13.9 | H61: y
B62: 42705 | C62: 42705 | D62: bank fee | E62: 10 | H62: y
B63: 42711 | C63: 42711 | D63: cash from esdon roof | F63: 280 | H63: y
B64: 42736 | C64: 42736 | D64: car insuance | E64: 95 | H64: y
B65: 42754 | C65: 42754 | D65: check book | E65: 17.64 | H65: y
B66: 42760 | C66: 42760 | D66: cc fee | E66: 13.9 | H66: y
B67: 42768 | C67: 42768 | D67: handyman cohen | F67: 350 | H67: y
B68: 42788 | C68: 42788 | D68: bed delivery kalan | F68: 50
B69: 42795 | C69: 42795 | D69: bank fee | E69: 1.65 | H69: y
B70: 42795 | C70: 42795 | D70: bank fee | E70: 10 | H70: y
B71: 42796 | C71: 42796 | D71: cleaner zach refunt | F71: 112
B72: 42804 | C72: 42804 | D72: car insurance | E72: 95
B73: 42803 | C73: 42803 | D73: supplies fishcer | F73: 53.9
B74: 42809 | C74: 42809 | D74: cleaning ben netanel | F74: 40
B75: 42816 | C75: 42816 | D75: toilet paper pollace | F75: 64
B76: 42819 | C76: 42819 | D76: hainey cleaning | F76: 160
B77: 42819 | C77: 42819 | D77: cc fee | E77: 13.9
B78: 42824 | C78: 42824 | D78: handy man fischer | F78: 50 | H78: y
B79: 42825 | C79: 42825 | D79: ben window cleaning | F79: 40
B80: 42827 | C80: 42827 | D80: ben kashering pollac | F80: 100 | H80: y
B81: 42827 | C81: 42827 | D81: bank fee | E81: 14.85 | H81: y
B82: 42827 | C82: 42827 | D82: bank fee | E82: 10 | H82: y
B83: 42835 | C83: 42835 | D83: car insurance | E83: 95
B84: 42832 | C84: 42832 | D84: ben kashering cohen | F84: 160
B85: 42856 | C85: 42856 | D85: bank fee | E85: 10 | H85: y
B86: 42860 | C86: 42860 | D86: Ilan cleaning | F86: 120 | H86: y
B87: 42865 | C87: 42865 | D87: car insurance | E87: 95
B88: 42862 | C88: 42862 | D88: yehuda moving | F88: 140 | H88: y
B89: 42871 | C89: 42871 | D89: yehuda weeds | F89: 60 | H89: y
B90: 42872 | C90: 42872 | D90: cash return of 5 to lissac and jacobson | E90: 10
B91: 42880 | C91: 42880 | D91: cc fee | E91: 13.9 | H91: y
B92: 42883 | C92: 42883 | D92: took cash of 1008 electric cohen | E92: 1008 | H92: y
B93: 42887 | C93: 42887 | D93: bank fee | E93: 14.85 | H93: y
B94: 42887 | C94: 42887 | D94: bank fee | E94: 10 | H94: y
B95: 42897 | C95: 42897 | D95: car insurance | E95: 95 | H95: y
B96: 42911 | C96: 42911 | D96: cc fee | E96: 13.9 | H96: y
B97: 42918 | C97: 42918 | D97: bank fee | E97: 10 | H97: y
B98: 42919 | C98: 42919 | D98: water silver | F98: 215.2
B99: 42926 | C99: 42926 | D99: car insurance | E99: 95 | H99: y
B100: 42941 | C100: 42941 | D100: cc fee | E100: 13.9 | H100: y
...

Sheet 03 EX
A1: Prop ID | B1: Date | C1: Section | D1: Notes | E1: Type | F1: Amount | G1: Inflow | H1: He/She paid | I1: Method | J1: Reconciled | K1: Company | L1: Reciept | M1: Rental income | N1: Reported | O1: Report sent | P1: Balance | Q1: Total Amount | R1: Total Inflow
A2: 03 | B2: 42471 | C2: Pre paid expenses | G2: 1200 | J2: y | N2: Y | P2: =R2-Q2 -> 1200 | Q2: =SUM($F$2:F2) -> 0 | R2: =SUM($G$2:G2) -> 1200
A3: 03 | B3: 42473 | C3: locksmith | F3: 395 | I3: check | J3: y | K3: Chaim Manuilim | L3: 8307 | N3: Y | P3: =R3-Q3 -> 805 | Q3: =SUM($F$2:F3) -> 395 | R3: =SUM($G$2:G3) -> 1200
A4: 03 | B4: 42495 | C4: Arnona | F4: 140.3 | I4: credit | J4: y | K4: Moatza | L4: 1213584 | N4: Y | P4: =R4-Q4 -> 664.7 | Q4: =SUM($F$2:F4) -> 535.3 | R4: =SUM($G$2:G4) -> 1200
A5: 03 | B5: 42523 | C5: cleaning | F5: 702 | I5: transfer | J5: y | L5: 283 | N5: Y | P5: =R5-Q5 -> -37.3 | Q5: =SUM($F$2:F5) -> 1237.3 | R5: =SUM($G$2:G5) -> 1200
A6: 03 | B6: 42551 | C6: laundry | F6: 195 | I6: credit | J6: y | K6: סל כביסה | L6: 291 | N6: Y | P6: =R6-Q6 -> -232.3 | Q6: =SUM($F$2:F6) -> 1432.3 | R6: =SUM($G$2:G6) -> 1200
A7: 03 | B7: 42565 | C7: Pre paid expenses | G7: 8283.1 | I7: transfer | J7: y | N7: Y | P7: =R7-Q7 -> 8050.8 | Q7: =SUM($F$2:F7) -> 1432.3 | R7: =SUM($G$2:G7) -> 9483.1
A8: 03 | B8: 42569 | C8: Gardener - Graham | F8: 3140 | I8: transfer | J8: y | K8: Graham Eskin | L8: 80 | N8: Y | P8: =R8-Q8 -> 4910.8 | Q8: =SUM($F$2:F8) -> 4572.3 | R8: =SUM($G$2:G8) -> 9483.1
A9: 03 | B9: 42578 | C9: Exterminator | F9: 400 | I9: transfer | J9: y | K9: עדי מזרחי | L9: 1839 | N9: Y | P9: =R9-Q9 -> 4510.8 | Q9: =SUM($F$2:F9) -> 4972.3 | R9: =SUM($G$2:G9) -> 9483.1
A10: 03 | B10: 42584 | C10: pre paid expenses | G10: 6696 | I10: cash | N10: Y | P10: =R10-Q10 -> 11206.8 | Q10: =SUM($F$2:F10) -> 4972.3 | R10: =SUM($G$2:G10) -> 16179.1
A11: 03 | B11: 42619 | C11: cleaning | F11: 3510 | I11: transfer | J11: y | K11: ניקיון אחר | L11: 337 | N11: Y | P11: =R11-Q11 -> 7696.8 | Q11: =SUM($F$2:F11) -> 8482.3 | R11: =SUM($G$2:G11) -> 16179.1
A12: 03 | B12: 42635 | C12: gardener !/2 may, june, july and august plus parts | F12: 1738 | I12: transfer | J12: y | K12: Graham Eskin | L12: 92 | N12: Y | P12: =R12-Q12 -> 5958.8 | Q12: =SUM($F$2:F12) -> 10220.3 | R12: =SUM($G$2:G12) -> 16179.1
A13: 03 | B13: 42643 | C13: water 14-6-16 till 15-8-16 | H13: 758.85 | J13: y | K13: tagid mayanot | L13: 1178078 | N13: Y | P13: =R13-Q13 -> 5958.8 | Q13: =SUM($F$2:F13) -> 10220.3 | R13: =SUM($G$2:G13) -> 16179.1
A14: 03 | B14: 42648 | C14: cleaning 30-9-16 | F14: 702 | I14: transfer | J14: y | K14: ניקיון אחר | L14: 364 | N14: Y | P14: =R14-Q14 -> 5256.8 | Q14: =SUM($F$2:F14) -> 10922.3 | R14: =SUM($G$2:G14) -> 16179.1
A15: 03 | B15: 42675 | C15: Cleaning supplies | F15: 38.5 | I15: credit | J15: y | K15: super habaron | L15: 87930 | N15: Y | P15: =R15-Q15 -> 5218.3 | Q15: =SUM($F$2:F15) -> 10960.8 | R15: =SUM($G$2:G15) -> 16179.1
A16: 03 | B16: 42687 | C16: cleaning 2-11-16 | F16: 702 | I16: transfer | J16: y | K16: ניקיון אחר | L16: 414 | N16: Y | P16: =R16-Q16 -> 4516.3 | Q16: =SUM($F$2:F16) -> 11662.8 | R16: =SUM($G$2:G16) -> 16179.1
A17: 03 | B17: 42688 | C17: Pre paid expenses | G17: 3056 | I17: cash | J17: y | L17: 65 | N17: Y | P17: =R17-Q17 -> 7572.3 | Q17: =SUM($F$2:F17) -> 11662.8 | R17: =SUM($G$2:G17) -> 19235.1
A18: 03 | B18: 42725 | C18: Cleaning supplies | F18: 12.9 | I18: credit | J18: y | K18: sefa habaron | L18: 94320 | N18: Y | P18: =R18-Q18 -> 7559.4 | Q18: =SUM($F$2:F18) -> 11675.7 | R18: =SUM($G$2:G18) -> 19235.1
A19: 03 | B19: 42726 | C19: Pre paid expenses | G19: 6130.02 | I19: tranfer | J19: y | K19: Sandi Ryker | L19: 295 | N19: Y | P19: =R19-Q19 -> 13689.42 | Q19: =SUM($F$2:F19) -> 11675.7 | R19: =SUM($G$2:G19) -> 25365.12
A20: 03 | B20: 42736 | C20: Sandi payment | F20: 7120 | I20: transfer | J20: y | L20: 295/296 | N20: Y | P20: =R20-Q20 -> 6569.42 | Q20: =SUM($F$2:F20) -> 18795.7 | R20: =SUM($G$2:G20) -> 25365.12
A21: 03 | B21: 42737 | C21: management fee- | F21: 3510 | I21: transfer | J21: y | K21: MIP | L21: 302 | N21: Y | P21: =R21-Q21 -> 3059.42 | Q21: =SUM($F$2:F21) -> 22305.7 | R21: =SUM($G$2:G21) -> 25365.12
A22: 03 | B22: 42738 | C22: roof | F22: 585 | I22: transfer | J22: y | K22: michelle | N22: Y | P22: =R22-Q22 -> 2474.42 | Q22: =SUM($F$2:F22) -> 22890.7 | R22: =SUM($G$2:G22) -> 25365.12
A23: 03 | B23: 42738 | C23: shower head | F23: 160 | I23: cc | K23: ronis | N23: Y | P23: =R23-Q23 -> 2314.42 | Q23: =SUM($F$2:F23) -> 23050.7 | R23: =SUM($G$2:G23) -> 25365.12
A24: 03 | B24: 42799 | C24: gardener sept- jan | F24: 3978 | I24: transfer | J24: y | K24: Graham Eskin | L24: 94 | N24: Y | P24: =R24-Q24 -> -1663.58 | Q24: =SUM($F$2:F24) -> 27028.7 | R24: =SUM($G$2:G24) -> 25365.12
A25: 03 | B25: 42801 | C25: cleaning | F25: 702 | I25: transfer | J25: y | K25: Nikayon acher | L25: 503 | N25: Y | P25: =R25-Q25 -> -2365.58 | Q25: =SUM($F$2:F25) -> 27730.7 | R25: =SUM($G$2:G25) -> 25365.12
A26: 03 | B26: 42821 | C26: Pre paid expenses | G26: 4000 | I26: 5000396 | J26: y | K26: MIP | L26: 83 | N26: Y | P26: =R26-Q26 -> 1634.42 | Q26: =SUM($F$2:F26) -> 27730.7 | R26: =SUM($G$2:G26) -> 29365.12
A27: 03 | B27: 42825 | C27: window | F27: 40 | I27: cash | J27: y | K27: ben | L27: no | N27: Y | P27: =R27-Q27 -> 1594.42 | Q27: =SUM($F$2:F27) -> 27770.7 | R27: =SUM($G$2:G27) -> 29365.12
A28: 03 | B28: 42859 | C28: cleaning 31-3 | F28: 702 | I28: transfer | J28: y | K28: Nikayon acher | L28: 528 | N28: Y | P28: =R28-Q28 -> 892.42 | Q28: =SUM($F$2:F28) -> 28472.7 | R28: =SUM($G$2:G28) -> 29365.12
A29: 03 | B29: 42859 | C29: cleaning 25-4-17 | F29: 702 | I29: transfer | J29: y | K29: Nikayon acher | L29: 531 | N29: Y | P29: =R29-Q29 -> 190.42 | Q29: =SUM($F$2:F29) -> 29174.7 | R29: =SUM($G$2:G29) -> 29365.12
A30: 03 | B30: 42872 | C30: pre paid expenses | G30: 712 | J30: y | N30: Y | P30: =R30-Q30 -> 902.42 | Q30: =SUM($F$2:F30) -> 29174.7 | R30: =SUM($G$2:G30) -> 30077.12
A31: 03 | B31: 42874 | C31: Plumber | F31: 351 | J31: y | L31: 70 | N31: Y | P31: =R31-Q31 -> 551.42 | Q31: =SUM($F$2:F31) -> 29525.7 | R31: =SUM($G$2:G31) -> 30077.12
A32: 03 | B32: 42877 | C32: shower head | F32: 269 | I32: cc | J32: y | K32: Ronis | L32: RC179000470 | N32: Y | P32: =R32-Q32 -> 282.42 | Q32: =SUM($F$2:F32) -> 29794.7 | R32: =SUM($G$2:G32) -> 30077.12
A33: 03 | B33: 42877 | C33: Pre paid expenses | G33: 10552.89 | I33: tramsfer | J33: y | K33: MIP | L33: 89 | N33: Y | P33: =R33-Q33 -> 10835.31 | Q33: =SUM($F$2:F33) -> 29794.7 | R33: =SUM($G$2:G33) -> 40630.01
A34: 03 | B34: 42878 | C34: management fee- | F34: 3510 | I34: transfer | J34: y | K34: MIP | L34: 320 | N34: Y | P34: =R34-Q34 -> 7325.31 | Q34: =SUM($F$2:F34) -> 33304.7 | R34: =SUM($G$2:G34) -> 40630.01
A35: 03 | B35: 42878 | C35: Gardener | F35: 4092 | I35: transfer | J35: y | K35: Graham | L35: 97 | N35: Y | P35: =R35-Q35 -> 3233.31 | Q35: =SUM($F$2:F35) -> 37396.7 | R35: =SUM($G$2:G35) -> 40630.01
A36: 03 | B36: 42885 | C36: water 03-04 | H36: 117.92 | N36: Y | P36: =R36-Q36 -> 3233.31 | Q36: =SUM($F$2:F36) -> 37396.7 | R36: =SUM($G$2:G36) -> 40630.01
A37: 03 | B37: 42908 | C37: milk | F37: 6.8 | I37: cc | J37: y | K37: super shefa habaron | N37: Y | P37: =R37-Q37 -> 3226.51 | Q37: =SUM($F$2:F37) -> 37403.5 | R37: =SUM($G$2:G37) -> 40630.01
A38: 03 | B38: 42928 | C38: Cleaning 22-6-17 | F38: 702 | I38: transfer | J38: y | K38: nikayon acher | L38: 571 | N38: Y | P38: =R38-Q38 -> 2524.51 | Q38: =SUM($F$2:F38) -> 38105.5 | R38: =SUM($G$2:G38) -> 40630.01
A39: 03 | B39: 42933 | C39: wall repairs | F39: 750 | I39: transfer | J39: y | K39: chaim dasa | N39: Y | P39: =R39-Q39 -> 1774.51 | Q39: =SUM($F$2:F39) -> 38855.5 | R39: =SUM($G$2:G39) -> 40630.01
A40: 03 | B40: 42934 | C40: shower head | F40: 269 | I40: cc | J40: y | K40: Ronis | L40: Rc179000690 | N40: Y | P40: =R40-Q40 -> 1505.51 | Q40: =SUM($F$2:F40) -> 39124.5 | R40: =SUM($G$2:G40) -> 40630.01
A41: 03 | B41: 42941 | C41: parking ticket | F41: 100 | I41: cc | J41: y | L41: 82695- | N41: Y | P41: =R41-Q41 -> 1405.51 | Q41: =SUM($F$2:F41) -> 39224.5 | R41: =SUM($G$2:G41) -> 40630.01
A42: 03 | B42: 42941 | C42: Pre paid expenses | H42: =3530+550 -> 4080 | J42: y | L42: 96 | N42: Y | P42: =R42-Q42 -> 1405.51 | Q42: =SUM($F$2:F42) -> 39224.5 | R42: =SUM($G$2:G42) -> 40630.01
A43: 03 | B43: 42941 | C43: management fee- | H43: 3510 | J43: y | K43: MIP | L43: 337 | N43: Y | P43: =R43-Q43 -> 1405.51 | Q43: =SUM($F$2:F43) -> 39224.5 | R43: =SUM($G$2:G43) -> 40630.01
A44: 03 | B44: 42949 | C44: gardener april-june | F44: 2544 | J44: y | K44: graham | L44: 98 | N44: Y | P44: =R44-Q44 -> -1138.49 | Q44: =SUM($F$2:F44) -> 41768.5 | R44: =SUM($G$2:G44) -> 40630.01
A45: 03 | B45: 42972 | C45: supersol | F45: 33.91 | J45: y | L45: 2142003117406 | N45: Y | P45: =R45-Q45 -> -1172.4 | Q45: =SUM($F$2:F45) -> 41802.41 | R45: =SUM($G$2:G45) -> 40630.01
A46: 03 | B46: 42983 | C46: mamad winsow | H46: 200 | J46: y | K46: tris cohen | L46: no | N46: Y | P46: =R46-Q46 -> -1172.4 | Q46: =SUM($F$2:F46) -> 41802.41 | R46: =SUM($G$2:G46) -> 40630.01
A47: 03 | B47: 42989 | C47: ar 09-10 | H47: 1714.2 | J47: y | N47: Y | P47: =R47-Q47 -> -1172.4 | Q47: =SUM($F$2:F47) -> 41802.41 | R47: =SUM($G$2:G47) -> 40630.01
A48: 03 | B48: 43033 | C48: gardner July - Spet | F48: 1228 | J48: y | K48: graham | L48: 13 | N48: Y | P48: =R48-Q48 -> -2400.4 | Q48: =SUM($F$2:F48) -> 43030.41 | R48: =SUM($G$2:G48) -> 40630.01
A49: 03 | B49: 43040 | C49: cleaning | F49: 270 | I49: transer | J49: y | K49: 3 | N49: Y | P49: =R49-Q49 -> -2670.4 | Q49: =SUM($F$2:F49) -> 43300.41 | R49: =SUM($G$2:G49) -> 40630.01
A50: 03 | B50: 43040 | C50: cleaning BL | F50: 19 | J50: y | N50: Y | P50: =R50-Q50 -> -2689.4 | Q50: =SUM($F$2:F50) -> 43319.41 | R50: =SUM($G$2:G50) -> 40630.01
A51: 03 | B51: 43044 | C51: soloar | F51: 1225 | J51: y | K51: יי אנרגיה | L51: 1001003 | N51: Y | P51: =R51-Q51 -> -3914.4 | Q51: =SUM($F$2:F51) -> 44544.41 | R51: =SUM($G$2:G51) -> 40630.01
A52: 03 | B52: 43047 | C52: heater tipul | F52: 1380 | I52: 5000108 | J52: y | K52: זידאני הסקות | L52: 1626 | N52: Y | P52: =R52-Q52 -> -5294.4 | Q52: =SUM($F$2:F52) -> 45924.41 | R52: =SUM($G$2:G52) -> 40630.01
A53: 03 | B53: 43059 | C53: Pre paid expenses | G53: 10348.58 | I53: transfer | J53: y | K53: sandi | L53: 124 | N53: Y | P53: =R53-Q53 -> 5054.18 | Q53: =SUM($F$2:F53) -> 45924.41 | R53: =SUM($G$2:G53) -> 50978.59
A54: 03 | B54: 43074 | C54: cleaning | F54: 640 | I54: transer | J54: y | K54: elena | N54: Y | P54: =R54-Q54 -> 4414.18 | Q54: =SUM($F$2:F54) -> 46564.41 | R54: =SUM($G$2:G54) -> 50978.59
A55: 03 | B55: 43074 | C55: bituach leumi cleaning | F55: 44.8 | J55: y | K55: bituach leumi | N55: Y | P55: =R55-Q55 -> 4369.38 | Q55: =SUM($F$2:F55) -> 46609.21 | R55: =SUM($G$2:G55) -> 50978.59
A56: 03 | B56: 43074 | C56: a/c repair and remote | F56: 800 | I56: transer | J56: y | K56: yosi ben adiva | N56: Y | P56: =R56-Q56 -> 3569.38 | Q56: =SUM($F$2:F56) -> 47409.21 | R56: =SUM($G$2:G56) -> 50978.59
A57: 03 | B57: 43083 | C57: cleaning | F57: 320 | N57: Y | P57: =R57-Q57 -> 3249.38 | Q57: =SUM($F$2:F57) -> 47729.21 | R57: =SUM($G$2:G57) -> 50978.59
A58: 03 | B58: 43096 | C58: workon the attic | H58: 4000 | J58: y | K58: Ido levi | N58: Y | P58: =R58-Q58 -> 3249.38 | Q58: =SUM($F$2:F58) -> 47729.21 | R58: =SUM($G$2:G58) -> 50978.59
A59: 03 | B59: 43096 | C59: workon the attic | F59: 2580 | I59: transfer | J59: y | K59: Ido levi | N59: Y | P59: =R59-Q59 -> 669.38 | Q59: =SUM($F$2:F59) -> 50309.21 | R59: =SUM($G$2:G59) -> 50978.59
A60: 03 | B60: 43098 | C60: cleaning | F60: 220 | K60: elena | N60: Y | P60: =R60-Q60 -> 449.38 | Q60: =SUM($F$2:F60) -> 50529.21 | R60: =SUM($G$2:G60) -> 50978.59
A61: 03 | B61: 43101 | C61: bituach leumi cleaning | F61: 37.6 | J61: y | N61: Y | P61: =R61-Q61 -> 411.78 | Q61: =SUM($F$2:F61) -> 50566.81 | R61: =SUM($G$2:G61) -> 50978.59
A62: 03 | B62: 43101 | C62: Cleaning supplies | F62: 211.7 | I62: cc | J62: y | K62: mega | N62: Y | P62: =R62-Q62 -> 200.08 | Q62: =SUM($F$2:F62) -> 50778.51 | R62: =SUM($G$2:G62) -> 50978.59
A63: 03 | B63: 43109 | C63: electric | H63: 842.37 | J63: y | N63: Y | P63: =R63-Q63 -> 200.08 | Q63: =SUM($F$2:F63) -> 50778.51 | R63: =SUM($G$2:G63) -> 50978.59
A64: 03 | B64: 43123 | C64: Arnona | H64: 1881.4 | J64: y | N64: Y | P64: =R64-Q64 -> 200.08 | Q64: =SUM($F$2:F64) -> 50778.51 | R64: =SUM($G$2:G64) -> 50978.59
A65: 03 | B65: 43130 | C65: Pre paid expenses | G65: 8400 | I65: deposit | J65: y | L65: 143 | N65: Y | P65: =R65-Q65 -> 8600.08 | Q65: =SUM($F$2:F65) -> 50778.51 | R65: =SUM($G$2:G65) -> 59378.59
A66: 03 | B66: 43130 | C66: management fee- | F66: 3510 | I66: transfer | J66: y | K66: sandi | L66: 384 | N66: Y | P66: =R66-Q66 -> 5090.08 | Q66: =SUM($F$2:F66) -> 54288.51 | R66: =SUM($G$2:G66) -> 59378.59
A67: 03 | B67: 43130 | C67: Gardener | F67: 2527 | I67: transfer | J67: y | K67: graham | L67: 22 | N67: Y | P67: =R67-Q67 -> 2563.08 | Q67: =SUM($F$2:F67) -> 56815.51 | R67: =SUM($G$2:G67) -> 59378.59
A68: 03 | B68: 43137 | C68: cleaner Jan | F68: 1080 | I68: transfer | J68: y | K68: elena | N68: Y | P68: =R68-Q68 -> 1483.08 | Q68: =SUM($F$2:F68) -> 57895.51 | R68: =SUM($G$2:G68) -> 59378.59
A69: 03 | B69: 43137 | C69: bituach leumi cleaning | F69: 75.6 | I69: transfer | J69: y | N69: Y | P69: =R69-Q69 -> 1407.48 | Q69: =SUM($F$2:F69) -> 57971.11 | R69: =SUM($G$2:G69) -> 59378.59
A70: 03 | B70: 43139 | C70: microwave | F70: 690 | I70: cc | J70: y | K70: Pr elect | N70: Y | P70: =R70-Q70 -> 717.48 | Q70: =SUM($F$2:F70) -> 58661.11 | R70: =SUM($G$2:G70) -> 59378.59
A71: 03 | B71: 43150 | C71: Plumber | F71: 315 | I71: transfer | J71: y | K71: samir | L71: 122 | N71: Y | P71: =R71-Q71 -> 402.48 | Q71: =SUM($F$2:F71) -> 58976.11 | R71: =SUM($G$2:G71) -> 59378.59
A72: 03 | B72: 43156 | C72: electric oct-Jan 18 | H72: 379.83 | J72: y | K72: chevrat chasmal | L72: 341563267 | N72: Y | P72: =R72-Q72 -> 402.48 | Q72: =SUM($F$2:F72) -> 58976.11 | R72: =SUM($G$2:G72) -> 59378.59
A73: 03 | B73: 43165 | C73: water /11/- Dec 17 | F73: 412 | I73: cc | J73: y | K73: tagid maysnoy | L73: 5757 | N73: Y | P73: =R73-Q73 -> -9.52 | Q73: =SUM($F$2:F73) -> 59388.11 | R73: =SUM($G$2:G73) -> 59378.59
A74: 03 | B74: 43165 | C74: gardne 1-2/2018 | F74: 1450 | I74: transfer | J74: y | K74: graham | L74: 29 | N74: Y | P74: =R74-Q74 -> -1459.52 | Q74: =SUM($F$2:F74) -> 60838.11 | R74: =SUM($G$2:G74) -> 59378.59
A75: 03 | B75: 43166 | C75: arnona /11/ -dec 18 | F75: 1964.8 | I75: cc | J75: y | K75: moatza zichron | N75: Y | P75: =R75-Q75 -> -3424.32 | Q75: =SUM($F$2:F75) -> 62802.91 | R75: =SUM($G$2:G75) -> 59378.59
A76: 03 | B76: 43169 | C76: cleaning | F76: 1060 | J76: y | K76: elena | N76: Y | P76: =R76-Q76 -> -4484.32 | Q76: =SUM($F$2:F76) -> 63862.91 | R76: =SUM($G$2:G76) -> 59378.59
A77: 03 | B77: 43169 | C77: cleaning-ביטוח לאומי | F77: 74.2 | J77: y | K77: elena | N77: Y | P77: =R77-Q77 -> -4558.52 | Q77: =SUM($F$2:F77) -> 63937.11 | R77: =SUM($G$2:G77) -> 59378.59
A78: 03 | B78: 43171 | C78: arnonan March- april | H78: 1816.3 | J78: y | K78: maotza | L78: 1401000 | N78: Y | P78: =R78-Q78 -> -4558.52 | Q78: =SUM($F$2:F78) -> 63937.11 | R78: =SUM($G$2:G78) -> 59378.59
A79: 03 | B79: 43172 | C79: water filter | F79: 1300 | J79: y | N79: Y | P79: =R79-Q79 -> -5858.52 | Q79: =SUM($F$2:F79) -> 65237.11 | R79: =SUM($G$2:G79) -> 59378.59
A80: 03 | B80: 43177 | C80: Pre paid expenses | G80: 2950 | I80: deposit | J80: y | L80: 160 | N80: Y | P80: =R80-Q80 -> -2908.52 | Q80: =SUM($F$2:F80) -> 65237.11 | R80: =SUM($G$2:G80) -> 62328.59
A81: 03 | B81: 43189 | C81: water Jan March 18 | H81: 546.41 | J81: y | N81: Y | P81: =R81-Q81 -> -2908.52 | Q81: =SUM($F$2:F81) -> 65237.11 | R81: =SUM($G$2:G81) -> 62328.59
A82: 03 | B82: 43191 | C82: cleaner March 1, 6 and 15th | F82: 960 | J82: y | K82: elena | N82: Y | P82: =R82-Q82 -> -3868.52 | Q82: =SUM($F$2:F82) -> 66197.11 | R82: =SUM($G$2:G82) -> 62328.59
A83: 03 | B83: 43191 | C83: bituach leumi cleaning | F83: 68.67 | J83: y | N83: Y | P83: =R83-Q83 -> -3937.19 | Q83: =SUM($F$2:F83) -> 66265.78 | R83: =SUM($G$2:G83) -> 62328.59
A84: 03 | B84: 43202 | C84: a/c remote 3 | F84: 600 | I84: transfer | J84: y | K84: yosi ben adiva | N84: Y | P84: =R84-Q84 -> -4537.19 | Q84: =SUM($F$2:F84) -> 66865.78 | R84: =SUM($G$2:G84) -> 62328.59
A85: 03 | B85: 43208 | C85: Pre paid expenses | G85: 6970 | I85: deposit | J85: y | K85: sandi | L85: 172 | N85: Y | P85: =R85-Q85 -> 2432.81 | Q85: =SUM($F$2:F85) -> 66865.78 | R85: =SUM($G$2:G85) -> 69298.59
A86: 03 | B86: 43212 | C86: Pre paid expenses | G86: 1050 | J86: y | L86: 176 | N86: Y | P86: =R86-Q86 -> 3482.81 | Q86: =SUM($F$2:F86) -> 66865.78 | R86: =SUM($G$2:G86) -> 70348.59
A87: 03 | B87: 43215 | C87: management fee- | F87: 3510 | I87: transfer | J87: y | N87: Y | P87: =R87-Q87 -> -27.19 | Q87: =SUM($F$2:F87) -> 70375.78 | R87: =SUM($G$2:G87) -> 70348.59
A88: 03 | B88: 43226 | C88: paint | F88: 500 | I88: 5000188 | J88: y | N88: Y | P88: =R88-Q88 -> -527.19 | Q88: =SUM($F$2:F88) -> 70875.78 | R88: =SUM($G$2:G88) -> 70348.59
A89: 03 | B89: 43229 | C89: cleaning | F89: 560 | I89: tranfer | J89: y | N89: Y | P89: =R89-Q89 -> -1087.19 | Q89: =SUM($F$2:F89) -> 71435.78 | R89: =SUM($G$2:G89) -> 70348.59
A90: 03 | B90: 43230 | C90: pensia elena | F90: 102 | I90: tranfer | J90: y | N90: Y | P90: =R90-Q90 -> -1189.19 | Q90: =SUM($F$2:F90) -> 71537.78 | R90: =SUM($G$2:G90) -> 70348.59
A91: 03 | B91: 43235 | C91: arnona 05-06/18 | H91: 1809.3 | J91: y | K91: moaza | L91: 4627853 | N91: Y | P91: =R91-Q91 -> -1189.19 | Q91: =SUM($F$2:F91) -> 71537.78 | R91: =SUM($G$2:G91) -> 70348.59
A92: 03 | B92: 43240 | C92: bituach leumi cleaning | F92: 41 | J92: y | N92: Y | P92: =R92-Q92 -> -1230.19 | Q92: =SUM($F$2:F92) -> 71578.78 | R92: =SUM($G$2:G92) -> 70348.59
A93: 03 | B93: 43250 | C93: electric 31/1-9/4/18 | H93: 434.09 | J93: y | K93: hevrat hasmal | L93: 490491418 | N93: Y | P93: =R93-Q93 -> -1230.19 | Q93: =SUM($F$2:F93) -> 71578.78 | R93: =SUM($G$2:G93) -> 70348.59
A94: 03 | B94: 43250 | C94: water 3-4/18 | H94: 318.62 | J94: y | L94: 1646956 | N94: Y | P94: =R94-Q94 -> -1230.19 | Q94: =SUM($F$2:F94) -> 71578.78 | R94: =SUM($G$2:G94) -> 70348.59
A95: 03 | B95: 43251 | C95: paint | F95: 500 | I95: 5000187 | J95: y | N95: Y | P95: =R95-Q95 -> -1730.19 | Q95: =SUM($F$2:F95) -> 72078.78 | R95: =SUM($G$2:G95) -> 70348.59
A96: 03 | B96: 43252 | C96: Gardener | F96: 1989 | I96: transfer | J96: y | K96: גרהם אסקין | L96: 50 | N96: Y | P96: =R96-Q96 -> -3719.19 | Q96: =SUM($F$2:F96) -> 74067.78 | R96: =SUM($G$2:G96) -> 70348.59
A97: 03 | B97: 43255 | C97: electric10/4-31/5 | H97: 300.6 | J97: y | K97: חברת חשמל | N97: Y | P97: =R97-Q97 -> -3719.19 | Q97: =SUM($F$2:F97) -> 74067.78 | R97: =SUM($G$2:G97) -> 70348.59
A98: 03 | B98: 43258 | C98: pay elena - may cleening | F98: 530 | I98: transfer | J98: y | N98: Y | P98: =R98-Q98 -> -4249.19 | Q98: =SUM($F$2:F98) -> 74597.78 | R98: =SUM($G$2:G98) -> 70348.59
A99: 03 | B99: 43262 | C99: pensia oct | F99: 95.94 | J99: y | N99: Y | P99: =R99-Q99 -> -4345.13 | Q99: =SUM($F$2:F99) -> 74693.72 | R99: =SUM($G$2:G99) -> 70348.59
A100: 03 | B100: 43263 | C100: adbara | F100: 450 | I100: transfer | J100: y | K100: עדי מזרחי | L100: 2883 | N100: Y | P100: =R100-Q100 -> -4795.13 | Q100: =SUM($F$2:F100) -> 75143.72 | R100: =SUM($G$2:G100) -> 70348.59
...

Sheet 04 EX
A1: Prop ID | B1: Date | C1: Section | D1: Notes | E1: Type | F1: Amount | G1: Inflow | H1: He/She paid | I1: Method | J1: Reconciled | K1: Company | L1: Reciept | M1: Rental income | N1: Reported | O1: Report sent | P1: Balance | Q1: Total Amount | R1: Total Inflow
A2: 04 | B2: 43864 | C2: Keys | F2: 135 | I2: cc | J2: y | K2: חיים מנעולים | L2: 9843 | N2: Y | P2: =R2-Q2 -> -135 | Q2: =SUBTOTAL(9,$F$2:F2) -> 135 | R2: =SUBTOTAL(9,$G$2:G2) -> 0
A3: 04 | B3: 43871 | C3: Paid in cash | G3: 135 | I3: מזומן | J3: y | N3: Y | P3: =R3-Q3 -> 0 | Q3: =SUBTOTAL(9,$F$2:F3) -> 135 | R3: =SUBTOTAL(9,$G$2:G3) -> 135
A4: 04 | B4: 43873 | C4: Electrician | F4: 234 | I4: t | J4: y | K4: איתי דרור | L4: 642 | N4: Y | P4: =R4-Q4 -> -234 | Q4: =SUBTOTAL(9,$F$2:F4) -> 369 | R4: =SUBTOTAL(9,$G$2:G4) -> 135
A5: 04 | B5: 43880 | C5: pre paid | G5: 700 | I5: שק | J5: y | N5: Y | P5: =R5-Q5 -> 466 | Q5: =SUBTOTAL(9,$F$2:F5) -> 369 | R5: =SUBTOTAL(9,$G$2:G5) -> 835
A6: 04 | B6: 43886 | F6: 550 | I6: t | J6: y | K6: עוזי אגסי | N6: Y | O6: 44153 | P6: =R6-Q6 -> -84 | Q6: =SUBTOTAL(9,$F$2:F6) -> 919 | R6: =SUBTOTAL(9,$G$2:G6) -> 835
A7: 04 | B7: 44188 | C7: pre paid | G7: 600 | I7: t | J7: y | P7: =R7-Q7 -> 516 | Q7: =SUBTOTAL(9,$F$2:F7) -> 919 | R7: =SUBTOTAL(9,$G$2:G7) -> 1435
A8: 04 | B8: 44265 | C8: Rent deposit | M8: 4300 | P8: =R8-Q8 -> 516 | Q8: =SUBTOTAL(9,$F$2:F8) -> 919 | R8: =SUBTOTAL(9,$G$2:G8) -> 1435
A9: 04 | B9: 44449 | C9: Rent deposit | M9: 4300 | P9: =R9-Q9 -> 516 | Q9: =SUBTOTAL(9,$F$2:F9) -> 919 | R9: =SUBTOTAL(9,$G$2:G9) -> 1435
A10: 04 | B10: 44510 | C10: Rent deposit | M10: 4300 | P10: =R10-Q10 -> 516 | Q10: =SUBTOTAL(9,$F$2:F10) -> 919 | R10: =SUBTOTAL(9,$G$2:G10) -> 1435
A11: 04 | B11: 44540 | C11: Rent deposit | M11: 4300 | P11: =R11-Q11 -> 516 | Q11: =SUBTOTAL(9,$F$2:F11) -> 919 | R11: =SUBTOTAL(9,$G$2:G11) -> 1435
A12: 04 | B12: 44571 | C12: Rent deposit | M12: 4300 | P12: =R12-Q12 -> 516 | Q12: =SUBTOTAL(9,$F$2:F12) -> 919 | R12: =SUBTOTAL(9,$G$2:G12) -> 1435
A13: 04 | B13: 44630 | C13: Rent deposit | M13: 4691 | P13: =R13-Q13 -> 516 | Q13: =SUBTOTAL(9,$F$2:F13) -> 919 | R13: =SUBTOTAL(9,$G$2:G13) -> 1435
A14: 04 | B14: 44661 | C14: Rent deposit | M14: 4691 | P14: =R14-Q14 -> 516 | Q14: =SUBTOTAL(9,$F$2:F14) -> 919 | R14: =SUBTOTAL(9,$G$2:G14) -> 1435
A15: 04 | B15: 44691 | C15: Rent deposit | M15: 4691 | P15: =R15-Q15 -> 516 | Q15: =SUBTOTAL(9,$F$2:F15) -> 919 | R15: =SUBTOTAL(9,$G$2:G15) -> 1435
A16: 04 | B16: 44722 | C16: Rent deposit | M16: 4691 | P16: =R16-Q16 -> 516 | Q16: =SUBTOTAL(9,$F$2:F16) -> 919 | R16: =SUBTOTAL(9,$G$2:G16) -> 1435
A17: 04 | B17: 44752 | C17: Rent deposit | M17: 4691 | P17: =R17-Q17 -> 516 | Q17: =SUBTOTAL(9,$F$2:F17) -> 919 | R17: =SUBTOTAL(9,$G$2:G17) -> 1435
A18: 04 | B18: 44778 | C18: Repair of air conditioner leak | D18: תיקון נזילת מזגן | F18: 363 | P18: =R18-Q18 -> 153 | Q18: =SUBTOTAL(9,$F$2:F18) -> 1282 | R18: =SUBTOTAL(9,$G$2:G18) -> 1435
A19: 04 | B19: 44784 | C19: Rent deposit | M19: 4691 | P19: =R19-Q19 -> 153 | Q19: =SUBTOTAL(9,$F$2:F19) -> 1282 | R19: =SUBTOTAL(9,$G$2:G19) -> 1435
A20: 04 | B20: 44816 | C20: Rent deposit | M20: 4691 | P20: =R20-Q20 -> 153 | Q20: =SUBTOTAL(9,$F$2:F20) -> 1282 | R20: =SUBTOTAL(9,$G$2:G20) -> 1435
A21: 04 | B21: 44878 | C21: Rent deposit | M21: 4691 | P21: =R21-Q21 -> 153 | Q21: =SUBTOTAL(9,$F$2:F21) -> 1282 | R21: =SUBTOTAL(9,$G$2:G21) -> 1435
A22: 04 | B22: 44906 | C22: Rent deposit | M22: 4691 | P22: =R22-Q22 -> 153 | Q22: =SUBTOTAL(9,$F$2:F22) -> 1282 | R22: =SUBTOTAL(9,$G$2:G22) -> 1435
A23: 04 | B23: 44923 | C23: Air conditioner repair | F23: 350 | K23: שולמן מזגנים | P23: =R23-Q23 -> -197 | Q23: =SUBTOTAL(9,$F$2:F23) -> 1632 | R23: =SUBTOTAL(9,$G$2:G23) -> 1435
A24: 04 | B24: 44938 | C24: Rent deposit | M24: 4691 | P24: =R24-Q24 -> -197 | Q24: =SUBTOTAL(9,$F$2:F24) -> 1632 | R24: =SUBTOTAL(9,$G$2:G24) -> 1435
P25: =R25-Q25 -> -197 | Q25: =SUBTOTAL(9,$F$2:F25) -> 1632 | R25: =SUBTOTAL(9,$G$2:G25) -> 1435

Sheet 08 ex
A1: Prop ID | B1: Date | C1: Section | D1: Notes | E1: Type | F1: Amount | G1: Inflow | H1: He/She paid | I1: Method | J1: Reconciled | K1: Company | L1: Reciept | M1: Rental income | N1: Reported | O1: Report sent | P1: Balance | Q1: Total Amount | R1: Total Inflow
A2: 08 | B2: 43830 | C2: pre paid | G2: 1000 | I2: t | J2: y | N2: Y | P2: =R2-Q2 -> 1000 | Q2: =SUBTOTAL(9,$F$2:F2) -> 0 | R2: =SUBTOTAL(9,$G$2:G2) -> 1000
A3: 08 | B3: 43846 | C3: חשמל | F3: 27.64 | N3: Y | P3: =R3-Q3 -> 972.36 | Q3: =SUBTOTAL(9,$F$2:F3) -> 27.64 | R3: =SUBTOTAL(9,$G$2:G3) -> 1000
A4: 08 | B4: 43846 | C4: ארנונה | F4: 563.2 | N4: Y | P4: =R4-Q4 -> 409.16 | Q4: =SUBTOTAL(9,$F$2:F4) -> 590.84 | R4: =SUBTOTAL(9,$G$2:G4) -> 1000
A5: 08 | B5: 43865 | C5: שילם בטעות לפה את הניהול | G5: 8424 | N5: Y | P5: =R5-Q5 -> 8833.16 | Q5: =SUBTOTAL(9,$F$2:F5) -> 590.84 | R5: =SUBTOTAL(9,$G$2:G5) -> 9424
A6: 08 | B6: 43867 | C6: העברתי לסנדי | F6: 8424 | N6: Y | P6: =R6-Q6 -> 409.16 | Q6: =SUBTOTAL(9,$F$2:F6) -> 9014.84 | R6: =SUBTOTAL(9,$G$2:G6) -> 9424
A7: 08 | B7: 43937 | C7: שכירות | M7: 7200 | N7: Y | P7: =R7-Q7 -> 409.16 | Q7: =SUBTOTAL(9,$F$2:F7) -> 9014.84 | R7: =SUBTOTAL(9,$G$2:G7) -> 9424
A8: 08 | B8: 43949 | C8: אבי קודיש חשמלאי | F8: 200 | I8: t | J8: y | N8: Y | P8: =R8-Q8 -> 209.16 | Q8: =SUBTOTAL(9,$F$2:F8) -> 9214.84 | R8: =SUBTOTAL(9,$G$2:G8) -> 9424
A9: 08 | B9: 43962 | C9: ניהול בטעות העביר לפה | G9: 2527.2 | I9: t | J9: y | N9: Y | P9: =R9-Q9 -> 2736.36 | Q9: =SUBTOTAL(9,$F$2:F9) -> 9214.84 | R9: =SUBTOTAL(9,$G$2:G9) -> 11951.2
A10: 08 | B10: 43965 | C10: ניהול העברתי לסנדי | F10: 2527.2 | I10: t | J10: y | N10: Y | P10: =R10-Q10 -> 209.16 | Q10: =SUBTOTAL(9,$F$2:F10) -> 11742.04 | R10: =SUBTOTAL(9,$G$2:G10) -> 11951.2
A11: 08 | B11: 44020 | C11: התקנת מערכת פילטרים | F11: 1521 | I11: t | J11: y | K11: אשר ברינבאום | L11: 755 | N11: Y | O11: 44022 | P11: =R11-Q11 -> -1311.84 | Q11: =SUBTOTAL(9,$F$2:F11) -> 13263.04 | R11: =SUBTOTAL(9,$G$2:G11) -> 11951.2
A12: 08 | B12: 44031 | C12: שכירות | M12: 7200 | N12: Y | P12: =R12-Q12 -> -1311.84 | Q12: =SUBTOTAL(9,$F$2:F12) -> 13263.04 | R12: =SUBTOTAL(9,$G$2:G12) -> 11951.2
A13: 08 | B13: 44059 | C13: שכירות | M13: 7200 | N13: Y | P13: =R13-Q13 -> -1311.84 | Q13: =SUBTOTAL(9,$F$2:F13) -> 13263.04 | R13: =SUBTOTAL(9,$G$2:G13) -> 11951.2
A14: 08 | B14: 44088 | C14: pre paid | G14: 2500 | I14: t | J14: y | N14: Y | P14: =R14-Q14 -> 1188.16 | Q14: =SUBTOTAL(9,$F$2:F14) -> 13263.04 | R14: =SUBTOTAL(9,$G$2:G14) -> 14451.2
A15: 08 | B15: 44123 | C15: שכירות | M15: 7200 | N15: Y | P15: =R15-Q15 -> 1188.16 | Q15: =SUBTOTAL(9,$F$2:F15) -> 13263.04 | R15: =SUBTOTAL(9,$G$2:G15) -> 14451.2
A16: 08 | B16: 44123 | C16: שכירות | M16: 7200 | N16: Y | P16: =R16-Q16 -> 1188.16 | Q16: =SUBTOTAL(9,$F$2:F16) -> 13263.04 | R16: =SUBTOTAL(9,$G$2:G16) -> 14451.2
A17: 08 | B17: 44151 | C17: שכירות | M17: 7200 | N17: Y | P17: =R17-Q17 -> 1188.16 | Q17: =SUBTOTAL(9,$F$2:F17) -> 13263.04 | R17: =SUBTOTAL(9,$G$2:G17) -> 14451.2
A18: 08 | B18: 44180 | C18: שכירות | M18: 7200 | N18: Y | P18: =R18-Q18 -> 1188.16 | Q18: =SUBTOTAL(9,$F$2:F18) -> 13263.04 | R18: =SUBTOTAL(9,$G$2:G18) -> 14451.2
A19: 08 | B19: 44193 | C19: Management Sandi | D19: ניהול בטעות העביר לפה | G19: 7581.6 | I19: t | J19: y | N19: Y | P19: =R19-Q19 -> 8769.76 | Q19: =SUBTOTAL(9,$F$2:F19) -> 13263.04 | R19: =SUBTOTAL(9,$G$2:G19) -> 22032.8
A20: 08 | B20: 44194 | C20: Management Sandi | D20: ניהול העברתי לסנדי | F20: 7581.6 | I20: t | J20: y | N20: Y | P20: =R20-Q20 -> 1188.16 | Q20: =SUBTOTAL(9,$F$2:F20) -> 20844.64 | R20: =SUBTOTAL(9,$G$2:G20) -> 22032.8
A21: 08 | B21: 44214 | C21: Deposit of rent | M21: 7700 | N21: Y | P21: =R21-Q21 -> 1188.16 | Q21: =SUBTOTAL(9,$F$2:F21) -> 20844.64 | R21: =SUBTOTAL(9,$G$2:G21) -> 22032.8
A22: 08 | B22: 44242 | C22: Deposit of rent | M22: 7700 | N22: Y | P22: =R22-Q22 -> 1188.16 | Q22: =SUBTOTAL(9,$F$2:F22) -> 20844.64 | R22: =SUBTOTAL(9,$G$2:G22) -> 22032.8
A23: 08 | B23: 44273 | C23: Deposit of rent | M23: 7700 | N23: Y | P23: =R23-Q23 -> 1188.16 | Q23: =SUBTOTAL(9,$F$2:F23) -> 20844.64 | R23: =SUBTOTAL(9,$G$2:G23) -> 22032.8
A24: 08 | B24: 44306 | C24: Deposit of rent | M24: 7700 | N24: Y | P24: =R24-Q24 -> 1188.16 | Q24: =SUBTOTAL(9,$F$2:F24) -> 20844.64 | R24: =SUBTOTAL(9,$G$2:G24) -> 22032.8
A25: 08 | B25: 44337 | C25: Deposit of rent | M25: 7700 | N25: Y | P25: =R25-Q25 -> 1188.16 | Q25: =SUBTOTAL(9,$F$2:F25) -> 20844.64 | R25: =SUBTOTAL(9,$G$2:G25) -> 22032.8
A26: 08 | B26: 44364 | C26: Deposit of rent | M26: 7700 | N26: Y | P26: =R26-Q26 -> 1188.16 | Q26: =SUBTOTAL(9,$F$2:F26) -> 20844.64 | R26: =SUBTOTAL(9,$G$2:G26) -> 22032.8
A27: 08 | B27: 44374 | C27: Management Sandi | D27: בטעות העביר לפה | G27: 5054.4 | I27: t | J27: y | N27: Y | P27: =R27-Q27 -> 6242.56 | Q27: =SUBTOTAL(9,$F$2:F27) -> 20844.64 | R27: =SUBTOTAL(9,$G$2:G27) -> 27087.2
A28: 08 | B28: 44375 | C28: Management Sandi | D28: העברתי לסנדי | F28: 5054.4 | I28: t | J28: y | N28: Y | P28: =R28-Q28 -> 1188.16 | Q28: =SUBTOTAL(9,$F$2:F28) -> 25899.04 | R28: =SUBTOTAL(9,$G$2:G28) -> 27087.2
A29: 08 | B29: 44396 | C29: Deposit of rent | M29: 7700 | N29: Y | P29: =R29-Q29 -> 1188.16 | Q29: =SUBTOTAL(9,$F$2:F29) -> 25899.04 | R29: =SUBTOTAL(9,$G$2:G29) -> 27087.2
A30: 08 | B30: 44431 | C30: Deposit of rent | M30: 7700 | N30: Y | P30: =R30-Q30 -> 1188.16 | Q30: =SUBTOTAL(9,$F$2:F30) -> 25899.04 | R30: =SUBTOTAL(9,$G$2:G30) -> 27087.2
A31: 08 | B31: 44458 | C31: Deposit of rent | M31: 7700 | N31: Y | P31: =R31-Q31 -> 1188.16 | Q31: =SUBTOTAL(9,$F$2:F31) -> 25899.04 | R31: =SUBTOTAL(9,$G$2:G31) -> 27087.2
A32: 08 | B32: 44553 | C32: Deposit of rent | M32: 7700 | N32: Y | P32: =R32-Q32 -> 1188.16 | Q32: =SUBTOTAL(9,$F$2:F32) -> 25899.04 | R32: =SUBTOTAL(9,$G$2:G32) -> 27087.2
A33: 08 | B33: 44704 | C33: Deposit of rent | M33: 8700 | N33: Y | P33: =R33-Q33 -> 1188.16 | Q33: =SUBTOTAL(9,$F$2:F33) -> 25899.04 | R33: =SUBTOTAL(9,$G$2:G33) -> 27087.2
A34: 08 | B34: 44732 | C34: Deposit of rent | M34: 7700 | N34: Y | P34: =R34-Q34 -> 1188.16 | Q34: =SUBTOTAL(9,$F$2:F34) -> 25899.04 | R34: =SUBTOTAL(9,$G$2:G34) -> 27087.2
A35: 08 | B35: 44788 | C35: Deposit of rent | M35: 7700 | N35: Y | P35: =R35-Q35 -> 1188.16 | Q35: =SUBTOTAL(9,$F$2:F35) -> 25899.04 | R35: =SUBTOTAL(9,$G$2:G35) -> 27087.2
A36: 08 | B36: 44824 | C36: Deposit of rent | M36: 7700 | N36: Y | P36: =R36-Q36 -> 1188.16 | Q36: =SUBTOTAL(9,$F$2:F36) -> 25899.04 | R36: =SUBTOTAL(9,$G$2:G36) -> 27087.2
A37: 08 | B37: 44854 | C37: Deposit of rent | M37: 7700 | N37: Y | P37: =R37-Q37 -> 1188.16 | Q37: =SUBTOTAL(9,$F$2:F37) -> 25899.04 | R37: =SUBTOTAL(9,$G$2:G37) -> 27087.2
A38: 08 | B38: 44881 | C38: Deposit of rent | M38: 7700 | N38: Y | P38: =R38-Q38 -> 1188.16 | Q38: =SUBTOTAL(9,$F$2:F38) -> 25899.04 | R38: =SUBTOTAL(9,$G$2:G38) -> 27087.2
A39: 08 | B39: 44943 | C39: Deposit of rent | M39: 7700 | N39: Y | P39: =R39-Q39 -> 1188.16 | Q39: =SUBTOTAL(9,$F$2:F39) -> 25899.04 | R39: =SUBTOTAL(9,$G$2:G39) -> 27087.2
A40: 08 | B40: 44977 | C40: Deposit of rent | M40: 7700 | N40: Y | P40: =R40-Q40 -> 1188.16 | Q40: =SUBTOTAL(9,$F$2:F40) -> 25899.04 | R40: =SUBTOTAL(9,$G$2:G40) -> 27087.2
... A55: 08 | B55: 45459 | C55: Deposit of rent | M55: 8700 | N55: Y | P55: =R55-Q55 -> 1188.16 | Q55: =SUBTOTAL(9,$F$2:F55) -> 25899.04 | R55: =SUBTOTAL(9,$G$2:G55) -> 27087.2
A56: 08 | B56: 45481 | C56: Toilet repair | F56: 239 | I56: cc | K56: עולם הניאגרה | L56: 30137 | N56: Y | P56: =R56-Q56 -> 949.16 | Q56: =SUBTOTAL(9,$F$2:F56) -> 26138.04 | R56: =SUBTOTAL(9,$G$2:G56) -> 27087.2
A57: 08 | B57: 45482 | C57: Repair niagara leak | D57: Osher | F57: 250 | I57: t | N57: Y | P57: =R57-Q57 -> 699.16 | Q57: =SUBTOTAL(9,$F$2:F57) -> 26388.04 | R57: =SUBTOTAL(9,$G$2:G57) -> 27087.2
A58: 08 | B58: 45490 | C58: Deposit of rent | M58: 9000 | N58: Y | P58: =R58-Q58 -> 699.16 | Q58: =SUBTOTAL(9,$F$2:F58) -> 26388.04 | R58: =SUBTOTAL(9,$G$2:G58) -> 27087.2
A59: 08 | B59: 45505 | C59: Deposit of rent | M59: 1000 | N59: Y | P59: =R59-Q59 -> 699.16 | Q59: =SUBTOTAL(9,$F$2:F59) -> 26388.04 | R59: =SUBTOTAL(9,$G$2:G59) -> 27087.2
A60: 08 | B60: 45550 | C60: Deposit of rent | M60: 9000 | N60: Y | P60: =R60-Q60 -> 699.16 | Q60: =SUBTOTAL(9,$F$2:F60) -> 26388.04 | R60: =SUBTOTAL(9,$G$2:G60) -> 27087.2
A61: 08 | B61: 45575 | C61: Electric shutter repair (tris) | F61: 500 | I61: t | K61: מוראד | L61: 280 | N61: Y | P61: =R61-Q61 -> 199.16 | Q61: =SUBTOTAL(9,$F$2:F61) -> 26888.04 | R61: =SUBTOTAL(9,$G$2:G61) -> 27087.2
A62: 08 | B62: 45580 | C62: Deposit of rent | M62: 9000 | N62: Y | P62: =R62-Q62 -> 199.16 | Q62: =SUBTOTAL(9,$F$2:F62) -> 26888.04 | R62: =SUBTOTAL(9,$G$2:G62) -> 27087.2
A63: 08 | B63: 45616 | C63: Deposit of rent | M63: 9000 | N63: Y | P63: =R63-Q63 -> 199.16 | Q63: =SUBTOTAL(9,$F$2:F63) -> 26888.04 | R63: =SUBTOTAL(9,$G$2:G63) -> 27087.2
A64: 08 | B64: 45642 | C64: Deposit of rent | M64: 9000 | N64: Y | P64: =R64-Q64 -> 199.16 | Q64: =SUBTOTAL(9,$F$2:F64) -> 26888.04 | R64: =SUBTOTAL(9,$G$2:G64) -> 27087.2
A65: 08 | B65: 45645 | C65: Damp repair | F65: 2400 | I65: t | K65: סאלח אל כליל | N65: Y | O65: 45652 | P65: =R65-Q65 -> -2200.84 | Q65: =SUBTOTAL(9,$F$2:F65) -> 29288.04 | R65: =SUBTOTAL(9,$G$2:G65) -> 27087.2
A66: 08 | B66: 45669 | C66: Advance | G66: 4000 | P66: =R66-Q66 -> 1799.16 | Q66: =SUBTOTAL(9,$F$2:F66) -> 29288.04 | R66: =SUBTOTAL(9,$G$2:G66) -> 31087.2
A67: 08 | B67: 45670 | C67: Shower system | F67: 117 | I67: cc | K67: בנדק | L67: 252401455 | P67: =R67-Q67 -> 1682.16 | Q67: =SUBTOTAL(9,$F$2:F67) -> 29405.04 | R67: =SUBTOTAL(9,$G$2:G67) -> 31087.2
A68: 08 | B68: 45677 | C68: Deposit of rent | M68: 9000 | P68: =R68-Q68 -> 1682.16 | Q68: =SUBTOTAL(9,$F$2:F68) -> 29405.04 | R68: =SUBTOTAL(9,$G$2:G68) -> 31087.2
A69: 08 | B69: 45693 | C69: Leak check + shower system replacement | D69: osher | F69: 250 | I69: t | P69: =R69-Q69 -> 1432.16 | Q69: =SUBTOTAL(9,$F$2:F69) -> 29655.04 | R69: =SUBTOTAL(9,$G$2:G69) -> 31087.2
A70: 08 | B70: 45704 | C70: Deposit of rent | M70: 9000 | P70: =R70-Q70 -> 1432.16 | Q70: =SUBTOTAL(9,$F$2:F70) -> 29655.04 | R70: =SUBTOTAL(9,$G$2:G70) -> 31087.2
A71: 08 | B71: 45733 | C71: Deposit of rent | M71: 9000 | P71: =R71-Q71 -> 1432.16 | Q71: =SUBTOTAL(9,$F$2:F71) -> 29655.04 | R71: =SUBTOTAL(9,$G$2:G71) -> 31087.2
A72: 08 | B72: 45762 | C72: Deposit of rent | M72: 9000 | P72: =R72-Q72 -> 1432.16 | Q72: =SUBTOTAL(9,$F$2:F72) -> 29655.04 | R72: =SUBTOTAL(9,$G$2:G72) -> 31087.2
A73: 08 | B73: 45791 | C73: repair supplies | F73: 450 | I73: cc | K73: בנדק | L73: 252414521 | P73: =R73-Q73 -> 982.16 | Q73: =SUBTOTAL(9,$F$2:F73) -> 30105.04 | R73: =SUBTOTAL(9,$G$2:G73) -> 31087.2
A74: 08 | B74: 45818 | C74: New faucet installation - removal of old, complex faucet with a rusted mount | D74: Osher | F74: 400 | I74: t | P74: =R74-Q74 -> 582.16 | Q74: =SUBTOTAL(9,$F$2:F74) -> 30505.04 | R74: =SUBTOTAL(9,$G$2:G74) -> 31087.2
A75: 08 | B75: 45824 | C75: Deposit of rent | M75: 9000 | P75: =R75-Q75 -> 582.16 | Q75: =SUBTOTAL(9,$F$2:F75) -> 30505.04 | R75: =SUBTOTAL(9,$G$2:G75) -> 31087.2
A76: 08 | B76: 45888 | C76: Deposit of rent | M76: 9200 | P76: =R76-Q76 -> 582.16 | Q76: =SUBTOTAL(9,$F$2:F76) -> 30505.04 | R76: =SUBTOTAL(9,$G$2:G76) -> 31087.2
A77: 08 | B77: 45915 | C77: Deposit of rent | M77: 9200 | P77: =R77-Q77 -> 582.16 | Q77: =SUBTOTAL(9,$F$2:F77) -> 30505.04 | R77: =SUBTOTAL(9,$G$2:G77) -> 31087.2
A78: 08 | B78: 45945 | C78: Deposit of rent | M78: 9100 | P78: =R78-Q78 -> 582.16 | Q78: =SUBTOTAL(9,$F$2:F78) -> 30505.04 | R78: =SUBTOTAL(9,$G$2:G78) -> 31087.2
A79: 08 | B79: 45978 | C79: Deposit of rent | M79: 6100 | P79: =R79-Q79 -> 582.16 | Q79: =SUBTOTAL(9,$F$2:F79) -> 30505.04 | R79: =SUBTOTAL(9,$G$2:G79) -> 31087.2
A80: 08 | B80: 45853 | C80: Deposit of rent | M80: 9200 | P80: =R80-Q80 -> 582.16 | Q80: =SUBTOTAL(9,$F$2:F80) -> 30505.04 | R80: =SUBTOTAL(9,$G$2:G80) -> 31087.2
C85: Report to leave for now

Sheet 05 ex
A1: Prop ID | B1: Date | C1: Section | D1: Notes | E1: Type | F1: Amount | G1: Inflow | H1: He/She paid | I1: Method | J1: Reconciled | K1: Company | L1: Reciept | M1: Rental income | N1: Reported | O1: Report sent | P1: Balance | Q1: Total Amount | R1: Total Inflow
A2: 05 | B2: 42514 | C2: electric | G2: 200 | I2: cash | J2: y | N2: Y | P2: =R2-Q2 -> 200 | Q2: =SUBTOTAL(9,$F$2:F2) -> 0 | R2: =SUBTOTAL(9,$G$2:G2) -> 200
A3: 05 | B3: 42738 | C3: keys | F3: 15 | I3: cc | J3: y | K3: chaim | L3: 8319 | N3: Y | P3: =R3-Q3 -> 185 | Q3: =SUBTOTAL(9,$F$2:F3) -> 15 | R3: =SUBTOTAL(9,$G$2:G3) -> 200
A4: 05 | B4: 42826 | C4: prepaid expenses | G4: 1068 | J4: y | K4: MIP | L4: 81 | N4: Y | P4: =R4-Q4 -> 1253 | Q4: =SUBTOTAL(9,$F$2:F4) -> 15 | R4: =SUBTOTAL(9,$G$2:G4) -> 1268
A5: 05 | B5: 42859 | C5: exterminator | F5: 450 | I5: transfer | J5: y | K5: עדי מזרחי | L5: 2115 | N5: Y | P5: =R5-Q5 -> 803 | Q5: =SUBTOTAL(9,$F$2:F5) -> 465 | R5: =SUBTOTAL(9,$G$2:G5) -> 1268
A6: 05 | B6: 42900 | C6: zack friend | F6: 45 | I6: transfer | J6: y | K6: zack | L6: no | N6: Y | P6: =R6-Q6 -> 758 | Q6: =SUBTOTAL(9,$F$2:F6) -> 510 | R6: =SUBTOTAL(9,$G$2:G6) -> 1268
A7: 05 | B7: 42901 | C7: keys | F7: 24 | I7: cc | J7: y | K7: chaim | L7: 7865 | N7: Y | P7: =R7-Q7 -> 734 | Q7: =SUBTOTAL(9,$F$2:F7) -> 534 | R7: =SUBTOTAL(9,$G$2:G7) -> 1268
A8: 05 | B8: 42901 | C8: Plumber | F8: 1368 | J8: y | L8: 57 | N8: Y | P8: =R8-Q8 -> -634 | Q8: =SUBTOTAL(9,$F$2:F8) -> 1902 | R8: =SUBTOTAL(9,$G$2:G8) -> 1268
A9: 05 | B9: 42919 | C9: Plumber | F9: 700 | I9: 5000093 | J9: y | K9: דוד סטורי | L9: 328 | N9: Y | P9: =R9-Q9 -> -1334 | Q9: =SUBTOTAL(9,$F$2:F9) -> 2602 | R9: =SUBTOTAL(9,$G$2:G9) -> 1268
A10: 05 | B10: 42934 | C10: gas installation | F10: 240 | I10: cc | J10: y | K10: electonic pro | L10: 1031624 | N10: Y | P10: =R10-Q10 -> -1574 | Q10: =SUBTOTAL(9,$F$2:F10) -> 2842 | R10: =SUBTOTAL(9,$G$2:G10) -> 1268
A11: 05 | B11: 42934 | C11: burners | F11: 1320 | I11: cc | J11: y | K11: Pr | L11: ov17501001177 | N11: Y | P11: =R11-Q11 -> -2894 | Q11: =SUBTOTAL(9,$F$2:F11) -> 4162 | R11: =SUBTOTAL(9,$G$2:G11) -> 1268
A12: 05 | B12: 42949 | C12: netvision 27-3-17 to 9-04-17 | F12: 163 | I12: cc | J12: y | K12: netvision | L12: 87572 | N12: Y | P12: =R12-Q12 -> -3057 | Q12: =SUBTOTAL(9,$F$2:F12) -> 4325 | R12: =SUBTOTAL(9,$G$2:G12) -> 1268
A13: 05 | B13: 42949 | C13: gas installation | F13: 200 | I13: 5000097 | J13: y | K13: david sheruti mizug | L13: 157 | N13: Y | P13: =R13-Q13 -> -3257 | Q13: =SUBTOTAL(9,$F$2:F13) -> 4525 | R13: =SUBTOTAL(9,$G$2:G13) -> 1268
A14: 05 | B14: 42962 | C14: ben cleaning | F14: 60 | J14: y | K14: ben | L14: no | N14: Y | P14: =R14-Q14 -> -3317 | Q14: =SUBTOTAL(9,$F$2:F14) -> 4585 | R14: =SUBTOTAL(9,$G$2:G14) -> 1268
A15: 05 | B15: 42996 | C15: prepaid expenses | G15: 3000 | J15: y | K15: mip | L15: 112 | N15: Y | P15: =R15-Q15 -> -317 | Q15: =SUBTOTAL(9,$F$2:F15) -> 4585 | R15: =SUBTOTAL(9,$G$2:G15) -> 4268
A16: 05 | B16: 43007 | C16: prepaid expenses | G16: 3032 | J16: y | K16: Mip | L16: 118 | N16: Y | P16: =R16-Q16 -> 2715 | Q16: =SUBTOTAL(9,$F$2:F16) -> 4585 | R16: =SUBTOTAL(9,$G$2:G16) -> 7300
A17: 05 | B17: 43023 | C17: Cleaning supplies | F17: 109.3 | I17: cc | J17: y | K17: Hendler | L17: 89010009 | N17: Y | P17: =R17-Q17 -> 2605.7 | Q17: =SUBTOTAL(9,$F$2:F17) -> 4694.3 | R17: =SUBTOTAL(9,$G$2:G17) -> 7300
A18: 05 | B18: 43025 | C18: water | F18: 11.9 | I18: cc | J18: y | K18: Mega bair | L18: 29600405012661 | N18: Y | P18: =R18-Q18 -> 2593.8 | Q18: =SUBTOTAL(9,$F$2:F18) -> 4706.2 | R18: =SUBTOTAL(9,$G$2:G18) -> 7300
A19: 05 | B19: 43025 | C19: groceries | F19: 119.82 | I19: cc | J19: y | K19: Hendler | L19: 9101009 | N19: Y | P19: =R19-Q19 -> 2473.98 | Q19: =SUBTOTAL(9,$F$2:F19) -> 4826.02 | R19: =SUBTOTAL(9,$G$2:G19) -> 7300
A20: 05 | B20: 43033 | C20: elecric | F20: 800 | I20: transfer | J20: y | K20: avv | L20: 254 | N20: Y | P20: =R20-Q20 -> 1673.98 | Q20: =SUBTOTAL(9,$F$2:F20) -> 5626.02 | R20: =SUBTOTAL(9,$G$2:G20) -> 7300
A21: 05 | B21: 43037 | C21: new key | F21: 12 | I21: cc | J21: y | K21: chaim manulim | L21: 8179 | N21: Y | P21: =R21-Q21 -> 1661.98 | Q21: =SUBTOTAL(9,$F$2:F21) -> 5638.02 | R21: =SUBTOTAL(9,$G$2:G21) -> 7300
A22: 05 | B22: 43039 | C22: water may June | F22: 134.5 | I22: cc | J22: y | K22: Tagid | L22: 5342 | N22: Y | P22: =R22-Q22 -> 1527.48 | Q22: =SUBTOTAL(9,$F$2:F22) -> 5772.52 | R22: =SUBTOTAL(9,$G$2:G22) -> 7300
A23: 05 | B23: 43039 | C23: water July August | F23: 426.7 | I23: cc | J23: y | K23: Tagit | L23: 5343 | N23: Y | P23: =R23-Q23 -> 1100.78 | Q23: =SUBTOTAL(9,$F$2:F23) -> 6199.22 | R23: =SUBTOTAL(9,$G$2:G23) -> 7300
A24: 05 | B24: 43039 | C24: electic June July | F24: 476.54 | I24: cc | J24: y | K24: electric | L24: 87395 | N24: Y | P24: =R24-Q24 -> 624.24 | Q24: =SUBTOTAL(9,$F$2:F24) -> 6675.76 | R24: =SUBTOTAL(9,$G$2:G24) -> 7300
A25: 05 | B25: 43040 | C25: cleaning BL | F25: 43.5 | J25: y | N25: Y | P25: =R25-Q25 -> 580.74 | Q25: =SUBTOTAL(9,$F$2:F25) -> 6719.26 | R25: =SUBTOTAL(9,$G$2:G25) -> 7300
A26: 05 | B26: 43040 | C26: cleaning 15/10 and 31/10 | F26: 615 | I26: transfer | J26: y | K26: elena | N26: Y | P26: =R26-Q26 -> -34.26 | Q26: =SUBTOTAL(9,$F$2:F26) -> 7334.26 | R26: =SUBTOTAL(9,$G$2:G26) -> 7300
A27: 05 | B27: 43055 | C27: cleaning | F27: 220 | I27: transfer | J27: y | K27: elena | N27: Y | P27: =R27-Q27 -> -254.26 | Q27: =SUBTOTAL(9,$F$2:F27) -> 7554.26 | R27: =SUBTOTAL(9,$G$2:G27) -> 7300
A28: 05 | B28: 43059 | C28: return of burner | G28: 600 | I28: 5008254 | J28: y | K28: pr | N28: Y | P28: =R28-Q28 -> 345.74 | Q28: =SUBTOTAL(9,$F$2:F28) -> 7554.26 | R28: =SUBTOTAL(9,$G$2:G28) -> 7900
A29: 05 | B29: 43060 | C29: Handyman | F29: 300 | I29: transfer | J29: y | K29: shalom shevach | L29: 327 | N29: Y | P29: =R29-Q29 -> 45.74 | Q29: =SUBTOTAL(9,$F$2:F29) -> 7854.26 | R29: =SUBTOTAL(9,$G$2:G29) -> 7900
A30: 05 | B30: 43061 | C30: elecrric box | H30: 2500 | I30: transfer | J30: y | K30: avi kodesh | N30: Y | P30: =R30-Q30 -> 45.74 | Q30: =SUBTOTAL(9,$F$2:F30) -> 7854.26 | R30: =SUBTOTAL(9,$G$2:G30) -> 7900
A31: 05 | B31: 43110 | C31: electric august to Dec | F31: 920.75 | I31: cc | J31: y | N31: Y | P31: =R31-Q31 -> -875.01 | Q31: =SUBTOTAL(9,$F$2:F31) -> 8775.01 | R31: =SUBTOTAL(9,$G$2:G31) -> 7900
A32: 05 | B32: 43115 | C32: water August - December | H32: 1289.6 | J32: y | N32: Y | P32: =R32-Q32 -> -875.01 | Q32: =SUBTOTAL(9,$F$2:F32) -> 8775.01 | R32: =SUBTOTAL(9,$G$2:G32) -> 7900
A33: 05 | B33: 43117 | C33: toilet and leak | F33: 877 | I33: 5000121 | J33: y | K33: Erez Lvenberg | L33: 8146 | N33: Y | P33: =R33-Q33 -> -1752.01 | Q33: =SUBTOTAL(9,$F$2:F33) -> 9652.01 | R33: =SUBTOTAL(9,$G$2:G33) -> 7900
A34: 05 | B34: 43120 | C34: fridge technicain | F34: 150 | I34: 5000122 | J34: y | K34: Aronav Alex | L34: 9848 | N34: Y | P34: =R34-Q34 -> -1902.01 | Q34: =SUBTOTAL(9,$F$2:F34) -> 9802.01 | R34: =SUBTOTAL(9,$G$2:G34) -> 7900
A35: 05 | B35: 43123 | C35: prepaid expenses | G35: 1000 | J35: y | L35: 146 | N35: Y | P35: =R35-Q35 -> -902.01 | Q35: =SUBTOTAL(9,$F$2:F35) -> 9802.01 | R35: =SUBTOTAL(9,$G$2:G35) -> 8900
A36: 05 | B36: 43130 | C36: faucet | F36: 596 | I36: cc | J36: y | K36: Ronis | L36: RC189000105 | N36: Y | P36: =R36-Q36 -> -1498.01 | Q36: =SUBTOTAL(9,$F$2:F36) -> 10398.01 | R36: =SUBTOTAL(9,$G$2:G36) -> 8900
A37: 05 | B37: 43130 | C37: electiric water - Hannah | G37: 2016 | I37: deposit | J37: y | L37: 144 | N37: Y | P37: =R37-Q37 -> 517.99 | Q37: =SUBTOTAL(9,$F$2:F37) -> 10398.01 | R37: =SUBTOTAL(9,$G$2:G37) -> 10916
A38: 05 | B38: 43130 | C38: electric water tamar | G38: 520 | I38: deposit | J38: y | L38: 141 | N38: Y | P38: =R38-Q38 -> 1037.99 | Q38: =SUBTOTAL(9,$F$2:F38) -> 10398.01 | R38: =SUBTOTAL(9,$G$2:G38) -> 11436
A39: 05 | B39: 43131 | C39: electric water tamar | G39: 15 | I39: from buffer | J39: y | N39: Y | P39: =R39-Q39 -> 1052.99 | Q39: =SUBTOTAL(9,$F$2:F39) -> 10398.01 | R39: =SUBTOTAL(9,$G$2:G39) -> 11451
A40: 05 | B40: 43132 | C40: faucet /toliet | F40: 645 | I40: 5000124 | J40: y | K40: tim | N40: Y | P40: =R40-Q40 -> 407.99 | Q40: =SUBTOTAL(9,$F$2:F40) -> 11043.01 | R40: =SUBTOTAL(9,$G$2:G40) -> 11451
A41: 05 | B41: 43132 | C41: arnona 2018 | F41: 12318 | I41: cc | J41: y | K41: moatza | L41: 1288447 | N41: Y | P41: =R41-Q41 -> -11910.01 | Q41: =SUBTOTAL(9,$F$2:F41) -> 23361.01 | R41: =SUBTOTAL(9,$G$2:G41) -> 11451
A42: 05 | B42: 43137 | C42: copper- Plumber | F42: 800 | I42: transfer | J42: y | K42: צפריר חממ י שרותי אינסלציה | N42: Y | P42: =R42-Q42 -> -12710.01 | Q42: =SUBTOTAL(9,$F$2:F42) -> 24161.01 | R42: =SUBTOTAL(9,$G$2:G42) -> 11451
A43: 05 | B43: 43137 | C43: prepaid expenses | G43: 12318 | I43: transfer | J43: y | K43: Mip | L43: 147 | N43: Y | P43: =R43-Q43 -> -392.01 | Q43: =SUBTOTAL(9,$F$2:F43) -> 24161.01 | R43: =SUBTOTAL(9,$G$2:G43) -> 23769
A44: 05 | B44: 43138 | C44: Cleaning joni | F44: 320 | I44: transfer | J44: y | N44: Y | P44: =R44-Q44 -> -712.01 | Q44: =SUBTOTAL(9,$F$2:F44) -> 24481.01 | R44: =SUBTOTAL(9,$G$2:G44) -> 23769
A45: 05 | B45: 43164 | C45: washing machine techn | F45: 250 | J45: y | N45: Y | P45: =R45-Q45 -> -962.01 | Q45: =SUBTOTAL(9,$F$2:F45) -> 24731.01 | R45: =SUBTOTAL(9,$G$2:G45) -> 23769
A46: 05 | B46: 43164 | C46: Plumber | F46: 450 | I46: 5000177 | J46: y | K46: שירותי אינסטלציה | L46: 2060 | N46: Y | P46: =R46-Q46 -> -1412.01 | Q46: =SUBTOTAL(9,$F$2:F46) -> 25181.01 | R46: =SUBTOTAL(9,$G$2:G46) -> 23769
A47: 05 | B47: 43164 | C47: water | F47: 9.5 | I47: cc | J47: y | K47: mayanot | N47: Y | P47: =R47-Q47 -> -1421.51 | Q47: =SUBTOTAL(9,$F$2:F47) -> 25190.51 | R47: =SUBTOTAL(9,$G$2:G47) -> 23769
A48: 05 | B48: 43171 | C48: bitucha leumi | F48: 525 | I48: cc | J48: y | N48: Y | P48: =R48-Q48 -> -1946.51 | Q48: =SUBTOTAL(9,$F$2:F48) -> 25715.51 | R48: =SUBTOTAL(9,$G$2:G48) -> 23769
A49: 05 | B49: 43172 | C49: electric | F49: 659.06 | J49: y | N49: Y | P49: =R49-Q49 -> -2605.57 | Q49: =SUBTOTAL(9,$F$2:F49) -> 26374.57 | R49: =SUBTOTAL(9,$G$2:G49) -> 23769
A50: 05 | B50: 43173 | C50: painter | H50: 6000 | I50: transfer | J50: y | K50: fredrick | L50: no | N50: Y | P50: =R50-Q50 -> -2605.57 | Q50: =SUBTOTAL(9,$F$2:F50) -> 26374.57 | R50: =SUBTOTAL(9,$G$2:G50) -> 23769
A51: 05 | B51: 43178 | C51: washing machine techn.chip | F51: 519 | I51: cc | J51: y | K51: csp | L51: 2018020147 | N51: Y | P51: =R51-Q51 -> -3124.57 | Q51: =SUBTOTAL(9,$F$2:F51) -> 26893.57 | R51: =SUBTOTAL(9,$G$2:G51) -> 23769
A52: 05 | B52: 43181 | C52: plumbing supplies | F52: 15 | I52: cc | J52: y | N52: Y | P52: =R52-Q52 -> -3139.57 | Q52: =SUBTOTAL(9,$F$2:F52) -> 26908.57 | R52: =SUBTOTAL(9,$G$2:G52) -> 23769
A53: 05 | B53: 43186 | C53: faucet for hana sink | F53: 257 | I53: cc | J53: y | K53: Ronis | L53: 96001004 | N53: Y | P53: =R53-Q53 -> -3396.57 | Q53: =SUBTOTAL(9,$F$2:F53) -> 27165.57 | R53: =SUBTOTAL(9,$G$2:G53) -> 23769
A54: 05 | B54: 43191 | C54: cleaning March 17 | F54: 420 | J54: y | N54: Y | P54: =R54-Q54 -> -3816.57 | Q54: =SUBTOTAL(9,$F$2:F54) -> 27585.57 | R54: =SUBTOTAL(9,$G$2:G54) -> 23769
A55: 05 | B55: 43191 | C55: bitucha leumi | F55: 30.52 | J55: y | N55: Y | P55: =R55-Q55 -> -3847.09 | Q55: =SUBTOTAL(9,$F$2:F55) -> 27616.09 | R55: =SUBTOTAL(9,$G$2:G55) -> 23769
A56: 05 | B56: 43212 | C56: Plumber for hanna | F56: 500 | I56: 5000176 | J56: y | K56: tim mckinney | L56: no | N56: Y | P56: =R56-Q56 -> -4347.09 | Q56: =SUBTOTAL(9,$F$2:F56) -> 28116.09 | R56: =SUBTOTAL(9,$G$2:G56) -> 23769
A57: 05 | B57: 43219 | C57: prepaid expenses | G57: 4000 | I57: transfer | J57: y | K57: mip | L57: 179 | N57: Y | P57: =R57-Q57 -> -347.09 | Q57: =SUBTOTAL(9,$F$2:F57) -> 28116.09 | R57: =SUBTOTAL(9,$G$2:G57) -> 27769
A58: 05 | B58: 43227 | C58: pensia joni | F58: 57.52 | I58: transfer | J58: y | N58: Y | P58: =R58-Q58 -> -404.61 | Q58: =SUBTOTAL(9,$F$2:F58) -> 28173.61 | R58: =SUBTOTAL(9,$G$2:G58) -> 27769
A59: 05 | B59: 43238 | C59: garden | H59: 15000 | I59: transfer | J59: y | K59: גרהם אסקין | L59: 47 | N59: Y | P59: =R59-Q59 -> -404.61 | Q59: =SUBTOTAL(9,$F$2:F59) -> 28173.61 | R59: =SUBTOTAL(9,$G$2:G59) -> 27769
A60: 05 | B60: 43242 | C60: water electric tamar | G60: 150 | I60: cash | J60: y | N60: Y | P60: =R60-Q60 -> -254.61 | Q60: =SUBTOTAL(9,$F$2:F60) -> 28173.61 | R60: =SUBTOTAL(9,$G$2:G60) -> 27919
A61: 05 | B61: 43245 | C61: adbara | F61: 550 | I61: transfer | J61: y | K61: עדי מזרחי | L61: 2802 | N61: Y | P61: =R61-Q61 -> -804.61 | Q61: =SUBTOTAL(9,$F$2:F61) -> 28723.61 | R61: =SUBTOTAL(9,$G$2:G61) -> 27919
A62: 05 | B62: 43248 | C62: garden | H62: 5000 | I62: transfer | J62: y | K62: graham eskin | L62: 47 | N62: Y | P62: =R62-Q62 -> -804.61 | Q62: =SUBTOTAL(9,$F$2:F62) -> 28723.61 | R62: =SUBTOTAL(9,$G$2:G62) -> 27919
A63: 05 | B63: 43249 | C63: garden | H63: 10000 | I63: transfer | J63: y | K63: graham eskin | L63: 47 | N63: Y | P63: =R63-Q63 -> -804.61 | Q63: =SUBTOTAL(9,$F$2:F63) -> 28723.61 | R63: =SUBTOTAL(9,$G$2:G63) -> 27919
A64: 05 | B64: 43249 | C64: hasmelai | H64: 300 | I64: transfer | J64: y | K64: avi kodis | N64: Y | P64: =R64-Q64 -> -804.61 | Q64: =SUBTOTAL(9,$F$2:F64) -> 28723.61 | R64: =SUBTOTAL(9,$G$2:G64) -> 27919
A65: 05 | B65: 43249 | C65: Food | F65: 265.79 | I65: cc | J65: y | K65: סופר שפע הברון | L65: 59 | N65: Y | P65: =R65-Q65 -> -1070.4 | Q65: =SUBTOTAL(9,$F$2:F65) -> 28989.4 | R65: =SUBTOTAL(9,$G$2:G65) -> 27919
A66: 05 | B66: 43250 | C66: drier | H66: 1490 | I66: cc | J66: y | K66: pr electric | N66: Y | P66: =R66-Q66 -> -1070.4 | Q66: =SUBTOTAL(9,$F$2:F66) -> 28989.4 | R66: =SUBTOTAL(9,$G$2:G66) -> 27919
A67: 05 | B67: 43250 | C67: espreso | H67: 1450 | I67: cc | J67: y | K67: pr electric | N67: Y | P67: =R67-Q67 -> -1070.4 | Q67: =SUBTOTAL(9,$F$2:F67) -> 28989.4 | R67: =SUBTOTAL(9,$G$2:G67) -> 27919
A68: 05 | B68: 43258 | C68: elektronika | H68: 1290 | J68: y | N68: Y | P68: =R68-Q68 -> -1070.4 | Q68: =SUBTOTAL(9,$F$2:F68) -> 28989.4 | R68: =SUBTOTAL(9,$G$2:G68) -> 27919
A69: 05 | B69: 43262 | C69: garden | H69: 5100 | I69: transfer | J69: y | K69: גרהם אסקין | L69: 47 | N69: Y | P69: =R69-Q69 -> -1070.4 | Q69: =SUBTOTAL(9,$F$2:F69) -> 28989.4 | R69: =SUBTOTAL(9,$G$2:G69) -> 27919
A70: 05 | B70: 43264 | C70: bitucha leumi | F70: 429 | I70: cc | J70: y | N70: Y | P70: =R70-Q70 -> -1499.4 | Q70: =SUBTOTAL(9,$F$2:F70) -> 29418.4 | R70: =SUBTOTAL(9,$G$2:G70) -> 27919
A71: 05 | B71: 43264 | C71: pensia elena may | F71: 134.36 | I71: transfer | J71: y | N71: Y | P71: =R71-Q71 -> -1633.76 | Q71: =SUBTOTAL(9,$F$2:F71) -> 29552.76 | R71: =SUBTOTAL(9,$G$2:G71) -> 27919
A72: 05 | B72: 43271 | C72: bitucha leumi may | F72: 53.83 | I72: transfer | J72: y | N72: Y | P72: =R72-Q72 -> -1687.59 | Q72: =SUBTOTAL(9,$F$2:F72) -> 29606.59 | R72: =SUBTOTAL(9,$G$2:G72) -> 27919
A73: 05 | B73: 43271 | C73: מפתחות | F73: 54 | I73: cc | J73: y | K73: חיים מנעולים | L73: 86452 | N73: Y | P73: =R73-Q73 -> -1741.59 | Q73: =SUBTOTAL(9,$F$2:F73) -> 29660.59 | R73: =SUBTOTAL(9,$G$2:G73) -> 27919
A74: 05 | B74: 43274 | C74: yes 1/6-30/6 | H74: 53.56 | J74: y | K74: יס | N74: Y | P74: =R74-Q74 -> -1741.59 | Q74: =SUBTOTAL(9,$F$2:F74) -> 29660.59 | R74: =SUBTOTAL(9,$G$2:G74) -> 27919
A75: 05 | B75: 43277 | C75: electric | F75: 301.15 | I75: cc | J75: y | K75: חברת חשמל | N75: Y | P75: =R75-Q75 -> -2042.74 | Q75: =SUBTOTAL(9,$F$2:F75) -> 29961.74 | R75: =SUBTOTAL(9,$G$2:G75) -> 27919
A76: 05 | B76: 43280 | C76: partner | F76: 36.73 | I76: cc | J76: y | N76: Y | P76: =R76-Q76 -> -2079.47 | Q76: =SUBTOTAL(9,$F$2:F76) -> 29998.47 | R76: =SUBTOTAL(9,$G$2:G76) -> 27919
A77: 05 | B77: 43287 | C77: pay elena cleaning may | F77: 780 | I77: transfer | J77: y | N77: Y | P77: =R77-Q77 -> -2859.47 | Q77: =SUBTOTAL(9,$F$2:F77) -> 30778.47 | R77: =SUBTOTAL(9,$G$2:G77) -> 27919
A78: 05 | B78: 43291 | C78: garden | H78: 9721.5 | J78: y | K78: גרהם אסקין | L78: 56 | N78: Y | P78: =R78-Q78 -> -2859.47 | Q78: =SUBTOTAL(9,$F$2:F78) -> 30778.47 | R78: =SUBTOTAL(9,$G$2:G78) -> 27919
A79: 05 | B79: 43300 | C79: החלפת אסלה וניאגרה | H79: 1000 | J79: y | K79: מנשה משה | L79: 290 | N79: Y | P79: =R79-Q79 -> -2859.47 | Q79: =SUBTOTAL(9,$F$2:F79) -> 30778.47 | R79: =SUBTOTAL(9,$G$2:G79) -> 27919
A80: 05 | B80: 43301 | C80: bituh leomi joni | F80: 23.09 | J80: y | N80: Y | P80: =R80-Q80 -> -2882.56 | Q80: =SUBTOTAL(9,$F$2:F80) -> 30801.56 | R80: =SUBTOTAL(9,$G$2:G80) -> 27919
A81: 05 | B81: 43304 | C81: bituh leomi stiven | F81: 207 | I81: cc | J81: y | N81: Y | P81: =R81-Q81 -> -3089.56 | Q81: =SUBTOTAL(9,$F$2:F81) -> 31008.56 | R81: =SUBTOTAL(9,$G$2:G81) -> 27919
A82: 05 | B82: 43307 | C82: קולט אדים | H82: 470 | J82: y | K82: אלקטרוניקה | L82: 2858 | N82: Y | P82: =R82-Q82 -> -3089.56 | Q82: =SUBTOTAL(9,$F$2:F82) -> 31008.56 | R82: =SUBTOTAL(9,$G$2:G82) -> 27919
A83: 05 | B83: 43314 | C83: electric 31/5-1/8 | F83: 531.31 | I83: cc | J83: y | K83: חברת חשמל | N83: Y | P83: =R83-Q83 -> -3620.87 | Q83: =SUBTOTAL(9,$F$2:F83) -> 31539.87 | R83: =SUBTOTAL(9,$G$2:G83) -> 27919
A84: 05 | B84: 43314 | C84: prepaid expenses | G84: 5000 | I84: transfer | J84: y | K84: העברה מהחשבון שלהם בבנק דיסקונט | L84: 80027 | N84: Y | P84: =R84-Q84 -> 1379.13 | Q84: =SUBTOTAL(9,$F$2:F84) -> 31539.87 | R84: =SUBTOTAL(9,$G$2:G84) -> 32919
A85: 05 | B85: 43316 | C85: managment fee | H85: 3952.26 | I85: transfer | J85: y | N85: Y | P85: =R85-Q85 -> 1379.13 | Q85: =SUBTOTAL(9,$F$2:F85) -> 31539.87 | R85: =SUBTOTAL(9,$G$2:G85) -> 32919
A86: 05 | B86: 43319 | C86: התקנת כיריים | F86: 300 | I86: 5000191 | J86: y | N86: Y | P86: =R86-Q86 -> 1079.13 | Q86: =SUBTOTAL(9,$F$2:F86) -> 31839.87 | R86: =SUBTOTAL(9,$G$2:G86) -> 32919
A87: 05 | B87: 43327 | C87: חומרי ניקוי | F87: 30.7 | I87: cc | J87: y | K87: הנדלר | N87: Y | P87: =R87-Q87 -> 1048.43 | Q87: =SUBTOTAL(9,$F$2:F87) -> 31870.57 | R87: =SUBTOTAL(9,$G$2:G87) -> 32919
A88: 05 | B88: 43331 | C88: water 5-6/18 | F88: 233.44 | I88: cc | J88: y | K88: מעיינות העמקים | N88: Y | P88: =R88-Q88 -> 814.99 | Q88: =SUBTOTAL(9,$F$2:F88) -> 32104.01 | R88: =SUBTOTAL(9,$G$2:G88) -> 32919
A89: 05 | B89: 43332 | C89: אינסטלטור | H89: 2550 | J89: y | K89: צפריר | L89: 2241 | N89: Y | P89: =R89-Q89 -> 814.99 | Q89: =SUBTOTAL(9,$F$2:F89) -> 32104.01 | R89: =SUBTOTAL(9,$G$2:G89) -> 32919
A90: 05 | B90: 43348 | C90: cleening elena aug | F90: 508.96 | I90: transfer | J90: y | N90: Y | P90: =R90-Q90 -> 306.03 | Q90: =SUBTOTAL(9,$F$2:F90) -> 32612.97 | R90: =SUBTOTAL(9,$G$2:G90) -> 32919
A91: 05 | B91: 43349 | C91: pensia elena aug | F91: 95.74 | I91: transfer | J91: y | N91: Y | P91: =R91-Q91 -> 210.29 | Q91: =SUBTOTAL(9,$F$2:F91) -> 32708.71 | R91: =SUBTOTAL(9,$G$2:G91) -> 32919
A92: 05 | B92: 43350 | C92: partner | F92: 46.04 | I92: cc | J92: y | N92: Y | P92: =R92-Q92 -> 164.25 | Q92: =SUBTOTAL(9,$F$2:F92) -> 32754.75 | R92: =SUBTOTAL(9,$G$2:G92) -> 32919
A93: 05 | B93: 43360 | C93: חשמלאי | H93: 1000 | J93: y | K93: אבי קודיש | N93: Y | P93: =R93-Q93 -> 164.25 | Q93: =SUBTOTAL(9,$F$2:F93) -> 32754.75 | R93: =SUBTOTAL(9,$G$2:G93) -> 32919
A94: 05 | B94: 43360 | C94: אינסלטור | H94: 2450 | J94: y | K94: מנשה משה | L94: 295 | N94: Y | P94: =R94-Q94 -> 164.25 | Q94: =SUBTOTAL(9,$F$2:F94) -> 32754.75 | R94: =SUBTOTAL(9,$G$2:G94) -> 32919
A95: 05 | B95: 43363 | C95: bituh leomi elena aug | F95: 38.58 | I95: transfer | J95: y | N95: Y | P95: =R95-Q95 -> 125.67 | Q95: =SUBTOTAL(9,$F$2:F95) -> 32793.33 | R95: =SUBTOTAL(9,$G$2:G95) -> 32919
A96: 05 | B96: 43373 | C96: water 7-8/18 | F96: 184.43 | I96: cc | J96: y | N96: Y | P96: =R96-Q96 -> -58.76 | Q96: =SUBTOTAL(9,$F$2:F96) -> 32977.76 | R96: =SUBTOTAL(9,$G$2:G96) -> 32919
A97: 05 | B97: 43377 | C97: cleening elena sep | F97: 602.73 | I97: transfer | J97: y | N97: Y | P97: =R97-Q97 -> -661.49 | Q97: =SUBTOTAL(9,$F$2:F97) -> 33580.49 | R97: =SUBTOTAL(9,$G$2:G97) -> 32919
A98: 05 | B98: 43377 | C98: pensia sep | F98: 114.93 | I98: transfer | J98: y | N98: Y | P98: =R98-Q98 -> -776.42 | Q98: =SUBTOTAL(9,$F$2:F98) -> 33695.42 | R98: =SUBTOTAL(9,$G$2:G98) -> 32919
A99: 05 | B99: 43383 | C99: גרהם אסקין | H99: 6000 | J99: y | K99: גרהם אסקין | L99: 69 | N99: Y | P99: =R99-Q99 -> -776.42 | Q99: =SUBTOTAL(9,$F$2:F99) -> 33695.42 | R99: =SUBTOTAL(9,$G$2:G99) -> 32919
A100: 05 | B100: 43383 | C100: תיקון דלת | F100: 212 | I100: cc | J100: y | K100: חיים מנעולים | L100: 8886 | N100: Y | P100: =R100-Q100 -> -988.42 | Q100: =SUBTOTAL(9,$F$2:F100) -> 33907.42 | R100: =SUBTOTAL(9,$G$2:G100) -> 32919
...

Sheet c4 EX
A1: Prop ID | B1: Date | C1: Section | D1: Notes | E1: Type | F1: Amount | G1: Inflow | H1: He/She paid | I1: Method | J1: Reconciled | K1: Company | L1: Reciept | M1: Rental income | N1: Reported | O1: Report sent | P1: Balance | Q1: Total Amount | R1: Total Inflow
A2: C4 | B2: 44131 | C2: נייר טואלט | F2: 99.6 | I2: cc | J2: y | K2: הנדלר | L2: 971 | N2: Y | P2: =R2-Q2 -> -99.6 | Q2: =SUBTOTAL(9,$F$2:F2) -> 99.6 | R2: =SUBTOTAL(9,$G$2:G2) -> 0
A3: C4 | B3: 44132 | C3: Pre paid | G3: 3600 | N3: Y | P3: =R3-Q3 -> 3500.4 | Q3: =SUBTOTAL(9,$F$2:F3) -> 99.6 | R3: =SUBTOTAL(9,$G$2:G3) -> 3600
A4: C4 | B4: 44139 | C4: מחסנית סיליפוס | F4: 370 | I4: cc | J4: y | K4: עמיעד | L4: 8131 | N4: Y | P4: =R4-Q4 -> 3130.4 | Q4: =SUBTOTAL(9,$F$2:F4) -> 469.6 | R4: =SUBTOTAL(9,$G$2:G4) -> 3600
A5: C4 | B5: 44144 | C5: גינון | F5: 2400 | I5: מזומן | J5: y | N5: Y | P5: =R5-Q5 -> 730.4 | Q5: =SUBTOTAL(9,$F$2:F5) -> 2869.6 | R5: =SUBTOTAL(9,$G$2:G5) -> 3600
A6: C4 | B6: 44172 | C6: גינון | F6: 2200 | I6: מזומן | J6: y | N6: Y | P6: =R6-Q6 -> -1469.6 | Q6: =SUBTOTAL(9,$F$2:F6) -> 5069.6 | R6: =SUBTOTAL(9,$G$2:G6) -> 3600
A7: C4 | B7: 44173 | C7: Cleaning november | F7: 535.78 | I7: t | J7: y | N7: Y | P7: =R7-Q7 -> -2005.38 | Q7: =SUBTOTAL(9,$F$2:F7) -> 5605.38 | R7: =SUBTOTAL(9,$G$2:G7) -> 3600
A8: C4 | B8: 44173 | C8: pensia Cleaning november | F8: 105.52 | I8: t | J8: y | N8: Y | P8: =R8-Q8 -> -2110.9 | Q8: =SUBTOTAL(9,$F$2:F8) -> 5710.9 | R8: =SUBTOTAL(9,$G$2:G8) -> 3600
A9: C4 | B9: 44173 | C9: תשלום | G9: 5000 | I9: t | J9: y | N9: Y | P9: =R9-Q9 -> 2889.1 | Q9: =SUBTOTAL(9,$F$2:F9) -> 5710.9 | R9: =SUBTOTAL(9,$G$2:G9) -> 8600
A10: C4 | B10: 44185 | C10: Bituach Leumi cleaner Nov | F10: 42.78 | I10: t | J10: y | N10: Y | P10: =R10-Q10 -> 2846.32 | Q10: =SUBTOTAL(9,$F$2:F10) -> 5753.68 | R10: =SUBTOTAL(9,$G$2:G10) -> 8600
A11: C4 | B11: 44200 | C11: גנן ותיקון מכונת כביסה | F11: 1300 | I11: cash | J11: y | N11: Y | P11: =R11-Q11 -> 1546.32 | Q11: =SUBTOTAL(9,$F$2:F11) -> 7053.68 | R11: =SUBTOTAL(9,$G$2:G11) -> 8600
A12: C4 | B12: 44203 | C12: Cleaning dec | F12: 1161.96 | I12: t | J12: y | N12: Y | P12: =R12-Q12 -> 384.36 | Q12: =SUBTOTAL(9,$F$2:F12) -> 8215.64 | R12: =SUBTOTAL(9,$G$2:G12) -> 8600
A13: C4 | B13: 44203 | C13: pensia Cleaning dec | F13: 225.12 | I13: t | J13: y | N13: Y | P13: =R13-Q13 -> 159.24 | Q13: =SUBTOTAL(9,$F$2:F13) -> 8440.76 | R13: =SUBTOTAL(9,$G$2:G13) -> 8600
A14: C4 | B14: 44216 | C14: Bituach Leumi cleaner Dec | F14: 93.4 | I14: t | J14: y | N14: Y | P14: =R14-Q14 -> 65.84 | Q14: =SUBTOTAL(9,$F$2:F14) -> 8534.16 | R14: =SUBTOTAL(9,$G$2:G14) -> 8600
A15: C4 | B15: 44228 | C15: מתלה לקיר | F15: 29.9 | I15: cc | J15: y | K15: סופר דיל | L15: 230 | N15: Y | P15: =R15-Q15 -> 35.94 | Q15: =SUBTOTAL(9,$F$2:F15) -> 8564.06 | R15: =SUBTOTAL(9,$G$2:G15) -> 8600
A16: C4 | B16: 44232 | C16: Advance | G16: 6000 | I16: t | J16: y | N16: Y | P16: =R16-Q16 -> 6035.94 | Q16: =SUBTOTAL(9,$F$2:F16) -> 8564.06 | R16: =SUBTOTAL(9,$G$2:G16) -> 14600
A17: C4 | B17: 44234 | C17: Cleaning jan | F17: 395.08 | I17: t | J17: y | N17: Y | P17: =R17-Q17 -> 5640.86 | Q17: =SUBTOTAL(9,$F$2:F17) -> 8959.14 | R17: =SUBTOTAL(9,$G$2:G17) -> 14600
A18: C4 | B18: 44234 | C18: pensia Cleaning jan | F18: 76.72 | I18: t | J18: y | N18: Y | P18: =R18-Q18 -> 5564.14 | Q18: =SUBTOTAL(9,$F$2:F18) -> 9035.86 | R18: =SUBTOTAL(9,$G$2:G18) -> 14600
A19: C4 | B19: 44236 | C19: גינון | F19: 1800 | I19: cash | J19: y | N19: Y | P19: =R19-Q19 -> 3764.14 | Q19: =SUBTOTAL(9,$F$2:F19) -> 10835.86 | R19: =SUBTOTAL(9,$G$2:G19) -> 14600
A20: C4 | B20: 44246 | C20: חומרי ניקיון | F20: 227.5 | I20: באפר | K20: שופרסל | L20: 9569 | N20: Y | P20: =R20-Q20 -> 3536.64 | Q20: =SUBTOTAL(9,$F$2:F20) -> 11063.36 | R20: =SUBTOTAL(9,$G$2:G20) -> 14600
A21: C4 | B21: 44247 | C21: Bituach Leumi cleaner Jan | F21: 31.34 | I21: t | J21: y | N21: Y | P21: =R21-Q21 -> 3505.3 | Q21: =SUBTOTAL(9,$F$2:F21) -> 11094.7 | R21: =SUBTOTAL(9,$G$2:G21) -> 14600
A22: C4 | B22: 44256 | C22: גינון | F22: 1200 | I22: cash | J22: y | N22: Y | P22: =R22-Q22 -> 2305.3 | Q22: =SUBTOTAL(9,$F$2:F22) -> 12294.7 | R22: =SUBTOTAL(9,$G$2:G22) -> 14600
A23: C4 | B23: 44259 | C23: Cleaning March | F23: 950.96 | N23: Y | P23: =R23-Q23 -> 1354.34 | Q23: =SUBTOTAL(9,$F$2:F23) -> 13245.66 | R23: =SUBTOTAL(9,$G$2:G23) -> 14600
A24: C4 | B24: 44259 | C24: pensia Cleaning March | F24: 182.15 | N24: Y | P24: =R24-Q24 -> 1172.19 | Q24: =SUBTOTAL(9,$F$2:F24) -> 13427.81 | R24: =SUBTOTAL(9,$G$2:G24) -> 14600
A25: C4 | B25: 44264 | C25: בדיקת מכונת כביסה | F25: 350 | I25: t | J25: y | K25: ירון דריקס | L25: 5410 | N25: Y | P25: =R25-Q25 -> 822.19 | Q25: =SUBTOTAL(9,$F$2:F25) -> 13777.81 | R25: =SUBTOTAL(9,$G$2:G25) -> 14600
A26: C4 | B26: 44267 | C26: תנור אמבטיה | F26: 89 | K26: טלראן | N26: Y | P26: =R26-Q26 -> 733.19 | Q26: =SUBTOTAL(9,$F$2:F26) -> 13866.81 | R26: =SUBTOTAL(9,$G$2:G26) -> 14600
A27: C4 | B27: 44271 | C27: החלפת טרמוסטט וגוף חימום | F27: 1228 | I27: t | J27: y | K27: עוז אגסי | L27: 4317 | N27: Y | P27: =R27-Q27 -> -494.81 | Q27: =SUBTOTAL(9,$F$2:F27) -> 15094.81 | R27: =SUBTOTAL(9,$G$2:G27) -> 14600
A28: C4 | B28: 44271 | C28: תיקון תריס חשמלי | F28: 527 | I28: t | J28: y | K28: צביקה | L28: 50118 | N28: Y | P28: =R28-Q28 -> -1021.81 | Q28: =SUBTOTAL(9,$F$2:F28) -> 15621.81 | R28: =SUBTOTAL(9,$G$2:G28) -> 14600
A29: C4 | B29: 44272 | C29: סופר דיל | F29: 19.9 | I29: cc | J29: y | N29: Y | P29: =R29-Q29 -> -1041.71 | Q29: =SUBTOTAL(9,$F$2:F29) -> 15641.71 | R29: =SUBTOTAL(9,$G$2:G29) -> 14600
A30: C4 | B30: 44275 | C30: Bituach Leumi cleaner March | F30: 74.74 | N30: Y | P30: =R30-Q30 -> -1116.45 | Q30: =SUBTOTAL(9,$F$2:F30) -> 15716.45 | R30: =SUBTOTAL(9,$G$2:G30) -> 14600
A31: C4 | B31: 44293 | C31: Cleaning mer | F31: 1228 | I31: t | J31: y | N31: Y | P31: =R31-Q31 -> -2344.45 | Q31: =SUBTOTAL(9,$F$2:F31) -> 16944.45 | R31: =SUBTOTAL(9,$G$2:G31) -> 14600
A32: C4 | B32: 44297 | C32: Advance | G32: 12000 | I32: t | J32: y | N32: Y | P32: =R32-Q32 -> 9655.55 | Q32: =SUBTOTAL(9,$F$2:F32) -> 16944.45 | R32: =SUBTOTAL(9,$G$2:G32) -> 26600
A33: C4 | B33: 44298 | C33: pensia Cleaning mer | F33: 252.95 | I33: t | J33: y | N33: Y | P33: =R33-Q33 -> 9402.6 | Q33: =SUBTOTAL(9,$F$2:F33) -> 17197.4 | R33: =SUBTOTAL(9,$G$2:G33) -> 26600
A34: C4 | B34: 44298 | C34: גינון | F34: 6000 | I34: cash | J34: y | N34: Y | P34: =R34-Q34 -> 3402.6 | Q34: =SUBTOTAL(9,$F$2:F34) -> 23197.4 | R34: =SUBTOTAL(9,$G$2:G34) -> 26600
A35: C4 | B35: 44306 | C35: Bituach Leumi cleaner Mar | F35: 141.89 | I35: t | J35: y | N35: Y | P35: =R35-Q35 -> 3260.71 | Q35: =SUBTOTAL(9,$F$2:F35) -> 23339.29 | R35: =SUBTOTAL(9,$G$2:G35) -> 26600
A36: C4 | B36: 44318 | C36: איזולירבנד | F36: 49 | I36: cc | J36: y | K36: בנדק | N36: Y | P36: =R36-Q36 -> 3211.71 | Q36: =SUBTOTAL(9,$F$2:F36) -> 23388.29 | R36: =SUBTOTAL(9,$G$2:G36) -> 26600
A37: C4 | B37: 44322 | C37: Cleaning april | F37: 1255.64 | N37: Y | P37: =R37-Q37 -> 1956.07 | Q37: =SUBTOTAL(9,$F$2:F37) -> 24643.93 | R37: =SUBTOTAL(9,$G$2:G37) -> 26600
A38: C4 | B38: 44322 | C38: pensia Cleaning april | F38: 244.64 | N38: Y | P38: =R38-Q38 -> 1711.43 | Q38: =SUBTOTAL(9,$F$2:F38) -> 24888.57 | R38: =SUBTOTAL(9,$G$2:G38) -> 26600
A39: C4 | B39: 44325 | C39: גינון | F39: 6000 | I39: cash | J39: ט | N39: Y | P39: =R39-Q39 -> -4288.57 | Q39: =SUBTOTAL(9,$F$2:F39) -> 30888.57 | R39: =SUBTOTAL(9,$G$2:G39) -> 26600
A40: C4 | B40: 44326 | C40: פילטר | F40: 530 | I40: cc | K40: מנדלסון | L40: 2712 | N40: Y | P40: =R40-Q40 -> -4818.57 | Q40: =SUBTOTAL(9,$F$2:F40) -> 31418.57 | R40: =SUBTOTAL(9,$G$2:G40) -> 26600
A41: C4 | B41: 44336 | C41: Bituach Leumi cleaner - Apr | F41: 99.82 | N41: Y | P41: =R41-Q41 -> -4918.39 | Q41: =SUBTOTAL(9,$F$2:F41) -> 31518.39 | R41: =SUBTOTAL(9,$G$2:G41) -> 26600
A42: C4 | B42: 44336 | C42: אשר ברינבאום תיקון תריס | F42: 292 | I42: t | J42: y | K42: אשר בירנבאום | L42: 911 | N42: Y | P42: =R42-Q42 -> -5210.39 | Q42: =SUBTOTAL(9,$F$2:F42) -> 31810.39 | R42: =SUBTOTAL(9,$G$2:G42) -> 26600
A43: C4 | B43: 44348 | C43: עדי מזרחי הדברה | F43: 877.5 | I43: t | J43: y | K43: עדי מזרחי | L43: 4039 | N43: Y | P43: =R43-Q43 -> -6087.89 | Q43: =SUBTOTAL(9,$F$2:F43) -> 32687.89 | R43: =SUBTOTAL(9,$G$2:G43) -> 26600
A44: C4 | B44: 44349 | C44: גינון | F44: 1200 | I44: cash | N44: Y | P44: =R44-Q44 -> -7287.89 | Q44: =SUBTOTAL(9,$F$2:F44) -> 33887.89 | R44: =SUBTOTAL(9,$G$2:G44) -> 26600
A45: C4 | B45: 44355 | C45: Cleaning may | F45: 1185.27 | N45: Y | P45: =R45-Q45 -> -8473.16 | Q45: =SUBTOTAL(9,$F$2:F45) -> 35073.16 | R45: =SUBTOTAL(9,$G$2:G45) -> 26600
A46: C4 | B46: 44355 | C46: pensia Cleaning may | F46: 230.28 | N46: Y | P46: =R46-Q46 -> -8703.44 | Q46: =SUBTOTAL(9,$F$2:F46) -> 35303.44 | R46: =SUBTOTAL(9,$G$2:G46) -> 26600
A47: C4 | B47: 44355 | C47: טיב טעם חומרי ניקוי | F47: 20.9 | I47: cc | J47: y | K47: טיב טעם | L47: 6733 | N47: Y | P47: =R47-Q47 -> -8724.34 | Q47: =SUBTOTAL(9,$F$2:F47) -> 35324.34 | R47: =SUBTOTAL(9,$G$2:G47) -> 26600
A48: C4 | B48: 44362 | C48: חשמל ישיר פנל לד | F48: 19 | I48: cc | J48: y | L48: 7313 | N48: Y | P48: =R48-Q48 -> -8743.34 | Q48: =SUBTOTAL(9,$F$2:F48) -> 35343.34 | R48: =SUBTOTAL(9,$G$2:G48) -> 26600
A49: C4 | B49: 44367 | C49: Advance | G49: 13000 | I49: t | J49: y | N49: Y | P49: =R49-Q49 -> 4256.66 | Q49: =SUBTOTAL(9,$F$2:F49) -> 35343.34 | R49: =SUBTOTAL(9,$G$2:G49) -> 39600
A50: C4 | B50: 44367 | C50: Bituach Leumi cleaner May | F50: 93.87 | N50: Y | P50: =R50-Q50 -> 4162.79 | Q50: =SUBTOTAL(9,$F$2:F50) -> 35437.21 | R50: =SUBTOTAL(9,$G$2:G50) -> 39600
A51: C4 | B51: 44367 | C51: מגבות | F51: 65.9 | I51: cc | J51: y | K51: שפע הברון | L51: 375 | N51: Y | P51: =R51-Q51 -> 4096.89 | Q51: =SUBTOTAL(9,$F$2:F51) -> 35503.11 | R51: =SUBTOTAL(9,$G$2:G51) -> 39600
A52: C4 | B52: 44367 | C52: תן גז | F52: 130 | I52: cc | J52: y | L52: 4085 | N52: Y | P52: =R52-Q52 -> 3966.89 | Q52: =SUBTOTAL(9,$F$2:F52) -> 35633.11 | R52: =SUBTOTAL(9,$G$2:G52) -> 39600
A53: C4 | B53: 44375 | C53: אינסטלטור | F53: 351 | I53: t | J53: y | K53: משה רוזנס | L53: 243 | N53: Y | P53: =R53-Q53 -> 3615.89 | Q53: =SUBTOTAL(9,$F$2:F53) -> 35984.11 | R53: =SUBTOTAL(9,$G$2:G53) -> 39600
A54: C4 | B54: 44383 | C54: תן גז | F54: 130 | I54: cc | J54: y | K54: תן גז | L54: 14249 | N54: Y | P54: =R54-Q54 -> 3485.89 | Q54: =SUBTOTAL(9,$F$2:F54) -> 36114.11 | R54: =SUBTOTAL(9,$G$2:G54) -> 39600
A55: C4 | B55: 44388 | C55: Cleaning 6.21 | F55: 508.98 | N55: Y | P55: =R55-Q55 -> 2976.91 | Q55: =SUBTOTAL(9,$F$2:F55) -> 36623.09 | R55: =SUBTOTAL(9,$G$2:G55) -> 39600
A56: C4 | B56: 44388 | C56: pensia Cleaning 6.21 | F56: 95.76 | N56: Y | P56: =R56-Q56 -> 2881.15 | Q56: =SUBTOTAL(9,$F$2:F56) -> 36718.85 | R56: =SUBTOTAL(9,$G$2:G56) -> 39600
A57: C4 | B57: 44388 | C57: גבריאלה | F57: 134.99 | N57: Y | P57: =R57-Q57 -> 2746.16 | Q57: =SUBTOTAL(9,$F$2:F57) -> 36853.84 | R57: =SUBTOTAL(9,$G$2:G57) -> 39600
A58: C4 | B58: 44392 | C58: ניקיון | F58: 2235 | I58: t | J58: y | K58: סטניסלב מישייב | L58: 1037 | N58: Y | P58: =R58-Q58 -> 511.16 | Q58: =SUBTOTAL(9,$F$2:F58) -> 39088.84 | R58: =SUBTOTAL(9,$G$2:G58) -> 39600
A59: C4 | B59: 44397 | C59: Bituach Leumi cleaner Jun | F59: 39.66 | N59: Y | P59: =R59-Q59 -> 471.5 | Q59: =SUBTOTAL(9,$F$2:F59) -> 39128.5 | R59: =SUBTOTAL(9,$G$2:G59) -> 39600
A60: C4 | B60: 44402 | C60: גינון | F60: 2500 | I60: cash | J60: y | N60: Y | P60: =R60-Q60 -> -2028.5 | Q60: =SUBTOTAL(9,$F$2:F60) -> 41628.5 | R60: =SUBTOTAL(9,$G$2:G60) -> 39600
A61: C4 | B61: 44405 | C61: אשר ברינבאום | F61: 234 | I61: t | J61: y | K61: אשר בירנבאום | L61: 932 | N61: Y | P61: =R61-Q61 -> -2262.5 | Q61: =SUBTOTAL(9,$F$2:F61) -> 41862.5 | R61: =SUBTOTAL(9,$G$2:G61) -> 39600
A62: C4 | B62: 44419 | C62: Cleaning jul | F62: 465.22 | N62: Y | P62: =R62-Q62 -> -2727.72 | Q62: =SUBTOTAL(9,$F$2:F62) -> 42327.72 | R62: =SUBTOTAL(9,$G$2:G62) -> 39600
A63: C4 | B63: 44419 | C63: הבראה | F63: 91.71 | N63: Y | P63: =R63-Q63 -> -2819.43 | Q63: =SUBTOTAL(9,$F$2:F63) -> 42419.43 | R63: =SUBTOTAL(9,$G$2:G63) -> 39600
A64: C4 | B64: 44419 | C64: טיב טעם | F64: 19.9 | I64: cc | J64: y | L64: 6444 | N64: Y | P64: =R64-Q64 -> -2839.33 | Q64: =SUBTOTAL(9,$F$2:F64) -> 42439.33 | R64: =SUBTOTAL(9,$G$2:G64) -> 39600
A65: C4 | B65: 44419 | C65: טיב טעם | F65: 22.2 | I65: cc | J65: y | L65: 6454 | N65: Y | P65: =R65-Q65 -> -2861.53 | Q65: =SUBTOTAL(9,$F$2:F65) -> 42461.53 | R65: =SUBTOTAL(9,$G$2:G65) -> 39600
A66: C4 | B66: 44420 | C66: pensia Cleaning jul | F66: 91.82 | N66: Y | P66: =R66-Q66 -> -2953.35 | Q66: =SUBTOTAL(9,$F$2:F66) -> 42553.35 | R66: =SUBTOTAL(9,$G$2:G66) -> 39600
A67: C4 | B67: 44424 | C67: גינון | F67: 1500 | I67: cash | J67: y | N67: Y | P67: =R67-Q67 -> -4453.35 | Q67: =SUBTOTAL(9,$F$2:F67) -> 44053.35 | R67: =SUBTOTAL(9,$G$2:G67) -> 39600
A68: C4 | B68: 44428 | C68: Bituach Leumi cleaner Jul | F68: 43.51 | N68: Y | P68: =R68-Q68 -> -4496.86 | Q68: =SUBTOTAL(9,$F$2:F68) -> 44096.86 | R68: =SUBTOTAL(9,$G$2:G68) -> 39600
A69: C4 | B69: 44428 | C69: ביטוח לאומי הבראה | F69: 20.42 | N69: Y | P69: =R69-Q69 -> -4517.28 | Q69: =SUBTOTAL(9,$F$2:F69) -> 44117.28 | R69: =SUBTOTAL(9,$G$2:G69) -> 39600
A70: C4 | B70: 44430 | C70: Cleaning supplies | F70: 282 | I70: יקירה שילמה והעברנו לה כסף | J70: y | K70: טיב טעם | L70: 8095 | N70: Y | P70: =R70-Q70 -> -4799.28 | Q70: =SUBTOTAL(9,$F$2:F70) -> 44399.28 | R70: =SUBTOTAL(9,$G$2:G70) -> 39600
A71: C4 | B71: 44431 | C71: cleaning july | F71: 2644 | I71: t | J71: y | K71: סטניסלב מישייב | L71: 1145 | N71: Y | P71: =R71-Q71 -> -7443.28 | Q71: =SUBTOTAL(9,$F$2:F71) -> 47043.28 | R71: =SUBTOTAL(9,$G$2:G71) -> 39600
A72: C4 | B72: 44441 | C72: Advance | G72: 10000 | N72: Y | P72: =R72-Q72 -> 2556.72 | Q72: =SUBTOTAL(9,$F$2:F72) -> 47043.28 | R72: =SUBTOTAL(9,$G$2:G72) -> 49600
A73: C4 | B73: 44448 | C73: yekira salary | F73: 193.97 | N73: Y | P73: =R73-Q73 -> 2362.75 | Q73: =SUBTOTAL(9,$F$2:F73) -> 47237.25 | R73: =SUBTOTAL(9,$G$2:G73) -> 49600
A74: C4 | B74: 44449 | C74: Cleaner Elena Aug | F74: 742.49 | N74: Y | P74: =R74-Q74 -> 1620.26 | Q74: =SUBTOTAL(9,$F$2:F74) -> 47979.74 | R74: =SUBTOTAL(9,$G$2:G74) -> 49600
A75: C4 | B75: 44454 | C75: Pension Elena Aug | F75: 146.6 | N75: Y | P75: =R75-Q75 -> 1473.66 | Q75: =SUBTOTAL(9,$F$2:F75) -> 48126.34 | R75: =SUBTOTAL(9,$G$2:G75) -> 49600
A76: C4 | B76: 44456 | C76: eli mechani | F76: 200 | N76: Y | P76: =R76-Q76 -> 1273.66 | Q76: =SUBTOTAL(9,$F$2:F76) -> 48326.34 | R76: =SUBTOTAL(9,$G$2:G76) -> 49600
A77: C4 | B77: 44458 | C77: gardener | F77: 1200 | I77: cash | N77: Y | P77: =R77-Q77 -> 73.66 | Q77: =SUBTOTAL(9,$F$2:F77) -> 49526.34 | R77: =SUBTOTAL(9,$G$2:G77) -> 49600
A78: C4 | B78: 44459 | C78: Bituach Leumi Elena Aug | F78: 82.78 | N78: Y | P78: =R78-Q78 -> -9.12 | Q78: =SUBTOTAL(9,$F$2:F78) -> 49609.12 | R78: =SUBTOTAL(9,$G$2:G78) -> 49600
A79: C4 | B79: 44461 | C79: Cleanliness | F79: 1217 | I79: t | J79: y | K79: סטניסלב מישייב | L79: 1254 | N79: Y | P79: =R79-Q79 -> -1226.12 | Q79: =SUBTOTAL(9,$F$2:F79) -> 50826.12 | R79: =SUBTOTAL(9,$G$2:G79) -> 49600
A80: C4 | B80: 44480 | C80: Cleaner Elena Sep | F80: 833.56 | N80: Y | P80: =R80-Q80 -> -2059.68 | Q80: =SUBTOTAL(9,$F$2:F80) -> 51659.68 | R80: =SUBTOTAL(9,$G$2:G80) -> 49600
A81: C4 | B81: 44480 | C81: yekira salary | F81: 447.81 | N81: Y | P81: =R81-Q81 -> -2507.49 | Q81: =SUBTOTAL(9,$F$2:F81) -> 52107.49 | R81: =SUBTOTAL(9,$G$2:G81) -> 49600
A82: C4 | B82: 44482 | C82: Pension Elena Sep | F82: 158.69 | N82: Y | P82: =R82-Q82 -> -2666.18 | Q82: =SUBTOTAL(9,$F$2:F82) -> 52266.18 | R82: =SUBTOTAL(9,$G$2:G82) -> 49600
A83: C4 | B83: 44488 | C83: Cleaning | F83: 527 | I83: t | J83: y | K83: סטניסלב מישייב | L83: 1311 | N83: Y | P83: =R83-Q83 -> -3193.18 | Q83: =SUBTOTAL(9,$F$2:F83) -> 52793.18 | R83: =SUBTOTAL(9,$G$2:G83) -> 49600
A84: C4 | B84: 44489 | C84: Bituach Leumi cleaner Sep | F84: 68.38 | N84: Y | O84: 44495 | P84: =R84-Q84 -> -3261.56 | Q84: =SUBTOTAL(9,$F$2:F84) -> 52861.56 | R84: =SUBTOTAL(9,$G$2:G84) -> 49600
A85: C4 | B85: 44509 | C85: Batteries | F85: 34 | I85: cc | K85: חשמל ישיר | L85: 13284 | N85: Y | P85: =R85-Q85 -> -3295.56 | Q85: =SUBTOTAL(9,$F$2:F85) -> 52895.56 | R85: =SUBTOTAL(9,$G$2:G85) -> 49600
A86: C4 | B86: 44515 | C86: Armchair Transport | F86: 600 | I86: cc | J86: y | K86: ציון הובלות | N86: Y | P86: =R86-Q86 -> -3895.56 | Q86: =SUBTOTAL(9,$F$2:F86) -> 53495.56 | R86: =SUBTOTAL(9,$G$2:G86) -> 49600
A87: C4 | B87: 44515 | C87: Upholstery | F87: 1404 | I87: t | K87: סולימן ראיד | L87: 84/1 | N87: Y | P87: =R87-Q87 -> -5299.56 | Q87: =SUBTOTAL(9,$F$2:F87) -> 54899.56 | R87: =SUBTOTAL(9,$G$2:G87) -> 49600
A88: C4 | B88: 44532 | C88: Sewage works | H88: 29367 | K88: בדר סאלח | L88: 145 | N88: Y | P88: =R88-Q88 -> -5299.56 | Q88: =SUBTOTAL(9,$F$2:F88) -> 54899.56 | R88: =SUBTOTAL(9,$G$2:G88) -> 49600
A89: C4 | B89: 44539 | C89: Cleaning Nov 2021 | D89: Elena | F89: 442 | N89: Y | P89: =R89-Q89 -> -5741.56 | Q89: =SUBTOTAL(9,$F$2:F89) -> 55341.56 | R89: =SUBTOTAL(9,$G$2:G89) -> 49600
A90: C4 | B90: 44540 | C90: Electrical lock repair | F90: 409 | I90: t | K90: אשר בירנבאום | L90: 1029 | N90: Y | P90: =R90-Q90 -> -6150.56 | Q90: =SUBTOTAL(9,$F$2:F90) -> 55750.56 | R90: =SUBTOTAL(9,$G$2:G90) -> 49600
A91: C4 | B91: 44545 | C91: Pension cleaning Nov 2021 | D91: Elena | F91: 86 | N91: Y | O91: 44536 | P91: =R91-Q91 -> -6236.56 | Q91: =SUBTOTAL(9,$F$2:F91) -> 55836.56 | R91: =SUBTOTAL(9,$G$2:G91) -> 49600
A92: C4 | B92: 44550 | C92: Advance | G92: 15000 | N92: Y | P92: =R92-Q92 -> 8763.44 | Q92: =SUBTOTAL(9,$F$2:F92) -> 55836.56 | R92: =SUBTOTAL(9,$G$2:G92) -> 64600
A93: C4 | B93: 44550 | C93: Bituach Leumi cleaning Nov 2021 | D93: Elena | F93: 35 | N93: Y | P93: =R93-Q93 -> 8728.44 | Q93: =SUBTOTAL(9,$F$2:F93) -> 55871.56 | R93: =SUBTOTAL(9,$G$2:G93) -> 64600
A94: C4 | B94: 44551 | C94: Management Sandi | F94: 4914 | N94: Y | P94: =R94-Q94 -> 3814.44 | Q94: =SUBTOTAL(9,$F$2:F94) -> 60785.56 | R94: =SUBTOTAL(9,$G$2:G94) -> 64600
A95: C4 | B95: 44564 | C95: Cleaning December 2021 | D95: סטניסלב - 21/12/21 + 27/12/21 | F95: 2469 | I95: t | K95: סטניסלב מישייב | L95: 1696 | N95: Y | P95: =R95-Q95 -> 1345.44 | Q95: =SUBTOTAL(9,$F$2:F95) -> 63254.56 | R95: =SUBTOTAL(9,$G$2:G95) -> 64600
A96: C4 | B96: 44588 | C96: Replacement of heating element | F96: 350 | I96: t | K96: עוז אגסי | L96: 4629 | N96: Y | P96: =R96-Q96 -> 995.44 | Q96: =SUBTOTAL(9,$F$2:F96) -> 63604.56 | R96: =SUBTOTAL(9,$G$2:G96) -> 64600
A97: C4 | B97: 44594 | C97: Cleaning January 2022 | D97: 4/1/22 - 16 + 18/1/22 - 6 | F97: 2059 | K97: סטניסלב מישייב | L97: 1811 | N97: Y | O97: 44619 | P97: =R97-Q97 -> -1063.56 | Q97: =SUBTOTAL(9,$F$2:F97) -> 65663.56 | R97: =SUBTOTAL(9,$G$2:G97) -> 64600
A98: C4 | B98: 44648 | C98: Cleaning supplies | F98: 110.3 | K98: טיב טעם | L98: 167367 | N98: Y | P98: =R98-Q98 -> -1173.86 | Q98: =SUBTOTAL(9,$F$2:F98) -> 65773.86 | R98: =SUBTOTAL(9,$G$2:G98) -> 64600
A99: C4 | B99: 44661 | C99: Bituach Leumi cleaning March 2022 | D99: Elena | F99: 61 | N99: Y | O99: 44661 | P99: =R99-Q99 -> -1234.86 | Q99: =SUBTOTAL(9,$F$2:F99) -> 65834.86 | R99: =SUBTOTAL(9,$G$2:G99) -> 64600
A100: C4 | B100: 44661 | C100: Cleaning March 2022 | D100: Elena | F100: 746 | N100: Y | P100: =R100-Q100 -> -1980.86 | Q100: =SUBTOTAL(9,$F$2:F100) -> 66580.86 | R100: =SUBTOTAL(9,$G$2:G100) -> 64600
...

Sheet 06
A1: Type | B1: Coment | C1: Name | D1: Company | E1: contract # | F1: Phone | G1: email | H1: customer # | I1: Meter # | J1: Payment method | L1: # Kriya | M1: wrranty | P1: model | Q1: serial #
A2: Personal | B2: Naomi and Eli Wurtman | E2: kfar Etzion 19 Jerusalem
A3: Personal | B3: Naomi | C3: 544872318
A4: Personal | B4: Eli
A8: contractor | B8: door | C8: Sagit | D8: next door | F8: 722400466 | G8: 054-5333956- yicel
A9: contractor | B9: kablan | C9: Ashraf | F9: 050-5566667
A10: contractor | B10: kablan | C10: Nassim | F10: 052-3718800
A11: contractor | B11: gardener | C11: Itamar | F11: 050-5517687
A12: appliance | B12: surge protector | D12: sherut mazor | F12: 04-6773000 | M12: 3 year warranty | O12: 42977 | P12: W85F44P/I
A13: appliance | B13: washing machine | D13: Gorenje | F13: 04-677300o

Sheet 09 ex
A1: Prop ID | B1: Date | C1: Section | D1: Notes | E1: Type | F1: Amount | G1: Inflow | H1: He/She paid | I1: Method | J1: Reconciled | K1: Company | L1: Reciept | M1: Rental income | N1: Reported | O1: Report sent | P1: Balance | Q1: Total Amount | R1: Total Inflow
A2: 09 | B2: 43671 | C2: Pre paid | G2: 1000 | I2: שק | J2: y | P2: =R2-Q2 -> 1000 | Q2: =SUBTOTAL(9,$F$2:F2) -> 0 | R2: =SUBTOTAL(9,$G$2:G2) -> 1000
A3: 09 | B3: 43724 | C3: Cleaning supplies | F3: 125.79 | I3: cc | J3: y | K3: הנדלר | L3: 11 | P3: =R3-Q3 -> 874.21 | Q3: =SUBTOTAL(9,$F$2:F3) -> 125.79 | R3: =SUBTOTAL(9,$G$2:G3) -> 1000
A4: 09 | B4: 43741 | C4: Cleaning September 2019 | F4: 113.79 | I4: t | J4: t | P4: =R4-Q4 -> 760.42 | Q4: =SUBTOTAL(9,$F$2:F4) -> 239.58 | R4: =SUBTOTAL(9,$G$2:G4) -> 1000
A5: 09 | B5: 43744 | C5: Pensia cleaning September 2019 | F5: 19.15 | I5: t | J5: y | P5: =R5-Q5 -> 741.27 | Q5: =SUBTOTAL(9,$F$2:F5) -> 258.73 | R5: =SUBTOTAL(9,$G$2:G5) -> 1000
A6: 09 | B6: 43758 | C6: Bituach Leumi cleaning September 2019 | F6: 7.8 | I6: t | J6: y | P6: =R6-Q6 -> 733.47 | Q6: =SUBTOTAL(9,$F$2:F6) -> 266.53 | R6: =SUBTOTAL(9,$G$2:G6) -> 1000
A7: 09 | B7: 43850 | C7: Food | F7: 35.24 | I7: cc | J7: y | P7: =R7-Q7 -> 698.23 | Q7: =SUBTOTAL(9,$F$2:F7) -> 301.77 | R7: =SUBTOTAL(9,$G$2:G7) -> 1000
A8: 09 | B8: 43867 | C8: Cleaning June 2020 | D8: Elena | F8: 207.54 | I8: t | J8: y | P8: =R8-Q8 -> 490.69 | Q8: =SUBTOTAL(9,$F$2:F8) -> 509.31 | R8: =SUBTOTAL(9,$G$2:G8) -> 1000
A9: 09 | B9: 43867 | C9: Pension cleaning June 2020 | D9: Elena | F9: 38.38 | I9: t | J9: y | P9: =R9-Q9 -> 452.31 | Q9: =SUBTOTAL(9,$F$2:F9) -> 547.69 | R9: =SUBTOTAL(9,$G$2:G9) -> 1000
A10: 09 | B10: 43870 | C10: Electrician | F10: 200 | I10: t | J10: y | K10: אבי קודיש | P10: =R10-Q10 -> 252.31 | Q10: =SUBTOTAL(9,$F$2:F10) -> 747.69 | R10: =SUBTOTAL(9,$G$2:G10) -> 1000
A11: 09 | B11: 43881 | C11: Bituach Leumi cleaning June 2020 | D11: Elena | F11: 15.71 | I11: t | J11: y | P11: =R11-Q11 -> 236.6 | Q11: =SUBTOTAL(9,$F$2:F11) -> 763.4 | R11: =SUBTOTAL(9,$G$2:G11) -> 1000
A12: 09 | B12: 44259 | C12: Cleaning Marchruary 2020 | D12: Elena | F12: 160.68 | I12: t | J12: y | P12: =R12-Q12 -> 75.92 | Q12: =SUBTOTAL(9,$F$2:F12) -> 924.08 | R12: =SUBTOTAL(9,$G$2:G12) -> 1000
A13: 09 | B13: 44275 | C13: Bituach Leumi cleaning Marchruary 2021 | D13: Elena | F13: 11.8 | I13: t | J13: y | P13: =R13-Q13 -> 64.12 | Q13: =SUBTOTAL(9,$F$2:F13) -> 935.88 | R13: =SUBTOTAL(9,$G$2:G13) -> 1000
A14: 09 | B14: 44298 | C14: Pension cleaning Marchruary 2021 | D14: Elena | F14: 28.76 | I14: t | J14: y | P14: =R14-Q14 -> 35.36 | Q14: =SUBTOTAL(9,$F$2:F14) -> 964.64 | R14: =SUBTOTAL(9,$G$2:G14) -> 1000
A15: 09 | B15: 44419 | C15: Cleaning July 2021 | D15: Elena | F15: 528.65 | P15: =R15-Q15 -> -493.29 | Q15: =SUBTOTAL(9,$F$2:F15) -> 1493.29 | R15: =SUBTOTAL(9,$G$2:G15) -> 1000
A16: 09 | B16: 44420 | C16: Pension cleaning July 2021 | D16: Elena | F16: 96.65 | P16: =R16-Q16 -> -589.94 | Q16: =SUBTOTAL(9,$F$2:F16) -> 1589.94 | R16: =SUBTOTAL(9,$G$2:G16) -> 1000
A17: 09 | B17: 44428 | C17: Bituach Leumi cleaning July 2021 | D17: Elena | F17: 45.8 | P17: =R17-Q17 -> -635.74 | Q17: =SUBTOTAL(9,$F$2:F17) -> 1635.74 | R17: =SUBTOTAL(9,$G$2:G17) -> 1000
A18: 09 | B18: 44456 | C18: Filter replacement | F18: 585 | K18: אשר ברינבאום | L18: 975 | P18: =R18-Q18 -> -1220.74 | Q18: =SUBTOTAL(9,$F$2:F18) -> 2220.74 | R18: =SUBTOTAL(9,$G$2:G18) -> 1000
A19: 09 | B19: 44468 | C19: Water bill | F19: 32.6 | I19: cc | J19: y | P19: =R19-Q19 -> -1253.34 | Q19: =SUBTOTAL(9,$F$2:F19) -> 2253.34 | R19: =SUBTOTAL(9,$G$2:G19) -> 1000
A20: 09 | B20: 44563 | C20: סגירת חשבון | G20: 1253.34

Sheet 06 ex
A1: Prop ID | B1: Date | C1: Section | D1: Notes | E1: Type | F1: Amount | G1: Inflow | H1: He/She paid | I1: Method | J1: Reconciled | K1: Company | L1: Reciept | M1: Rental income | N1: Reported | O1: Report sent | P1: Balance | Q1: Total Amount | R1: Total Inflow
A2: C6 | B2: 42936 | C2: prepaid | G2: 2000 | I2: transfer | J2: y | K2: MIP | L2: 95 | N2: Y | P2: =R2-Q2 -> 2000 | Q2: =SUBTOTAL(9,$F$2:F2) -> 0 | R2: =SUBTOTAL(9,$G$2:G2) -> 2000
A3: C6 | B3: 42941 | C3: toilet paper | F3: 34.9 | I3: cc | J3: y | K3: Bitan | L3: 163454 | N3: Y | P3: =R3-Q3 -> 1965.1 | Q3: =SUBTOTAL(9,$F$2:F3) -> 34.9 | R3: =SUBTOTAL(9,$G$2:G3) -> 2000
A4: C6 | B4: 42941 | C4: electtican | F4: 400 | I4: 5000094 | J4: y | K4: mesri | N4: Y | P4: =R4-Q4 -> 1565.1 | Q4: =SUBTOTAL(9,$F$2:F4) -> 434.9 | R4: =SUBTOTAL(9,$G$2:G4) -> 2000
A5: C6 | B5: 42946 | C5: cleaning | F5: 20 | J5: y | K5: ben | N5: Y | P5: =R5-Q5 -> 1545.1 | Q5: =SUBTOTAL(9,$F$2:F5) -> 454.9 | R5: =SUBTOTAL(9,$G$2:G5) -> 2000
A6: C6 | B6: 42947 | C6: exterminaor | F6: 700 | I6: transfer | J6: y | K6: Adi Hadbara | L6: 2492 | N6: Y | P6: =R6-Q6 -> 845.1 | Q6: =SUBTOTAL(9,$F$2:F6) -> 1154.9 | R6: =SUBTOTAL(9,$G$2:G6) -> 2000
A7: C6 | B7: 42950 | C7: tris repair | F7: 351 | I7: transfer | J7: y | K7: tzkia | L7: 40005 | N7: Y | P7: =R7-Q7 -> 494.1 | Q7: =SUBTOTAL(9,$F$2:F7) -> 1505.9 | R7: =SUBTOTAL(9,$G$2:G7) -> 2000
A8: C6 | B8: 42956 | C8: electrican | H8: 5000 | J8: y | K8: avi kosesh | L8: 223 | N8: Y | P8: =R8-Q8 -> 494.1 | Q8: =SUBTOTAL(9,$F$2:F8) -> 1505.9 | R8: =SUBTOTAL(9,$G$2:G8) -> 2000
A9: C6 | B9: 42977 | C9: surge protercor | F9: 480 | I9: cc | J9: y | K9: Sherut Mazaon | L9: 271047 | N9: Y | P9: =R9-Q9 -> 14.1 | Q9: =SUBTOTAL(9,$F$2:F9) -> 1985.9 | R9: =SUBTOTAL(9,$G$2:G9) -> 2000
A10: C6 | B10: 42989 | C10: ipardox app | F10: 71 | J10: y | K10: google play | L10: 3361-9825-2 | N10: Y | P10: =R10-Q10 -> -56.9 | Q10: =SUBTOTAL(9,$F$2:F10) -> 2056.9 | R10: =SUBTOTAL(9,$G$2:G10) -> 2000
A11: C6 | B11: 42990 | C11: prepaid | G11: 5000 | J11: y | K11: mip | L11: 108 | N11: Y | P11: =R11-Q11 -> 4943.1 | Q11: =SUBTOTAL(9,$F$2:F11) -> 2056.9 | R11: =SUBTOTAL(9,$G$2:G11) -> 7000
A12: C6 | B12: 42997 | C12: bird prevention | F12: 900 | I12: transfer | J12: y | K12: Danziman | L12: 50016 | N12: Y | P12: =R12-Q12 -> 4043.1 | Q12: =SUBTOTAL(9,$F$2:F12) -> 2956.9 | R12: =SUBTOTAL(9,$G$2:G12) -> 7000
A13: C6 | B13: 42997 | C13: a/c | F13: 960 | I13: transfer | J13: y | K13: mizug habaron | N13: Y | P13: =R13-Q13 -> 3083.1 | Q13: =SUBTOTAL(9,$F$2:F13) -> 3916.9 | R13: =SUBTOTAL(9,$G$2:G13) -> 7000
A14: C6 | B14: 43009 | C14: cleaning | F14: 250 | I14: cash | J14: y | K14: manny | N14: Y | P14: =R14-Q14 -> 2833.1 | Q14: =SUBTOTAL(9,$F$2:F14) -> 4166.9 | R14: =SUBTOTAL(9,$G$2:G14) -> 7000
A15: C6 | B15: 43018 | C15: cleaning 7-09-17 | F15: 702 | I15: transfer | J15: y | K15: talya | L15: 640 | N15: Y | P15: =R15-Q15 -> 2131.1 | Q15: =SUBTOTAL(9,$F$2:F15) -> 4868.9 | R15: =SUBTOTAL(9,$G$2:G15) -> 7000
A16: C6 | B16: 43031 | C16: Handyman buirds | F16: 549.9 | I16: transfer | J16: y | K16: tzvika | L16: 50022 | N16: Y | P16: =R16-Q16 -> 1581.2 | Q16: =SUBTOTAL(9,$F$2:F16) -> 5418.8 | R16: =SUBTOTAL(9,$G$2:G16) -> 7000
A17: C6 | B17: 43042 | C17: plumbing washing | F17: 125 | I17: transfer | J17: y | K17: samir | L17: 81 | N17: Y | P17: =R17-Q17 -> 1456.2 | Q17: =SUBTOTAL(9,$F$2:F17) -> 5543.8 | R17: =SUBTOTAL(9,$G$2:G17) -> 7000
A18: C6 | B18: 43044 | C18: gas balloon | F18: 130 | I18: cc | J18: y | K18: 10 gas | N18: Y | P18: =R18-Q18 -> 1326.2 | Q18: =SUBTOTAL(9,$F$2:F18) -> 5673.8 | R18: =SUBTOTAL(9,$G$2:G18) -> 7000
A19: C6 | B19: 43044 | C19: manny cleaning | F19: 250 | I19: cash | J19: y | K19: manny | N19: Y | P19: =R19-Q19 -> 1076.2 | Q19: =SUBTOTAL(9,$F$2:F19) -> 5923.8 | R19: =SUBTOTAL(9,$G$2:G19) -> 7000
A20: C6 | B20: 43063 | C20: cleaning of roof | F20: 800 | I20: cash | J20: y | K20: avis son | N20: Y | P20: =R20-Q20 -> 276.2 | Q20: =SUBTOTAL(9,$F$2:F20) -> 6723.8 | R20: =SUBTOTAL(9,$G$2:G20) -> 7000
A21: C6 | B21: 43066 | C21: prepaid | G21: 4000 | I21: transfer | J21: y | L21: 126 | N21: Y | P21: =R21-Q21 -> 4276.2 | Q21: =SUBTOTAL(9,$F$2:F21) -> 6723.8 | R21: =SUBTOTAL(9,$G$2:G21) -> 11000
A22: C6 | B22: 43073 | C22: electrican | F22: 4000 | I22: transfer | J22: y | K22: avi Kosesh | N22: Y | P22: =R22-Q22 -> 276.2 | Q22: =SUBTOTAL(9,$F$2:F22) -> 10723.8 | R22: =SUBTOTAL(9,$G$2:G22) -> 11000
A23: C6 | B23: 43109 | C23: prepaid | G23: 4212 | I23: transfer | J23: y | K23: mip | L23: 148 | N23: Y | P23: =R23-Q23 -> 4488.2 | Q23: =SUBTOTAL(9,$F$2:F23) -> 10723.8 | R23: =SUBTOTAL(9,$G$2:G23) -> 15212
A24: C6 | B24: 43137 | C24: cleaner 09-01-18 | F24: 320 | I24: transfer | J24: y | K24: elena | N24: Y | P24: =R24-Q24 -> 4168.2 | Q24: =SUBTOTAL(9,$F$2:F24) -> 11043.8 | R24: =SUBTOTAL(9,$G$2:G24) -> 15212
A25: C6 | B25: 43137 | C25: cleaner 09-01-18ביטוח לאומי | F25: 22.4 | J25: y | N25: Y | P25: =R25-Q25 -> 4145.8 | Q25: =SUBTOTAL(9,$F$2:F25) -> 11066.2 | R25: =SUBTOTAL(9,$G$2:G25) -> 15212
A26: C6 | B26: 43137 | C26: flunge | F26: 340 | I26: cc | J26: y | K26: Benidic | N26: Y | P26: =R26-Q26 -> 3805.8 | Q26: =SUBTOTAL(9,$F$2:F26) -> 11406.2 | R26: =SUBTOTAL(9,$G$2:G26) -> 15212
A27: C6 | B27: 43144 | C27: management fee | F27: 4212 | J27: y | N27: Y | P27: =R27-Q27 -> -406.2 | Q27: =SUBTOTAL(9,$F$2:F27) -> 15618.2 | R27: =SUBTOTAL(9,$G$2:G27) -> 15212
A28: C6 | B28: 43150 | C28: unblocking roof | F28: 409.5 | I28: transfer | J28: y | K28: samer | L28: 126 | N28: Y | P28: =R28-Q28 -> -815.7 | Q28: =SUBTOTAL(9,$F$2:F28) -> 16027.7 | R28: =SUBTOTAL(9,$G$2:G28) -> 15212
A29: C6 | B29: 43150 | C29: electrican | F29: 2150 | I29: transfer | J29: y | K29: avi | N29: Y | P29: =R29-Q29 -> -2965.7 | Q29: =SUBTOTAL(9,$F$2:F29) -> 18177.7 | R29: =SUBTOTAL(9,$G$2:G29) -> 15212
A30: C6 | B30: 43158 | C30: prepaid exp. | G30: 5000 | I30: transfer | J30: y | K30: mip | L30: 157 | N30: Y | P30: =R30-Q30 -> 2034.3 | Q30: =SUBTOTAL(9,$F$2:F30) -> 18177.7 | R30: =SUBTOTAL(9,$G$2:G30) -> 20212
A31: C6 | B31: 43172 | C31: Cleaning supplies | F31: 44.7 | I31: cc | J31: y | K31: מימון אור עקיבא | L31: 2095 | N31: Y | P31: =R31-Q31 -> 1989.6 | Q31: =SUBTOTAL(9,$F$2:F31) -> 18222.4 | R31: =SUBTOTAL(9,$G$2:G31) -> 20212
A32: C6 | B32: 43172 | C32: Cleaning supplies | F32: 28 | I32: cc | J32: y | K32: שופרסל | L32: 91722 | N32: Y | P32: =R32-Q32 -> 1961.6 | Q32: =SUBTOTAL(9,$F$2:F32) -> 18250.4 | R32: =SUBTOTAL(9,$G$2:G32) -> 20212
A33: C6 | B33: 43177 | C33: delivery | F33: 79 | I33: cc | J33: y | N33: Y | P33: =R33-Q33 -> 1882.6 | Q33: =SUBTOTAL(9,$F$2:F33) -> 18329.4 | R33: =SUBTOTAL(9,$G$2:G33) -> 20212
A34: C6 | B34: 43185 | C34: gardener | F34: 8300 | I34: 5000179 | J34: y | K34: אבעד | N34: Y | P34: =R34-Q34 -> -6417.4 | Q34: =SUBTOTAL(9,$F$2:F34) -> 26629.4 | R34: =SUBTOTAL(9,$G$2:G34) -> 20212
A35: C6 | B35: 43186 | C35: prepaid exp. | G35: 10000 | J35: y | K35: mip | L35: 169 | N35: Y | P35: =R35-Q35 -> 3582.6 | Q35: =SUBTOTAL(9,$F$2:F35) -> 26629.4 | R35: =SUBTOTAL(9,$G$2:G35) -> 30212
A36: C6 | B36: 43191 | C36: cleaning march 4 and 13 | F36: 640 | J36: y | N36: Y | P36: =R36-Q36 -> 2942.6 | Q36: =SUBTOTAL(9,$F$2:F36) -> 27269.4 | R36: =SUBTOTAL(9,$G$2:G36) -> 30212
A37: C6 | B37: 43191 | C37: bitucah leumi | F37: 45.78 | J37: y | N37: Y | P37: =R37-Q37 -> 2896.82 | Q37: =SUBTOTAL(9,$F$2:F37) -> 27315.18 | R37: =SUBTOTAL(9,$G$2:G37) -> 30212
A38: C6 | B38: 43200 | C38: cleening helena sep | F38: 602.73 | I38: transfer | J38: y | N38: Y | P38: =R38-Q38 -> 2294.09 | Q38: =SUBTOTAL(9,$F$2:F38) -> 27917.91 | R38: =SUBTOTAL(9,$G$2:G38) -> 30212
A39: C6 | B39: 43200 | C39: pensia sep | F39: 114.93 | I39: transfer | J39: y | N39: Y | P39: =R39-Q39 -> 2179.16 | Q39: =SUBTOTAL(9,$F$2:F39) -> 28032.84 | R39: =SUBTOTAL(9,$G$2:G39) -> 30212
A40: C6 | B40: 43202 | C40: a/c remote | F40: 200 | I40: transfer | J40: y | K40: yosi ben adiva | N40: Y | P40: =R40-Q40 -> 1979.16 | Q40: =SUBTOTAL(9,$F$2:F40) -> 28232.84 | R40: =SUBTOTAL(9,$G$2:G40) -> 30212
A41: C6 | B41: 43206 | C41: Cleaning supplies | F41: 7.9 | I41: cc | J41: y | K41: mega bair | L41: 2753 | N41: Y | P41: =R41-Q41 -> 1971.26 | Q41: =SUBTOTAL(9,$F$2:F41) -> 28240.74 | R41: =SUBTOTAL(9,$G$2:G41) -> 30212
A42: C6 | B42: 43220 | C42: stoper | F42: 58 | I42: cc | J42: y | K42: benedik | N42: Y | P42: =R42-Q42 -> 1913.26 | Q42: =SUBTOTAL(9,$F$2:F42) -> 28298.74 | R42: =SUBTOTAL(9,$G$2:G42) -> 30212
A43: C6 | B43: 43223 | C43: adbara | F43: 350 | I43: cc | J43: y | K43: magnor | N43: Y | P43: =R43-Q43 -> 1563.26 | Q43: =SUBTOTAL(9,$F$2:F43) -> 28648.74 | R43: =SUBTOTAL(9,$G$2:G43) -> 30212
A44: C6 | B44: 43226 | C44: tecnay gaz | F44: 100 | I44: cash | J44: y | N44: Y | P44: =R44-Q44 -> 1463.26 | Q44: =SUBTOTAL(9,$F$2:F44) -> 28748.74 | R44: =SUBTOTAL(9,$G$2:G44) -> 30212
A45: C6 | B45: 43229 | C45: cleaning | F45: 505 | I45: transfer | J45: y | N45: Y | P45: =R45-Q45 -> 958.26 | Q45: =SUBTOTAL(9,$F$2:F45) -> 29253.74 | R45: =SUBTOTAL(9,$G$2:G45) -> 30212
A46: C6 | B46: 43230 | C46: pensia elena | F46: 97 | I46: transfer | J46: y | N46: Y | P46: =R46-Q46 -> 861.26 | Q46: =SUBTOTAL(9,$F$2:F46) -> 29350.74 | R46: =SUBTOTAL(9,$G$2:G46) -> 30212
A47: C6 | B47: 43240 | C47: bitucah leumi | F47: 39 | J47: y | N47: Y | P47: =R47-Q47 -> 822.26 | Q47: =SUBTOTAL(9,$F$2:F47) -> 29389.74 | R47: =SUBTOTAL(9,$G$2:G47) -> 30212
A48: C6 | B48: 43241 | C48: adbara | F48: 1838 | I48: cc | J48: y | K48: מגנור | N48: Y | P48: =R48-Q48 -> -1015.74 | Q48: =SUBTOTAL(9,$F$2:F48) -> 31227.74 | R48: =SUBTOTAL(9,$G$2:G48) -> 30212
A49: C6 | B49: 43242 | C49: risos ekology2187 | F49: 2187 | I49: cc | J49: y | K49: verilife | L49: 7718 | N49: Y | P49: =R49-Q49 -> -3202.74 | Q49: =SUBTOTAL(9,$F$2:F49) -> 33414.74 | R49: =SUBTOTAL(9,$G$2:G49) -> 30212
A50: C6 | B50: 43248 | C50: norot | F50: 49 | I50: cc | J50: y | K50: בנדק | L50: 172512 | N50: Y | P50: =R50-Q50 -> -3251.74 | Q50: =SUBTOTAL(9,$F$2:F50) -> 33463.74 | R50: =SUBTOTAL(9,$G$2:G50) -> 30212
A51: C6 | B51: 43257 | C51: תיקונים | F51: 293 | I51: transfer | J51: y | K51: דנצימן | L51: 50046 | N51: Y | P51: =R51-Q51 -> -3544.74 | Q51: =SUBTOTAL(9,$F$2:F51) -> 33756.74 | R51: =SUBTOTAL(9,$G$2:G51) -> 30212
A52: C6 | B52: 43258 | C52: pay elena cleening may | F52: 340 | I52: transfer | J52: y | N52: Y | P52: =R52-Q52 -> -3884.74 | Q52: =SUBTOTAL(9,$F$2:F52) -> 34096.74 | R52: =SUBTOTAL(9,$G$2:G52) -> 30212
A53: C6 | B53: 43264 | C53: pensia elena may | F53: 57.58 | I53: transfer | J53: y | N53: Y | P53: =R53-Q53 -> -3942.32 | Q53: =SUBTOTAL(9,$F$2:F53) -> 34154.32 | R53: =SUBTOTAL(9,$G$2:G53) -> 30212
A54: C6 | B54: 43271 | C54: bitucah leumi may | F54: 23.07 | I54: transfer | J54: y | N54: Y | P54: =R54-Q54 -> -3965.39 | Q54: =SUBTOTAL(9,$F$2:F54) -> 34177.39 | R54: =SUBTOTAL(9,$G$2:G54) -> 30212
A55: C6 | B55: 43272 | C55: gardener | F55: 1300 | I55: 500190 | J55: y | K55: סאלם | N55: Y | P55: =R55-Q55 -> -5265.39 | Q55: =SUBTOTAL(9,$F$2:F55) -> 35477.39 | R55: =SUBTOTAL(9,$G$2:G55) -> 30212
A56: C6 | B56: 43276 | C56: pre pay | G56: 15000 | I56: transfer | J56: y | N56: Y | P56: =R56-Q56 -> 9734.61 | Q56: =SUBTOTAL(9,$F$2:F56) -> 35477.39 | R56: =SUBTOTAL(9,$G$2:G56) -> 45212
A57: C6 | B57: 43282 | C57: Cleaning | F57: 250 | I57: cash | J57: y | N57: Y | P57: =R57-Q57 -> 9484.61 | Q57: =SUBTOTAL(9,$F$2:F57) -> 35727.39 | R57: =SUBTOTAL(9,$G$2:G57) -> 45212
A58: C6 | B58: 43284 | C58: adbara | F58: 500 | I58: transfer | J58: y | K58: עדי מזרחי | L58: 2973 | N58: Y | P58: =R58-Q58 -> 8984.61 | Q58: =SUBTOTAL(9,$F$2:F58) -> 36227.39 | R58: =SUBTOTAL(9,$G$2:G58) -> 45212
A59: C6 | B59: 43307 | C59: תיקון - רשמנו חיוב פעמיים | G59: 2187 | J59: y | N59: Y | P59: =R59-Q59 -> 11171.61 | Q59: =SUBTOTAL(9,$F$2:F59) -> 36227.39 | R59: =SUBTOTAL(9,$G$2:G59) -> 47399
A60: C6 | B60: 43331 | C60: gardener | F60: 2600 | I60: 5000195 | J60: y | N60: Y | P60: =R60-Q60 -> 8571.61 | Q60: =SUBTOTAL(9,$F$2:F60) -> 38827.39 | R60: =SUBTOTAL(9,$G$2:G60) -> 47399
A61: C6 | B61: 43333 | C61: ניקיון לידיה - יולי | F61: 358 | I61: transfer | J61: y | N61: Y | P61: =R61-Q61 -> 8213.61 | Q61: =SUBTOTAL(9,$F$2:F61) -> 39185.39 | R61: =SUBTOTAL(9,$G$2:G61) -> 47399
A62: C6 | B62: 43341 | C62: חיים מנעולים | F62: 34 | I62: cc | J62: y | N62: Y | P62: =R62-Q62 -> 8179.61 | Q62: =SUBTOTAL(9,$F$2:F62) -> 39219.39 | R62: =SUBTOTAL(9,$G$2:G62) -> 47399
A63: C6 | B63: 43345 | C63: gardener | F63: 1300 | I63: 5000197 | J63: y | K63: עבד עקל | L63: אין | N63: Y | P63: =R63-Q63 -> 6879.61 | Q63: =SUBTOTAL(9,$F$2:F63) -> 40519.39 | R63: =SUBTOTAL(9,$G$2:G63) -> 47399
A64: C6 | B64: 43345 | C64: טכנאי מקרר | F64: 500 | I64: 5000198 | J64: y | K64: אליאסי שיווק | L64: אין | N64: Y | P64: =R64-Q64 -> 6379.61 | Q64: =SUBTOTAL(9,$F$2:F64) -> 41019.39 | R64: =SUBTOTAL(9,$G$2:G64) -> 47399
A65: C6 | B65: 43348 | C65: cleening helena aug | F65: 602.72 | I65: transfer | J65: y | N65: Y | P65: =R65-Q65 -> 5776.89 | Q65: =SUBTOTAL(9,$F$2:F65) -> 41622.11 | R65: =SUBTOTAL(9,$G$2:G65) -> 47399
A66: C6 | B66: 43349 | C66: pensya elena aug | F66: 114.9 | I66: transfer | J66: y | N66: Y | P66: =R66-Q66 -> 5661.99 | Q66: =SUBTOTAL(9,$F$2:F66) -> 41737.01 | R66: =SUBTOTAL(9,$G$2:G66) -> 47399
A67: C6 | B67: 43359 | C67: פילטר מים | F67: 350 | I67: cc | J67: y | K67: אקווה ספרינג | N67: Y | P67: =R67-Q67 -> 5311.99 | Q67: =SUBTOTAL(9,$F$2:F67) -> 42087.01 | R67: =SUBTOTAL(9,$G$2:G67) -> 47399
A68: C6 | B68: 43360 | C68: כדורסל | F68: 345 | I68: cc | J68: y | K68: אוורסט | N68: Y | P68: =R68-Q68 -> 4966.99 | Q68: =SUBTOTAL(9,$F$2:F68) -> 42432.01 | R68: =SUBTOTAL(9,$G$2:G68) -> 47399
A69: C6 | B69: 43363 | C69: bituh leomi aug elena | F69: 46.3 | I69: transfer | J69: y | N69: Y | P69: =R69-Q69 -> 4920.69 | Q69: =SUBTOTAL(9,$F$2:F69) -> 42478.31 | R69: =SUBTOTAL(9,$G$2:G69) -> 47399
A70: C6 | B70: 43370 | C70: הובלה והתקנה כדורסל | F70: 250 | I70: שק 199 | J70: y | K70: יורי הובלות | N70: Y | P70: =R70-Q70 -> 4670.69 | Q70: =SUBTOTAL(9,$F$2:F70) -> 42728.31 | R70: =SUBTOTAL(9,$G$2:G70) -> 47399
A71: C6 | B71: 43380 | C71: תיקון מזגן והחלפת חוט | F71: 400 | I71: transfer | J71: y | K71: יוסי בן אדיבה | N71: Y | P71: =R71-Q71 -> 4270.69 | Q71: =SUBTOTAL(9,$F$2:F71) -> 43128.31 | R71: =SUBTOTAL(9,$G$2:G71) -> 47399
A72: C6 | B72: 43380 | C72: אבי החשמלאי | F72: 500 | I72: transfer | J72: y | K72: אבי קודיש | N72: Y | P72: =R72-Q72 -> 3770.69 | Q72: =SUBTOTAL(9,$F$2:F72) -> 43628.31 | R72: =SUBTOTAL(9,$G$2:G72) -> 47399
A73: C6 | B73: 43383 | C73: water filter ballon | F73: 400 | I73: cc | J73: y | K73: אקוה ספרינג | L73: 929 | N73: Y | P73: =R73-Q73 -> 3370.69 | Q73: =SUBTOTAL(9,$F$2:F73) -> 44028.31 | R73: =SUBTOTAL(9,$G$2:G73) -> 47399
A74: C6 | B74: 43393 | C74: bituh leomi sep | F74: 46.81 | I74: transfer | J74: y | N74: Y | P74: =R74-Q74 -> 3323.88 | Q74: =SUBTOTAL(9,$F$2:F74) -> 44075.12 | R74: =SUBTOTAL(9,$G$2:G74) -> 47399
A75: C6 | B75: 43396 | C75: הסרת אבנית | F75: 3510 | I75: transfer | J75: y | K75: ידיד ליטושים | L75: 690 | N75: Y | P75: =R75-Q75 -> -186.12 | Q75: =SUBTOTAL(9,$F$2:F75) -> 47585.12 | R75: =SUBTOTAL(9,$G$2:G75) -> 47399
A76: C6 | B76: 43410 | C76: cleening helena oct | F76: 301.35 | J76: y | N76: Y | P76: =R76-Q76 -> -487.47 | Q76: =SUBTOTAL(9,$F$2:F76) -> 47886.47 | R76: =SUBTOTAL(9,$G$2:G76) -> 47399
A77: C6 | B77: 43410 | C77: pensia oct | F77: 57.57 | J77: y | N77: Y | P77: =R77-Q77 -> -545.04 | Q77: =SUBTOTAL(9,$F$2:F77) -> 47944.04 | R77: =SUBTOTAL(9,$G$2:G77) -> 47399
A78: C6 | B78: 43424 | C78: bituh leomi oct | F78: 23.19 | J78: y | N78: Y | P78: =R78-Q78 -> -568.23 | Q78: =SUBTOTAL(9,$F$2:F78) -> 47967.23 | R78: =SUBTOTAL(9,$G$2:G78) -> 47399
A79: C6 | B79: 43429 | C79: תיקון צינור דוד שמש | K79: סאמר מחניה | L79: 208 | N79: Y | P79: =R79-Q79 -> -568.23 | Q79: =SUBTOTAL(9,$F$2:F79) -> 47967.23 | R79: =SUBTOTAL(9,$G$2:G79) -> 47399
A80: C6 | B80: 43437 | C80: הבראה מנקה | F80: 63.8 | I80: transfer | J80: y | N80: Y | P80: =R80-Q80 -> -632.03 | Q80: =SUBTOTAL(9,$F$2:F80) -> 48031.03 | R80: =SUBTOTAL(9,$G$2:G80) -> 47399
A81: C6 | B81: 43438 | C81: ביקור | F81: 601 | I81: transfer | J81: y | K81: סאמר מחניה | L81: 212 | N81: Y | P81: =R81-Q81 -> -1233.03 | Q81: =SUBTOTAL(9,$F$2:F81) -> 48632.03 | R81: =SUBTOTAL(9,$G$2:G81) -> 47399
A82: C6 | B82: 43471 | C82: pre paid | G82: 10000 | I82: transfer | J82: y | N82: Y | P82: =R82-Q82 -> 8766.97 | Q82: =SUBTOTAL(9,$F$2:F82) -> 48632.03 | R82: =SUBTOTAL(9,$G$2:G82) -> 57399
A83: C6 | B83: 43478 | C83: Gardner | F83: 3900 | I83: 5000239 | J83: y | K83: עבד עקל | N83: Y | P83: =R83-Q83 -> 4866.97 | Q83: =SUBTOTAL(9,$F$2:F83) -> 52532.03 | R83: =SUBTOTAL(9,$G$2:G83) -> 57399
A84: C6 | B84: 43492 | C84: אחיקם ציפקיס תיקון גג | F84: 200 | I84: transfer | J84: y | N84: Y | P84: =R84-Q84 -> 4666.97 | Q84: =SUBTOTAL(9,$F$2:F84) -> 52732.03 | R84: =SUBTOTAL(9,$G$2:G84) -> 57399
A85: C6 | B85: 43494 | C85: אחיקם ציפקיס תיקון גג | F85: 100 | I85: transfer | J85: y | N85: Y | P85: =R85-Q85 -> 4566.97 | Q85: =SUBTOTAL(9,$F$2:F85) -> 52832.03 | R85: =SUBTOTAL(9,$G$2:G85) -> 57399
A86: C6 | B86: 43500 | C86: תיקון תריס חשמלי | F86: 800 | I86: 5000242 | J86: y | K86: ש ש תיקונים | L86: 14 | N86: Y | P86: =R86-Q86 -> 3766.97 | Q86: =SUBTOTAL(9,$F$2:F86) -> 53632.03 | R86: =SUBTOTAL(9,$G$2:G86) -> 57399
A87: C6 | B87: 43503 | C87: Cleaner | F87: 348.19 | J87: y | N87: Y | P87: =R87-Q87 -> 3418.78 | Q87: =SUBTOTAL(9,$F$2:F87) -> 53980.22 | R87: =SUBTOTAL(9,$G$2:G87) -> 57399
A88: C6 | B88: 43503 | C88: Cleaner Pension Jan | F88: 67.17 | J88: y | N88: Y | P88: =R88-Q88 -> 3351.61 | Q88: =SUBTOTAL(9,$F$2:F88) -> 54047.39 | R88: =SUBTOTAL(9,$G$2:G88) -> 57399
A89: C6 | B89: 43516 | C89: Cleaner Bituach Leumi Jan | F89: 27.6 | J89: y | N89: Y | P89: =R89-Q89 -> 3324.01 | Q89: =SUBTOTAL(9,$F$2:F89) -> 54074.99 | R89: =SUBTOTAL(9,$G$2:G89) -> 57399
A90: C6 | B90: 43549 | C90: ניקוי שטיחים וריפודים | F90: 3077 | I90: transfer | J90: y | K90: מסעוד משה | L90: 277 | N90: Y | P90: =R90-Q90 -> 247.01 | Q90: =SUBTOTAL(9,$F$2:F90) -> 57151.99 | R90: =SUBTOTAL(9,$G$2:G90) -> 57399
A91: C6 | B91: 43549 | C91: החלפת מנוע מאוורר | F91: 1950 | I91: transfer | J91: y | K91: מזגני הייתם | L91: 693 | N91: Y | P91: =R91-Q91 -> -1702.99 | Q91: =SUBTOTAL(9,$F$2:F91) -> 59101.99 | R91: =SUBTOTAL(9,$G$2:G91) -> 57399
A92: C6 | B92: 43552 | C92: חומרי ניקוי | F92: 118.7 | I92: cc | J92: y | K92: טיב טעם | L92: 7490 | N92: Y | P92: =R92-Q92 -> -1821.69 | Q92: =SUBTOTAL(9,$F$2:F92) -> 59220.69 | R92: =SUBTOTAL(9,$G$2:G92) -> 57399
A93: C6 | B93: 43558 | C93: Cleaner mer | F93: 833.64 | I93: transfer | J93: y | N93: Y | P93: =R93-Q93 -> -2655.33 | Q93: =SUBTOTAL(9,$F$2:F93) -> 60054.33 | R93: =SUBTOTAL(9,$G$2:G93) -> 57399
A94: C6 | B94: 43558 | C94: Cleaner Pension mer | F94: 158.26 | I94: transfer | J94: y | N94: Y | P94: =R94-Q94 -> -2813.59 | Q94: =SUBTOTAL(9,$F$2:F94) -> 60212.59 | R94: =SUBTOTAL(9,$G$2:G94) -> 57399
A95: C6 | B95: 43559 | C95: gardener | F95: 3900 | I95: chac5000245 | J95: y | N95: Y | P95: =R95-Q95 -> -6713.59 | Q95: =SUBTOTAL(9,$F$2:F95) -> 64112.59 | R95: =SUBTOTAL(9,$G$2:G95) -> 57399
A96: C6 | B96: 43565 | C96: שטיפת קו ביוב | F96: 585 | I96: chac500246 | J96: y | K96: בורה | L96: 3016 | N96: Y | P96: =R96-Q96 -> -7298.59 | Q96: =SUBTOTAL(9,$F$2:F96) -> 64697.59 | R96: =SUBTOTAL(9,$G$2:G96) -> 57399
A97: C6 | B97: 43565 | C97: טיב טעם | F97: 27.9 | I97: cc | J97: y | N97: Y | P97: =R97-Q97 -> -7326.49 | Q97: =SUBTOTAL(9,$F$2:F97) -> 64725.49 | R97: =SUBTOTAL(9,$G$2:G97) -> 57399
A98: C6 | B98: 43570 | C98: חומרי ניקוי | F98: 22.5 | I98: cc | J98: y | K98: טיב טעם | N98: Y | P98: =R98-Q98 -> -7348.99 | Q98: =SUBTOTAL(9,$F$2:F98) -> 64747.99 | R98: =SUBTOTAL(9,$G$2:G98) -> 57399
A99: C6 | B99: 43572 | C99: שלום שבח כדורסל | F99: 100 | I99: cash | J99: y | N99: Y | P99: =R99-Q99 -> -7448.99 | Q99: =SUBTOTAL(9,$F$2:F99) -> 64847.99 | R99: =SUBTOTAL(9,$G$2:G99) -> 57399
A100: C6 | B100: 43572 | C100: אוורסט כיסוי לשולחן פינגפונג | F100: 280 | I100: cc | J100: y | N100: Y | P100: =R100-Q100 -> -7728.99 | Q100: =SUBTOTAL(9,$F$2:F100) -> 65127.99 | R100: =SUBTOTAL(9,$G$2:G100) -> 57399
...

Sheet 12 ex
A1: Prop ID | B1: Date | C1: Section | D1: Notes | E1: Type | F1: Amount | G1: Inflow | H1: He/She paid | I1: Method | J1: Reconciled | K1: Company | L1: Reciept | M1: Rental income | N1: Reported | O1: Report sent | P1: Balance | Q1: Total Amount | R1: Total Inflow
A2: 12 | B2: 43643 | C2: pre paid | G2: 3000 | I2: t | J2: y | N2: Y | P2: =R2-Q2 -> 3000 | Q2: =SUBTOTAL(9,$F$2:F2) -> 0 | R2: =SUBTOTAL(9,$G$2:G2) -> 3000
A3: 12 | B3: 43643 | C3: חומר ניקוי | F3: 8.9 | I3: cc | J3: y | N3: Y | P3: =R3-Q3 -> 2991.1 | Q3: =SUBTOTAL(9,$F$2:F3) -> 8.9 | R3: =SUBTOTAL(9,$G$2:G3) -> 3000
A4: 12 | B4: 43648 | C4: שכירות | J4: y | M4: 6000 | N4: Y | P4: =R4-Q4 -> 2991.1 | Q4: =SUBTOTAL(9,$F$2:F4) -> 8.9 | R4: =SUBTOTAL(9,$G$2:G4) -> 3000
A5: 12 | B5: 43649 | C5: Cleaning june | F5: 903.21 | I5: t | J5: y | N5: Y | P5: =R5-Q5 -> 2087.89 | Q5: =SUBTOTAL(9,$F$2:F5) -> 912.11 | R5: =SUBTOTAL(9,$G$2:G5) -> 3000
A6: 12 | B6: 43649 | C6: pensia Cleaning june | F6: 144.23 | I6: t | J6: y | N6: Y | P6: =R6-Q6 -> 1943.66 | Q6: =SUBTOTAL(9,$F$2:F6) -> 1056.34 | R6: =SUBTOTAL(9,$G$2:G6) -> 3000
A7: 12 | B7: 43666 | C7: bituh leomi Cleaning june | F7: 59.16 | I7: t | J7: y | N7: Y | P7: =R7-Q7 -> 1884.5 | Q7: =SUBTOTAL(9,$F$2:F7) -> 1115.5 | R7: =SUBTOTAL(9,$G$2:G7) -> 3000
A8: 12 | B8: 43653 | C8: תשלום ניהול סנדי נכנס בטעות לחשבון הזה | G8: 1930.5 | N8: Y | P8: =R8-Q8 -> 3815 | Q8: =SUBTOTAL(9,$F$2:F8) -> 1115.5 | R8: =SUBTOTAL(9,$G$2:G8) -> 4930.5
A9: 12 | B9: 43655 | C9: העברת התשלום לסנדי | F9: 1930.5 | N9: Y | P9: =R9-Q9 -> 1884.5 | Q9: =SUBTOTAL(9,$F$2:F9) -> 3046 | R9: =SUBTOTAL(9,$G$2:G9) -> 4930.5
A10: 12 | B10: 43656 | C10: ארנונה | F10: 1465.7 | I10: cc | J10: y | N10: Y | P10: =R10-Q10 -> 418.8 | Q10: =SUBTOTAL(9,$F$2:F10) -> 4511.7 | R10: =SUBTOTAL(9,$G$2:G10) -> 4930.5
A11: 12 | B11: 43656 | C11: מעיינות העמקים מים | F11: 351.8 | I11: cc | J11: y | N11: Y | P11: =R11-Q11 -> 67 | Q11: =SUBTOTAL(9,$F$2:F11) -> 4863.5 | R11: =SUBTOTAL(9,$G$2:G11) -> 4930.5
A12: 12 | B12: 43657 | C12: חשמל | F12: 154.88 | I12: cc | J12: y | N12: Y | P12: =R12-Q12 -> -87.88 | Q12: =SUBTOTAL(9,$F$2:F12) -> 5018.38 | R12: =SUBTOTAL(9,$G$2:G12) -> 4930.5
A13: 12 | B13: 43657 | C13: יונס שיפוצים מקלחות | F13: 819 | I13: 5000260 | J13: y | K13: יונס שיפוצים | L13: 41 | N13: Y | P13: =R13-Q13 -> -906.88 | Q13: =SUBTOTAL(9,$F$2:F13) -> 5837.38 | R13: =SUBTOTAL(9,$G$2:G13) -> 4930.5
A14: 12 | B14: 43663 | C14: שלום שבח | F14: 600 | I14: t | J14: y | K14: שלום שבח | N14: Y | P14: =R14-Q14 -> -1506.88 | Q14: =SUBTOTAL(9,$F$2:F14) -> 6437.38 | R14: =SUBTOTAL(9,$G$2:G14) -> 4930.5
A15: 12 | B15: 43678 | C15: שכירות | J15: y | M15: 6000 | N15: Y | P15: =R15-Q15 -> -1506.88 | Q15: =SUBTOTAL(9,$F$2:F15) -> 6437.38 | R15: =SUBTOTAL(9,$G$2:G15) -> 4930.5
A16: 12 | B16: 43685 | C16: pre paid | G16: 2500 | I16: t | J16: y | N16: Y | P16: =R16-Q16 -> 993.12 | Q16: =SUBTOTAL(9,$F$2:F16) -> 6437.38 | R16: =SUBTOTAL(9,$G$2:G16) -> 7430.5
A17: 12 | B17: 43710 | C17: שכירות | J17: y | M17: 6000 | N17: Y | P17: =R17-Q17 -> 993.12 | Q17: =SUBTOTAL(9,$F$2:F17) -> 6437.38 | R17: =SUBTOTAL(9,$G$2:G17) -> 7430.5
A18: 12 | B18: 43723 | C18: צנור לברז | F18: 102.96 | I18: cc | J18: y | K18: הנגב | L18: 4109 | N18: Y | P18: =R18-Q18 -> 890.16 | Q18: =SUBTOTAL(9,$F$2:F18) -> 6540.34 | R18: =SUBTOTAL(9,$G$2:G18) -> 7430.5
A19: 12 | B19: 43749 | C19: בטעות שילם לחשבון הזה ניהול | F19: 1930.5 | I19: t | J19: y | N19: Y | P19: =R19-Q19 -> -1040.34 | Q19: =SUBTOTAL(9,$F$2:F19) -> 8470.84 | R19: =SUBTOTAL(9,$G$2:G19) -> 7430.5
A20: 12 | B20: 43755 | C20: העברה לסנדי מכיוון ששילם בטעות | G20: 1930.5 | I20: t | J20: y | N20: Y | P20: =R20-Q20 -> 890.16 | Q20: =SUBTOTAL(9,$F$2:F20) -> 8470.84 | R20: =SUBTOTAL(9,$G$2:G20) -> 9361
A21: 12 | B21: 43769 | C21: חשמל 2/8-6/10/19 | H21: 4854.89 | N21: Y | P21: =R21-Q21 -> 890.16 | Q21: =SUBTOTAL(9,$F$2:F21) -> 8470.84 | R21: =SUBTOTAL(9,$G$2:G21) -> 9361
A22: 12 | B22: 43772 | C22: שכירות | M22: 6000 | N22: Y | P22: =R22-Q22 -> 890.16 | Q22: =SUBTOTAL(9,$F$2:F22) -> 8470.84 | R22: =SUBTOTAL(9,$G$2:G22) -> 9361
A23: 12 | B23: 43800 | C23: מחסני תאורה | F23: 79.8 | I23: cc | J23: y | K23: מחסני תאורה | L23: 875 | N23: Y | P23: =R23-Q23 -> 810.36 | Q23: =SUBTOTAL(9,$F$2:F23) -> 8550.64 | R23: =SUBTOTAL(9,$G$2:G23) -> 9361
A24: 12 | B24: 43801 | C24: שכירות | M24: 6000 | N24: Y | P24: =R24-Q24 -> 810.36 | Q24: =SUBTOTAL(9,$F$2:F24) -> 8550.64 | R24: =SUBTOTAL(9,$G$2:G24) -> 9361
A25: 12 | B25: 43831 | C25: שכירות | M25: 6000 | N25: Y | P25: =R25-Q25 -> 810.36 | Q25: =SUBTOTAL(9,$F$2:F25) -> 8550.64 | R25: =SUBTOTAL(9,$G$2:G25) -> 9361
A26: 12 | B26: 43832 | C26: תיקון אסלה וברז במטבח | F26: 585 | I26: 5000208 | J26: y | K26: פואד - שק נרשם לגולן לבניין | L26: 1497ד | N26: Y | P26: =R26-Q26 -> 225.36 | Q26: =SUBTOTAL(9,$F$2:F26) -> 9135.64 | R26: =SUBTOTAL(9,$G$2:G26) -> 9361
A27: 12 | B27: 43839 | C27: נורה | F27: 57 | I27: cc | J27: y | K27: חשמל ישיר | L27: 433 | N27: Y | P27: =R27-Q27 -> 168.36 | Q27: =SUBTOTAL(9,$F$2:F27) -> 9192.64 | R27: =SUBTOTAL(9,$G$2:G27) -> 9361
A28: 12 | B28: 43800 | C28: זיכוי מחסני תאורה | G28: 79.8 | I28: cc | J28: y | N28: Y | P28: =R28-Q28 -> 248.16 | Q28: =SUBTOTAL(9,$F$2:F28) -> 9192.64 | R28: =SUBTOTAL(9,$G$2:G28) -> 9440.8
A29: 12 | B29: 43864 | C29: העביר ניהול בטעות לפה | G29: 1931 | I29: t | J29: y | N29: Y | P29: =R29-Q29 -> 2179.16 | Q29: =SUBTOTAL(9,$F$2:F29) -> 9192.64 | R29: =SUBTOTAL(9,$G$2:G29) -> 11371.8
A30: 12 | B30: 43865 | C30: העברתי לסנדי את הניהול | F30: 1931 | I30: t | J30: y | N30: Y | P30: =R30-Q30 -> 248.16 | Q30: =SUBTOTAL(9,$F$2:F30) -> 11123.64 | R30: =SUBTOTAL(9,$G$2:G30) -> 11371.8
A31: 12 | B31: 43863 | C31: שכירות | M31: 6000 | N31: Y | P31: =R31-Q31 -> 248.16 | Q31: =SUBTOTAL(9,$F$2:F31) -> 11123.64 | R31: =SUBTOTAL(9,$G$2:G31) -> 11371.8
A32: 12 | B32: 43893 | C32: שכירות | M32: 6000 | N32: Y | P32: =R32-Q32 -> 248.16 | Q32: =SUBTOTAL(9,$F$2:F32) -> 11123.64 | R32: =SUBTOTAL(9,$G$2:G32) -> 11371.8
A33: 12 | B33: 43923 | C33: ניהול סנדי בטעות העבירו לפה | G33: 1930.5 | I33: t | J33: y | N33: Y | P33: =R33-Q33 -> 2178.66 | Q33: =SUBTOTAL(9,$F$2:F33) -> 11123.64 | R33: =SUBTOTAL(9,$G$2:G33) -> 13302.3
A34: 12 | B34: 43927 | C34: סנדי העבירה לחשבון שלה את הניהול | F34: 1930.5 | I34: t | J34: y | N34: Y | P34: =R34-Q34 -> 248.16 | Q34: =SUBTOTAL(9,$F$2:F34) -> 13054.14 | R34: =SUBTOTAL(9,$G$2:G34) -> 13302.3
A35: 12 | B35: 43922 | C35: שכירות | M35: 6000 | N35: Y | P35: =R35-Q35 -> 248.16 | Q35: =SUBTOTAL(9,$F$2:F35) -> 13054.14 | R35: =SUBTOTAL(9,$G$2:G35) -> 13302.3
A36: 12 | B36: 43956 | C36: שכירות | M36: 6000 | N36: Y | P36: =R36-Q36 -> 248.16 | Q36: =SUBTOTAL(9,$F$2:F36) -> 13054.14 | R36: =SUBTOTAL(9,$G$2:G36) -> 13302.3
A37: 12 | B37: 43977 | C37: החלפת מצוף ניאגרה | F37: 410 | I37: t | J37: y | K37: אמבלונס לאינסטלציה | L37: 16 | N37: Y | P37: =R37-Q37 -> -161.84 | Q37: =SUBTOTAL(9,$F$2:F37) -> 13464.14 | R37: =SUBTOTAL(9,$G$2:G37) -> 13302.3
A38: 12 | B38: 43983 | C38: שכירות | M38: 6000 | N38: Y | P38: =R38-Q38 -> -161.84 | Q38: =SUBTOTAL(9,$F$2:F38) -> 13464.14 | R38: =SUBTOTAL(9,$G$2:G38) -> 13302.3
A39: 12 | B39: 44013 | C39: שכירות | M39: 6000 | N39: Y | P39: =R39-Q39 -> -161.84 | Q39: =SUBTOTAL(9,$F$2:F39) -> 13464.14 | R39: =SUBTOTAL(9,$G$2:G39) -> 13302.3
A40: 12 | B40: 44020 | C40: menegment | G40: 1930.5 | I40: t | J40: y | N40: Y | P40: =R40-Q40 -> 1768.66 | Q40: =SUBTOTAL(9,$F$2:F40) -> 13464.14 | R40: =SUBTOTAL(9,$G$2:G40) -> 15232.8
A41: 12 | B41: 44027 | C41: הועבר לסנדי בטעות עבר לפה זה ניהול | F41: 1930.5 | I41: t | J41: y | N41: Y | P41: =R41-Q41 -> -161.84 | Q41: =SUBTOTAL(9,$F$2:F41) -> 15394.64 | R41: =SUBTOTAL(9,$G$2:G41) -> 15232.8
A42: 12 | B42: 44075 | C42: שכירות | M42: 5500 | N42: Y | P42: =R42-Q42 -> -161.84 | Q42: =SUBTOTAL(9,$F$2:F42) -> 15394.64 | R42: =SUBTOTAL(9,$G$2:G42) -> 15232.8
A43: 12 | B43: 44105 | C43: שכירות | M43: 5500 | N43: Y | P43: =R43-Q43 -> -161.84 | Q43: =SUBTOTAL(9,$F$2:F43) -> 15394.64 | R43: =SUBTOTAL(9,$G$2:G43) -> 15232.8
A44: 12 | B44: 44140 | C44: שכירות | M44: 6000 | N44: Y | P44: =R44-Q44 -> -161.84 | Q44: =SUBTOTAL(9,$F$2:F44) -> 15394.64 | R44: =SUBTOTAL(9,$G$2:G44) -> 15232.8
A45: 12 | B45: 44153 | C45: ניהול סנדי בטעות העבירו לפה | G45: 1930.5 | I45: t | J45: y | N45: Y | P45: =R45-Q45 -> 1768.66 | Q45: =SUBTOTAL(9,$F$2:F45) -> 15394.64 | R45: =SUBTOTAL(9,$G$2:G45) -> 17163.3
A46: 12 | B46: 44155 | C46: הועבר לסנדי בטעות עבר לפה זה ניהול | F46: 1930.5 | I46: t | J46: y | N46: Y | P46: =R46-Q46 -> -161.84 | Q46: =SUBTOTAL(9,$F$2:F46) -> 17325.14 | R46: =SUBTOTAL(9,$G$2:G46) -> 17163.3
A47: 12 | B47: 44168 | C47: שכירות | M47: 6000 | N47: Y | P47: =R47-Q47 -> -161.84 | Q47: =SUBTOTAL(9,$F$2:F47) -> 17325.14 | R47: =SUBTOTAL(9,$G$2:G47) -> 17163.3
A48: 12 | B48: 44200 | C48: ניהול סנדי בטעות העבירו לפה | G48: 1930.5 | I48: t | J48: y | N48: Y | P48: =R48-Q48 -> 1768.66 | Q48: =SUBTOTAL(9,$F$2:F48) -> 17325.14 | R48: =SUBTOTAL(9,$G$2:G48) -> 19093.8
A49: 12 | B49: 44201 | C49: הועבר לסנדי בטעות עבר לפה זה ניהול | F49: 1930.5 | I49: t | J49: y | N49: Y | P49: =R49-Q49 -> -161.84 | Q49: =SUBTOTAL(9,$F$2:F49) -> 19255.64 | R49: =SUBTOTAL(9,$G$2:G49) -> 19093.8
A50: 12 | B50: 44200 | C50: שכירות | M50: 6000 | N50: Y | P50: =R50-Q50 -> -161.84 | Q50: =SUBTOTAL(9,$F$2:F50) -> 19255.64 | R50: =SUBTOTAL(9,$G$2:G50) -> 19093.8
A51: 12 | B51: 44228 | C51: שכירות | M51: 6000 | N51: Y | P51: =R51-Q51 -> -161.84 | Q51: =SUBTOTAL(9,$F$2:F51) -> 19255.64 | R51: =SUBTOTAL(9,$G$2:G51) -> 19093.8
A52: 12 | B52: 44255 | C52: advance | G52: 1000 | I52: t | J52: y | N52: Y | P52: =R52-Q52 -> 838.16 | Q52: =SUBTOTAL(9,$F$2:F52) -> 19255.64 | R52: =SUBTOTAL(9,$G$2:G52) -> 20093.8
A53: 12 | B53: 44256 | C53: שכירות | M53: 6000 | N53: Y | P53: =R53-Q53 -> 838.16 | Q53: =SUBTOTAL(9,$F$2:F53) -> 19255.64 | R53: =SUBTOTAL(9,$G$2:G53) -> 20093.8
A54: 12 | B54: 44292 | C54: ניהול סנדי בטעות העבירו לפה | G54: 1930.5 | I54: t | J54: y | N54: Y | P54: =R54-Q54 -> 2768.66 | Q54: =SUBTOTAL(9,$F$2:F54) -> 19255.64 | R54: =SUBTOTAL(9,$G$2:G54) -> 22024.3
A55: 12 | B55: 44294 | C55: הועבר לסנדי בטעות עבר לפה זה ניהול | F55: 1930.5 | I55: t | J55: y | N55: Y | P55: =R55-Q55 -> 838.16 | Q55: =SUBTOTAL(9,$F$2:F55) -> 21186.14 | R55: =SUBTOTAL(9,$G$2:G55) -> 22024.3
A56: 12 | B56: 44291 | C56: שכירות | M56: 6000 | N56: Y | P56: =R56-Q56 -> 838.16 | Q56: =SUBTOTAL(9,$F$2:F56) -> 21186.14 | R56: =SUBTOTAL(9,$G$2:G56) -> 22024.3
A57: 12 | B57: 44318 | C57: שכירות | M57: 6000 | N57: Y | P57: =R57-Q57 -> 838.16 | Q57: =SUBTOTAL(9,$F$2:F57) -> 21186.14 | R57: =SUBTOTAL(9,$G$2:G57) -> 22024.3
A58: 12 | B58: 44327 | C58: החלפת שעון שבת | F58: 350 | I58: t | J58: y | K58: אבי קודיש | L58: 528 | N58: Y | P58: =R58-Q58 -> 488.16 | Q58: =SUBTOTAL(9,$F$2:F58) -> 21536.14 | R58: =SUBTOTAL(9,$G$2:G58) -> 22024.3
A59: 12 | B59: 44355 | C59: עוז אגסי | F59: 800 | I59: t | J59: y | L59: 4413 | N59: Y | O59: 44397 | P59: =R59-Q59 -> -311.84 | Q59: =SUBTOTAL(9,$F$2:F59) -> 22336.14 | R59: =SUBTOTAL(9,$G$2:G59) -> 22024.3
A60: 12 | B60: 44403 | C60: Advance | G60: 1300 | I60: t | J60: y | N60: Y | P60: =R60-Q60 -> 988.16 | Q60: =SUBTOTAL(9,$F$2:F60) -> 22336.14 | R60: =SUBTOTAL(9,$G$2:G60) -> 23324.3
A61: 12 | B61: 44417 | C61: Deposit of rent | M61: 6000 | N61: Y | P61: =R61-Q61 -> 988.16 | Q61: =SUBTOTAL(9,$F$2:F61) -> 22336.14 | R61: =SUBTOTAL(9,$G$2:G61) -> 23324.3
A62: 12 | B62: 44440 | C62: Deposit of rent | M62: 6000 | N62: Y | P62: =R62-Q62 -> 988.16 | Q62: =SUBTOTAL(9,$F$2:F62) -> 22336.14 | R62: =SUBTOTAL(9,$G$2:G62) -> 23324.3
A63: 12 | B63: 44470 | C63: Deposit of rent | M63: 6000 | N63: Y | P63: =R63-Q63 -> 988.16 | Q63: =SUBTOTAL(9,$F$2:F63) -> 22336.14 | R63: =SUBTOTAL(9,$G$2:G63) -> 23324.3
A64: 12 | B64: 44472 | C64: Management Sandi | G64: 1930.5 | N64: Y | P64: =R64-Q64 -> 2918.66 | Q64: =SUBTOTAL(9,$F$2:F64) -> 22336.14 | R64: =SUBTOTAL(9,$G$2:G64) -> 25254.8
A65: 12 | B65: 44475 | C65: Management Sandi - the right account | F65: 1930.5 | I65: t | N65: Y | P65: =R65-Q65 -> 988.16 | Q65: =SUBTOTAL(9,$F$2:F65) -> 24266.64 | R65: =SUBTOTAL(9,$G$2:G65) -> 25254.8
A66: 12 | B66: 44502 | C66: Deposit of rent | M66: 6000 | N66: Y | P66: =R66-Q66 -> 988.16 | Q66: =SUBTOTAL(9,$F$2:F66) -> 24266.64 | R66: =SUBTOTAL(9,$G$2:G66) -> 25254.8
A67: 12 | B67: 44566 | C67: Management Sandi | G67: 1930.5 | N67: Y | P67: =R67-Q67 -> 2918.66 | Q67: =SUBTOTAL(9,$F$2:F67) -> 24266.64 | R67: =SUBTOTAL(9,$G$2:G67) -> 27185.3
A68: 12 | B68: 44567 | C68: Management Sandi - the right account | F68: 1930.5 | I68: t | N68: Y | P68: =R68-Q68 -> 988.16 | Q68: =SUBTOTAL(9,$F$2:F68) -> 26197.14 | R68: =SUBTOTAL(9,$G$2:G68) -> 27185.3
A69: 12 | B69: 44654 | C69: Management MIP | G69: 1930.5 | N69: Y | P69: =R69-Q69 -> 2918.66 | Q69: =SUBTOTAL(9,$F$2:F69) -> 26197.14 | R69: =SUBTOTAL(9,$G$2:G69) -> 29115.8
A70: 12 | B70: 44656 | C70: Management MIP - the right account | F70: 1930.5 | I70: t | N70: Y | P70: =R70-Q70 -> 988.16 | Q70: =SUBTOTAL(9,$F$2:F70) -> 28127.64 | R70: =SUBTOTAL(9,$G$2:G70) -> 29115.8
A71: 12 | B71: 44746 | C71: Management MIP | G71: 1930.5 | N71: Y | P71: =R71-Q71 -> 2918.66 | Q71: =SUBTOTAL(9,$F$2:F71) -> 28127.64 | R71: =SUBTOTAL(9,$G$2:G71) -> 31046.3
A72: 12 | B72: 44749 | C72: Management MIP - the right account | F72: 1930.5 | I72: t | N72: Y | P72: =R72-Q72 -> 988.16 | Q72: =SUBTOTAL(9,$F$2:F72) -> 30058.14 | R72: =SUBTOTAL(9,$G$2:G72) -> 31046.3
A73: 12 | B73: 44784 | C73: Deposit of rent | M73: 6500 | N73: Y | P73: =R73-Q73 -> 988.16 | Q73: =SUBTOTAL(9,$F$2:F73) -> 30058.14 | R73: =SUBTOTAL(9,$G$2:G73) -> 31046.3
A74: 12 | B74: 44840 | C74: Management MIP | G74: 1930.5 | N74: Y | P74: =R74-Q74 -> 2918.66 | Q74: =SUBTOTAL(9,$F$2:F74) -> 30058.14 | R74: =SUBTOTAL(9,$G$2:G74) -> 32976.8
A75: 12 | B75: 44852 | C75: Management MIP - the right account | F75: 1930.5 | I75: t | N75: Y | P75: =R75-Q75 -> 988.16 | Q75: =SUBTOTAL(9,$F$2:F75) -> 31988.64 | R75: =SUBTOTAL(9,$G$2:G75) -> 32976.8
A76: 12 | B76: 44867 | C76: Deposit of rent | M76: 6500 | N76: Y | P76: =R76-Q76 -> 988.16 | Q76: =SUBTOTAL(9,$F$2:F76) -> 31988.64 | R76: =SUBTOTAL(9,$G$2:G76) -> 32976.8
A77: 12 | B77: 44900 | C77: Deposit of rent | M77: 6500 | N77: Y | P77: =R77-Q77 -> 988.16 | Q77: =SUBTOTAL(9,$F$2:F77) -> 31988.64 | R77: =SUBTOTAL(9,$G$2:G77) -> 32976.8
A78: 12 | B78: 44934 | C78: תיקון מדרגות ומסילה ופנלים | F78: 1755 | I78: t | K78: אורי אריפול | L78: 421 | N78: Y | P78: =R78-Q78 -> -766.84 | Q78: =SUBTOTAL(9,$F$2:F78) -> 33743.64 | R78: =SUBTOTAL(9,$G$2:G78) -> 32976.8
A79: 12 | B79: 44928 | C79: Management MIP | G79: 1930.5 | N79: Y | P79: =R79-Q79 -> 1163.66 | Q79: =SUBTOTAL(9,$F$2:F79) -> 33743.64 | R79: =SUBTOTAL(9,$G$2:G79) -> 34907.3
A80: 12 | B80: 44934 | C80: Management MIP - the right account | F80: 1930.5 | I80: t | N80: Y | O80: 44935 | P80: =R80-Q80 -> -766.84 | Q80: =SUBTOTAL(9,$F$2:F80) -> 35674.14 | R80: =SUBTOTAL(9,$G$2:G80) -> 34907.3
A81: 12 | B81: 44937 | C81: Advance | G81: 1500 | N81: Y | P81: =R81-Q81 -> 733.16 | Q81: =SUBTOTAL(9,$F$2:F81) -> 35674.14 | R81: =SUBTOTAL(9,$G$2:G81) -> 36407.3
A82: 12 | B82: 44970 | C82: Deposit of rent | M82: 6500 | N82: Y | P82: =R82-Q82 -> 733.16 | Q82: =SUBTOTAL(9,$F$2:F82) -> 35674.14 | R82: =SUBTOTAL(9,$G$2:G82) -> 36407.3
A83: 12 | B83: 44986 | C83: Deposit of rent | M83: 6500 | N83: Y | P83: =R83-Q83 -> 733.16 | Q83: =SUBTOTAL(9,$F$2:F83) -> 35674.14 | R83: =SUBTOTAL(9,$G$2:G83) -> 36407.3
A84: 12 | B84: 45019 | C84: Deposit of rent | M84: 6500 | N84: Y | P84: =R84-Q84 -> 733.16 | Q84: =SUBTOTAL(9,$F$2:F84) -> 35674.14 | R84: =SUBTOTAL(9,$G$2:G84) -> 36407.3
A85: 12 | B85: 45019 | C85: Management MIP | G85: 1930.5 | N85: Y | P85: =R85-Q85 -> 2663.66 | Q85: =SUBTOTAL(9,$F$2:F85) -> 35674.14 | R85: =SUBTOTAL(9,$G$2:G85) -> 38337.8
A86: 12 | B86: 45025 | C86: Management MIP - the right account | F86: 1930.5 | I86: t | N86: Y | P86: =R86-Q86 -> 733.16 | Q86: =SUBTOTAL(9,$F$2:F86) -> 37604.64 | R86: =SUBTOTAL(9,$G$2:G86) -> 38337.8
A87: 12 | B87: 45048 | C87: Deposit of rent | M87: 6500 | N87: Y | P87: =R87-Q87 -> 733.16 | Q87: =SUBTOTAL(9,$F$2:F87) -> 37604.64 | R87: =SUBTOTAL(9,$G$2:G87) -> 38337.8
A88: 12 | B88: 45078 | C88: Deposit of rent | M88: 6500 | N88: Y | P88: =R88-Q88 -> 733.16 | Q88: =SUBTOTAL(9,$F$2:F88) -> 37604.64 | R88: =SUBTOTAL(9,$G$2:G88) -> 38337.8
A89: 12 | B89: 45116 | C89: Management MIP | G89: 1930.5 | N89: Y | P89: =R89-Q89 -> 2663.66 | Q89: =SUBTOTAL(9,$F$2:F89) -> 37604.64 | R89: =SUBTOTAL(9,$G$2:G89) -> 40268.3
A90: 12 | B90: 45117 | C90: Management MIP - the right account | F90: 1930.5 | I90: t | N90: Y | P90: =R90-Q90 -> 733.16 | Q90: =SUBTOTAL(9,$F$2:F90) -> 39535.14 | R90: =SUBTOTAL(9,$G$2:G90) -> 40268.3
A91: 12 | B91: 45117 | C91: Deposit of rent | M91: 6500 | N91: Y | P91: =R91-Q91 -> 733.16 | Q91: =SUBTOTAL(9,$F$2:F91) -> 39535.14 | R91: =SUBTOTAL(9,$G$2:G91) -> 40268.3
A92: 12 | B92: 45148 | C92: Air conditioning technician | F92: 300 | I92: t | K92: מיזוג הברון | L92: 32174 | N92: Y | P92: =R92-Q92 -> 433.16 | Q92: =SUBTOTAL(9,$F$2:F92) -> 39835.14 | R92: =SUBTOTAL(9,$G$2:G92) -> 40268.3
A93: 12 | B93: 45117 | C93: Deposit of rent | M93: 6700 | N93: Y | P93: =R93-Q93 -> 433.16 | Q93: =SUBTOTAL(9,$F$2:F93) -> 39835.14 | R93: =SUBTOTAL(9,$G$2:G93) -> 40268.3
A94: 12 | B94: 45163 | C94: Deposit of rent | M94: 7700 | N94: Y | P94: =R94-Q94 -> 433.16 | Q94: =SUBTOTAL(9,$F$2:F94) -> 39835.14 | R94: =SUBTOTAL(9,$G$2:G94) -> 40268.3
A95: 12 | B95: 45173 | C95: םPower point arrangement + gluing panels | D95: סידור נקודת חשמל + הדבקת פנלים | F95: 250 | I95: t | N95: Y | P95: =R95-Q95 -> 183.16 | Q95: =SUBTOTAL(9,$F$2:F95) -> 40085.14 | R95: =SUBTOTAL(9,$G$2:G95) -> 40268.3
A96: 12 | B96: 45202 | C96: Deposit of rent | M96: 6700 | N96: Y | P96: =R96-Q96 -> 183.16 | Q96: =SUBTOTAL(9,$F$2:F96) -> 40085.14 | R96: =SUBTOTAL(9,$G$2:G96) -> 40268.3
A97: 12 | B97: 45205 | C97: Management MIP | G97: 1930.5 | N97: Y | P97: =R97-Q97 -> 2113.66 | Q97: =SUBTOTAL(9,$F$2:F97) -> 40085.14 | R97: =SUBTOTAL(9,$G$2:G97) -> 42198.8
A98: 12 | B98: 45214 | C98: Management MIP - the right account | F98: 1930.5 | I98: t | N98: Y | P98: =R98-Q98 -> 183.16 | Q98: =SUBTOTAL(9,$F$2:F98) -> 42015.64 | R98: =SUBTOTAL(9,$G$2:G98) -> 42198.8
A99: 12 | B99: 45238 | C99: Deposit of rent | M99: 6700 | N99: Y | P99: =R99-Q99 -> 183.16 | Q99: =SUBTOTAL(9,$F$2:F99) -> 42015.64 | R99: =SUBTOTAL(9,$G$2:G99) -> 42198.8
A100: 12 | B100: 45263 | C100: Deposit of rent | M100: 6700 | N100: Y | P100: =R100-Q100 -> 183.16 | Q100: =SUBTOTAL(9,$F$2:F100) -> 42015.64 | R100: =SUBTOTAL(9,$G$2:G100) -> 42198.8
...

Sheet C8
A1: Prop ID | B1: Date | C1: Section | D1: Notes | E1: Type | F1: Amount | G1: Inflow | H1: He/She paid | I1: Method | J1: Reconciled | K1: Company | L1: Reciept | M1: Rental income | N1: Reported | O1: Report sent | P1: Balance | Q1: Total Amount | R1: Total Inflow
A2: C8 | B2: 46022 | C2: Key | F2: 140 | K2: חיים מנעולים | L2: 13378 | N2: Y | P2: =R2-Q2 -> -140 | Q2: =SUBTOTAL(9,$F$2:F2) -> 140 | R2: =SUBTOTAL(9,$G$2:G2) -> 0
A3: C8 | B3: 46031 | C3: Cleaning + Pension + Bituch Leumi 12.2025 11.2025 | D3: David | F3: 695 | N3: Y | P3: =R3-Q3 -> -835 | Q3: =SUBTOTAL(9,$F$2:F3) -> 835 | R3: =SUBTOTAL(9,$G$2:G3) -> 0
A4: C8 | B4: 46062 | C4: Cleaning + Pension + Bituch Leumi 01.2026 | D4: David | F4: 354 | N4: Y | O4: 45698 | P4: =R4-Q4 -> -1189 | Q4: =SUBTOTAL(9,$F$2:F4) -> 1189 | R4: =SUBTOTAL(9,$G$2:G4) -> 0
A5: C8 | B5: 46065 | C5: Advance | G5: 1189 | L5: leumi receipt | M5: 130335 | N5: Y | P5: =R5-Q5 -> 0 | Q5: =SUBTOTAL(9,$F$2:F5) -> 1189 | R5: =SUBTOTAL(9,$G$2:G5) -> 1189
A6: C8 | B6: 46069 | C6: Plumber verification | H6: 2360 | L6: דוד ביטון | M6: 60516 | N6: Y | P6: =R6-Q6 -> 0 | Q6: =SUBTOTAL(9,$F$2:F6) -> 1189 | R6: =SUBTOTAL(9,$G$2:G6) -> 1189
A7: C8 | B7: 46090 | C7: Cleaning + Pension + Bituch Leumi 02.2026 | D7: David | F7: 353.43 | N7: Y | P7: =R7-Q7 -> -353.43 | Q7: =SUBTOTAL(9,$F$2:F7) -> 1542.43 | R7: =SUBTOTAL(9,$G$2:G7) -> 1189
A8: C8 | B8: 46152 | C8: Cleaning + Pension + Bituch Leumi 04.2026 | D8: David | F8: 386.45 | N8: Y | O8: 46155 | P8: =R8-Q8 -> -739.88 | Q8: =SUBTOTAL(9,$F$2:F8) -> 1928.88 | R8: =SUBTOTAL(9,$G$2:G8) -> 1189
A9: C8 | B9: 46166 | C9: Advance | G9: 3000 | L9: leumi receipt | M9: 130360 | P9: =R9-Q9 -> 2260.12 | Q9: =SUBTOTAL(9,$F$2:F9) -> 1928.88 | R9: =SUBTOTAL(9,$G$2:G9) -> 4189
A10: C8 | B10: 46173 | C10: Exterminator | F10: 650 | L10: ישי הדברות | M10: 1470 | P10: =R10-Q10 -> 1610.12 | Q10: =SUBTOTAL(9,$F$2:F10) -> 2578.88 | R10: =SUBTOTAL(9,$G$2:G10) -> 4189
A11: C8 | B11: 46301 | C11: Cleaning + Pension + Bituch Leumi 05.2026 | F11: 1062 | P11: =R11-Q11 -> 548.12 | Q11: =SUBTOTAL(9,$F$2:F11) -> 3640.88 | R11: =SUBTOTAL(9,$G$2:G11) -> 4189
A12: C8 | B12: 46211 | C12: Cleaning + Pension + Bitauch Leumi 06.2026 | F12: 273.39 | L12: david | P12: =R12-Q12 -> 274.73 | Q12: =SUBTOTAL(9,$F$2:F12) -> 3914.27 | R12: =SUBTOTAL(9,$G$2:G12) -> 4189

Sheet 13
A1: Prop ID | B1: Date | C1: Section | D1: Notes | E1: Type | F1: Amount | G1: Inflow | H1: He/She paid | I1: Method | J1: Reconciled | K1: Company | L1: Reciept | M1: Rental income | N1: Reported | O1: Report sent | P1: Balance | Q1: Total Amount | R1: Total Inflow
A2: 13 | B2: 44790 | C2: Advance | G2: 6000 | N2: Y | P2: =R2-Q2 -> 6000 | Q2: =SUBTOTAL(9,$F$2:F2) -> 0 | R2: =SUBTOTAL(9,$G$2:G2) -> 6000
A3: 13 | B3: 44798 | C3: Plumber | F3: 1404 | N3: Y | P3: =R3-Q3 -> 4596 | Q3: =SUBTOTAL(9,$F$2:F3) -> 1404 | R3: =SUBTOTAL(9,$G$2:G3) -> 6000
A4: 13 | B4: 44808 | C4: Deductible - Harel Blue | F4: 200 | N4: Y | P4: =R4-Q4 -> 4396 | Q4: =SUBTOTAL(9,$F$2:F4) -> 1604 | R4: =SUBTOTAL(9,$G$2:G4) -> 6000
A5: 13 | B5: 44834 | C5: Electric bill 8/7/22-28/9/22 | H5: 158.96 | N5: Y | P5: =R5-Q5 -> 4396 | Q5: =SUBTOTAL(9,$F$2:F5) -> 1604 | R5: =SUBTOTAL(9,$G$2:G5) -> 6000
A6: 13 | B6: 44846 | C6: Advance | G6: 9360 | N6: Y | P6: =R6-Q6 -> 13756 | Q6: =SUBTOTAL(9,$F$2:F6) -> 1604 | R6: =SUBTOTAL(9,$G$2:G6) -> 15360
A7: 13 | B7: 44874 | C7: Replacement of new feed pipes + all feed pipes under the house | D7: החלפת צנרת הזנה חדשה + כל צנרת ההזנה שתחת הבית | F7: 9360 | I7: t | K7: דוד ביטון | L7: 5372 | N7: Y | P7: =R7-Q7 -> 4396 | Q7: =SUBTOTAL(9,$F$2:F7) -> 10964 | R7: =SUBTOTAL(9,$G$2:G7) -> 15360
A8: 13 | B8: 44886 | C8: Repair of water leak in the kitchen | F8: 300 | I8: t | K8: דוד ביטון | L8: 5394 | N8: Y | P8: =R8-Q8 -> 4096 | Q8: =SUBTOTAL(9,$F$2:F8) -> 11264 | R8: =SUBTOTAL(9,$G$2:G8) -> 15360
A9: 13 | B9: 44897 | C9: Advance | G9: 14614.8 | N9: Y | P9: =R9-Q9 -> 18710.8 | Q9: =SUBTOTAL(9,$F$2:F9) -> 11264 | R9: =SUBTOTAL(9,$G$2:G9) -> 29974.8
A10: 13 | B10: 44899 | C10: Gardener November 2022 | F10: 14614.8 | I10: t | K10: גרהם | N10: Y | P10: =R10-Q10 -> 4096 | Q10: =SUBTOTAL(9,$F$2:F10) -> 25878.8 | R10: =SUBTOTAL(9,$G$2:G10) -> 29974.8
A11: 13 | B11: 44903 | C11: Measuring 2 shower stalls | F11: 100 | I11: מזומן | N11: Y | P11: =R11-Q11 -> 3996 | Q11: =SUBTOTAL(9,$F$2:F11) -> 25978.8 | R11: =SUBTOTAL(9,$G$2:G11) -> 29974.8
A12: 13 | B12: 44909 | C12: Tiles for panels | F12: 200 | I12: cc | K12: רוניס אריחים | L12: 225000434 | N12: Y | P12: =R12-Q12 -> 3796 | Q12: =SUBTOTAL(9,$F$2:F12) -> 26178.8 | R12: =SUBTOTAL(9,$G$2:G12) -> 29974.8
A13: 13 | B13: 44909 | C13: Cutting panels | F13: 100 | I13: מזומן | K13: שיש פרדיס | L13: 2948 | N13: Y | P13: =R13-Q13 -> 3696 | Q13: =SUBTOTAL(9,$F$2:F13) -> 26278.8 | R13: =SUBTOTAL(9,$G$2:G13) -> 29974.8
A14: 13 | B14: 44916 | C14: Walk-in Showers | F14: 3730 | I14: CC | K14: רוניס | L14: 229001282 | N14: Y | P14: =R14-Q14 -> -34 | Q14: =SUBTOTAL(9,$F$2:F14) -> 30008.8 | R14: =SUBTOTAL(9,$G$2:G14) -> 29974.8
A15: 13 | B15: 44929 | C15: Itching and moisture in the walls | D15: גירוד רטיבות בקירות | F15: 150 | I15: t | N15: Y | P15: =R15-Q15 -> -184 | Q15: =SUBTOTAL(9,$F$2:F15) -> 30158.8 | R15: =SUBTOTAL(9,$G$2:G15) -> 29974.8
A16: 13 | B16: 44931 | C16: Advance | G16: 14989.8 | N16: Y | P16: =R16-Q16 -> 14805.8 | Q16: =SUBTOTAL(9,$F$2:F16) -> 30158.8 | R16: =SUBTOTAL(9,$G$2:G16) -> 44964.6
A17: 13 | B17: 44938 | C17: Cutting panels | E17: שולם ע"י אלישבע 40 ₪ | F17: 40 | I17: מזומן | K17: שיש פרדיס | L17: 2948 | N17: Y | P17: =R17-Q17 -> 14765.8 | Q17: =SUBTOTAL(9,$F$2:F17) -> 30198.8 | R17: =SUBTOTAL(9,$G$2:G17) -> 44964.6
A18: 13 | B18: 44948 | C18: Sealing work in the shower stall | D18: עבודת איטום במקלחון | F18: 819 | I18: t | K18: דוד ביטון | L18: 5408 | N18: Y | P18: =R18-Q18 -> 13946.8 | Q18: =SUBTOTAL(9,$F$2:F18) -> 31017.8 | R18: =SUBTOTAL(9,$G$2:G18) -> 44964.6
A19: 13 | B19: 44948 | C19: Bypassing a leaky drainage line in the shower stall room | D19: ביצוע מעקף קו ניקוז דלוחי בחדר המקלחון | F19: 8951 | I19: t | K19: דוד ביטון | L19: 5409 | N19: Y | P19: =R19-Q19 -> 4995.8 | Q19: =SUBTOTAL(9,$F$2:F19) -> 39968.8 | R19: =SUBTOTAL(9,$G$2:G19) -> 44964.6
A20: 13 | B20: 44964 | C20: Rental of moisture-absorbing equipment for drying wet cavities | D20: השכרת ציוד סופחי לחות לייבוש חללים רטובים | F20: 1755 | I20: t | K20: דוד ביטון | L20: 5428 | N20: Y | P20: =R20-Q20 -> 3240.8 | Q20: =SUBTOTAL(9,$F$2:F20) -> 41723.8 | R20: =SUBTOTAL(9,$G$2:G20) -> 44964.6
A21: 13 | B21: 44977 | C21: Front porch flooring | F21: 1880 | I21: cc | K21: רוניס | L21: 239000124 | N21: Y | P21: =R21-Q21 -> 1360.8 | Q21: =SUBTOTAL(9,$F$2:F21) -> 43603.8 | R21: =SUBTOTAL(9,$G$2:G21) -> 44964.6
A22: 13 | B22: 44992 | C22: Scratching moisture from the walls | D22: גירוד רטיבות קירות | E22: אושר | F22: 200 | I22: t | N22: Y | P22: =R22-Q22 -> 1160.8 | Q22: =SUBTOTAL(9,$F$2:F22) -> 43803.8 | R22: =SUBTOTAL(9,$G$2:G22) -> 44964.6
A23: 13 | B23: 44998 | C23: Advance | G23: 9466.8 | N23: Y | P23: =R23-Q23 -> 10627.6 | Q23: =SUBTOTAL(9,$F$2:F23) -> 43803.8 | R23: =SUBTOTAL(9,$G$2:G23) -> 54431.4
A24: 13 | B24: 45011 | C24: Short circuit repair | D24: תיקון קצר חשמלי | F24: 300 | I24: t | K24: איתי דרור | N24: Y | P24: =R24-Q24 -> 10327.6 | Q24: =SUBTOTAL(9,$F$2:F24) -> 44103.8 | R24: =SUBTOTAL(9,$G$2:G24) -> 54431.4
A25: 13 | B25: 45012 | C25: Dismantling ceramics, sealing and flooring including stairs | D25: פירוק קרמיקה, איטום וריצוף כולל מדרגות | F25: 9477 | I25: t | K25: אריה מרדכי | L25: 513 | N25: Y | P25: =R25-Q25 -> 850.6 | Q25: =SUBTOTAL(9,$F$2:F25) -> 53580.8 | R25: =SUBTOTAL(9,$G$2:G25) -> 54431.4
A26: 13 | B26: 45049 | C26: Hanging toilet | F26: 930 | I26: cc | K26: רוניס אריחים | L26: 235000124 | N26: Y | P26: =R26-Q26 -> -79.4 | Q26: =SUBTOTAL(9,$F$2:F26) -> 54510.8 | R26: =SUBTOTAL(9,$G$2:G26) -> 54431.4
A27: 13 | B27: 45053 | C27: Toilet replacement | D27: החלפת אסלה | F27: 850 | I27: t | K27: דוד ביטון | L27: 5463 | N27: Y | P27: =R27-Q27 -> -929.4 | Q27: =SUBTOTAL(9,$F$2:F27) -> 55360.8 | R27: =SUBTOTAL(9,$G$2:G27) -> 54431.4
A28: 13 | B28: 45079 | C28: Advance | G28: 5254.8 | N28: Y | P28: =R28-Q28 -> 4325.4 | Q28: =SUBTOTAL(9,$F$2:F28) -> 55360.8 | R28: =SUBTOTAL(9,$G$2:G28) -> 59686.2
A29: 13 | B29: 45081 | C29: Underfloor drying | F29: 5265 | I29: t | K29: זיו פתרונות מקצועיים | L29: 714 | N29: Y | P29: =R29-Q29 -> -939.6 | Q29: =SUBTOTAL(9,$F$2:F29) -> 60625.8 | R29: =SUBTOTAL(9,$G$2:G29) -> 59686.2
A30: 13 | B30: 45085 | C30: Advance | G30: 9989.8 | N30: Y | P30: =R30-Q30 -> 9050.2 | Q30: =SUBTOTAL(9,$F$2:F30) -> 60625.8 | R30: =SUBTOTAL(9,$G$2:G30) -> 69676
A31: 13 | B31: 45106 | C31: Deposit | F31: 1000 | I31: t | K31: שרון דאלין | N31: Y | P31: =R31-Q31 -> 8050.2 | Q31: =SUBTOTAL(9,$F$2:F31) -> 61625.8 | R31: =SUBTOTAL(9,$G$2:G31) -> 69676
A32: 13 | B32: 45116 | C32: Niagara hidden leak repair | D32: אושר | E32: תיקון נזילה ניאגרה סמויה + החלפת מצוף וגומיות | F32: 350 | I32: t | N32: Y | P32: =R32-Q32 -> 7700.2 | Q32: =SUBTOTAL(9,$F$2:F32) -> 61975.8 | R32: =SUBTOTAL(9,$G$2:G32) -> 69676
A33: 13 | B33: 45146 | C33: Repair of hole flooring | D33: אושר | E33: תיקון ריצוף חורים | F33: 550 | I33: t | N33: Y | P33: =R33-Q33 -> 7150.2 | Q33: =SUBTOTAL(9,$F$2:F33) -> 62525.8 | R33: =SUBTOTAL(9,$G$2:G33) -> 69676
A34: 13 | B34: 45197 | C34: Painting | F34: 8500 | I34: t | K34: Caley Vernon Dal | N34: Y | O34: 45264 | P34: =R34-Q34 -> -1349.8 | Q34: =SUBTOTAL(9,$F$2:F34) -> 71025.8 | R34: =SUBTOTAL(9,$G$2:G34) -> 69676
A35: 13 | B35: 45287 | C35: Advance | G35: 9485.66 | N35: Y | P35: =R35-Q35 -> 8135.86 | Q35: =SUBTOTAL(9,$F$2:F35) -> 71025.8 | R35: =SUBTOTAL(9,$G$2:G35) -> 79161.66
A36: 13 | B36: 45385 | C36: Repairs and painting a laundry room + installation of 2 light fixtures | D36: אושר | E36: תיקונים + צביעת חדר כביסה + התקנת 2 גופי תאורה | F36: 400 | I36: t | N36: Y | P36: =R36-Q36 -> 7735.86 | Q36: =SUBTOTAL(9,$F$2:F36) -> 71425.8 | R36: =SUBTOTAL(9,$G$2:G36) -> 79161.66
A37: 13 | B37: 45440 | C37: Plumber | F37: 2457 | I37: t | K37: דוד ביטון | L37: 13888 | N37: Y | P37: =R37-Q37 -> 5278.86 | Q37: =SUBTOTAL(9,$F$2:F37) -> 73882.8 | R37: =SUBTOTAL(9,$G$2:G37) -> 79161.66
A38: 13 | B38: 45441 | C38: Advance | G38: 5265 | N38: Y | P38: =R38-Q38 -> 10543.86 | Q38: =SUBTOTAL(9,$F$2:F38) -> 73882.8 | R38: =SUBTOTAL(9,$G$2:G38) -> 84426.66
A39: 13 | B39: 45477 | C39: Scraping leak off walls | D39: osher | F39: 250 | I39: t | N39: Y | P39: =R39-Q39 -> 10293.86 | Q39: =SUBTOTAL(9,$F$2:F39) -> 74132.8 | R39: =SUBTOTAL(9,$G$2:G39) -> 84426.66
A40: 13 | B40: 45505 | C40: Construction - repairs + paint | D40: OSHER | F40: 4200 | I40: t | N40: Y | P40: =R40-Q40 -> 6093.86 | Q40: =SUBTOTAL(9,$F$2:F40) -> 78332.8 | R40: =SUBTOTAL(9,$G$2:G40) -> 84426.66
A41: 13 | B41: 45510 | C41: Plumber | F41: 5265 | I41: t | K41: דוד ביטון | L41: 40281 | N41: Y | P41: =R41-Q41 -> 828.86 | Q41: =SUBTOTAL(9,$F$2:F41) -> 83597.8 | R41: =SUBTOTAL(9,$G$2:G41) -> 84426.66
A42: 13 | B42: 45511 | C42: Faucet | F42: 60 | I42: cc | K42: בנדק | L42: 242427151 | N42: Y | P42: =R42-Q42 -> 768.86 | Q42: =SUBTOTAL(9,$F$2:F42) -> 83657.8 | R42: =SUBTOTAL(9,$G$2:G42) -> 84426.66
A43: 13 | B43: 45511 | C43: Pipe + 'Flower faucet' + plug - Sink supplies | F43: 329 | I43: cc | K43: בנדק | L43: 242427118 | N43: Y | P43: =R43-Q43 -> 439.86 | Q43: =SUBTOTAL(9,$F$2:F43) -> 83986.8 | R43: =SUBTOTAL(9,$G$2:G43) -> 84426.66
A44: 13 | B44: 45514 | C44: Leak repair + replace shower pipe | D44: osher | F44: 300 | I44: t | N44: Y | P44: =R44-Q44 -> 139.86 | Q44: =SUBTOTAL(9,$F$2:F44) -> 84286.8 | R44: =SUBTOTAL(9,$G$2:G44) -> 84426.66
A45: 13 | B45: 45524 | C45: Replacing 3 faucets + 2 extension pipes | D45: osher | F45: 400 | I45: t | N45: Y | O45: 45543 | P45: =R45-Q45 -> -260.14 | Q45: =SUBTOTAL(9,$F$2:F45) -> 84686.8 | R45: =SUBTOTAL(9,$G$2:G45) -> 84426.66
A46: 13 | B46: 45627 | C46: Advance | G46: 2260.16 | N46: Y | P46: =R46-Q46 -> 2000.02 | Q46: =SUBTOTAL(9,$F$2:F46) -> 84686.8 | R46: =SUBTOTAL(9,$G$2:G46) -> 86686.82
A47: 13 | B47: 45650 | C47: Handyman supplies | F47: 321 | I47: cc | K47: בנדק | L47: 242445163 | N47: Y | P47: =R47-Q47 -> 1679.02 | Q47: =SUBTOTAL(9,$F$2:F47) -> 85007.8 | R47: =SUBTOTAL(9,$G$2:G47) -> 86686.82
A48: 13 | B48: 45650 | C48: Handyman supplies | F48: 72 | I48: cc | K48: בנדק | L48: 242445188 | N48: Y | P48: =R48-Q48 -> 1607.02 | Q48: =SUBTOTAL(9,$F$2:F48) -> 85079.8 | R48: =SUBTOTAL(9,$G$2:G48) -> 86686.82
A49: 13 | B49: 45661 | C49: Instal tap + filling holes in floor | D49: Osher | F49: 650 | I49: t | N49: Y | P49: =R49-Q49 -> 957.02 | Q49: =SUBTOTAL(9,$F$2:F49) -> 85729.8 | R49: =SUBTOTAL(9,$G$2:G49) -> 86686.82
A50: 13 | B50: 45788 | C50: Mold-resistant silicone sealing in the shower | D50: Osher | F50: 250 | N50: Y | P50: =R50-Q50 -> 707.02 | Q50: =SUBTOTAL(9,$F$2:F50) -> 85979.8 | R50: =SUBTOTAL(9,$G$2:G50) -> 86686.82
A51: 13 | B51: 45797 | C51: Tree pruning | F51: 4130 | I51: t | K51: אורי גיזומים | L51: 50494 | N51: Y | P51: =R51-Q51 -> -3422.98 | Q51: =SUBTOTAL(9,$F$2:F51) -> 90109.8 | R51: =SUBTOTAL(9,$G$2:G51) -> 86686.82
A52: 13 | B52: 45816 | C52: Tree pruning - participation in payment | G52: 1000 | N52: Y | P52: =R52-Q52 -> -2422.98 | Q52: =SUBTOTAL(9,$F$2:F52) -> 90109.8 | R52: =SUBTOTAL(9,$G$2:G52) -> 87686.82
A53: 13 | B53: 45818 | C53: Leak in concealed cistern – repair of mechanism + replacement of float valve | D53: osher | F53: 450 | N53: Y | O53: 45818 | P53: =R53-Q53 -> -2872.98 | Q53: =SUBTOTAL(9,$F$2:F53) -> 90559.8 | R53: =SUBTOTAL(9,$G$2:G53) -> 87686.82
A54: 13 | B54: 45825 | C54: Plumber - Pipeline inspection | F54: 472 | I54: t | K54: דוד ביטון | L54: 40116 | P54: =R54-Q54 -> -3344.98 | Q54: =SUBTOTAL(9,$F$2:F54) -> 91031.8 | R54: =SUBTOTAL(9,$G$2:G54) -> 87686.82
A55: 13 | B55: 45831 | C55: Advance | G55: 9872.98 | P55: =R55-Q55 -> 6528 | Q55: =SUBTOTAL(9,$F$2:F55) -> 91031.8 | R55: =SUBTOTAL(9,$G$2:G55) -> 97559.8
A56: 13 | B56: 45900 | C56: Dampness repairs and painting in the kitchen – materials and labor included. | F56: 2700 | I56: t | K56: אושר הנדימן | L56: 11 | P56: =R56-Q56 -> 3828 | Q56: =SUBTOTAL(9,$F$2:F56) -> 93731.8 | R56: =SUBTOTAL(9,$G$2:G56) -> 97559.8
A57: 13 | B57: 45901 | C57: sending garamtee checks to the lawyer | F57: 32.7 | I57: cc | K57: דואר ישראל | L57: 1062 | P57: =R57-Q57 -> 3795.3 | Q57: =SUBTOTAL(9,$F$2:F57) -> 93764.5 | R57: =SUBTOTAL(9,$G$2:G57) -> 97559.8
A58: 13 | B58: 45909 | C58: Plumber inspection | F58: 413 | I58: t | K58: דוד ביטון | L58: 40161 | P58: =R58-Q58 -> 3382.3 | Q58: =SUBTOTAL(9,$F$2:F58) -> 94177.5 | R58: =SUBTOTAL(9,$G$2:G58) -> 97559.8
A59: 13 | B59: 45921 | C59: Advance | G59: 9440 | P59: =R59-Q59 -> 12822.3 | Q59: =SUBTOTAL(9,$F$2:F59) -> 94177.5 | R59: =SUBTOTAL(9,$G$2:G59) -> 106999.8
A60: 13 | B60: 45928 | C60: Dismantling and Installing a Shower Enclosure | F60: 9440 | I60: t | K60: יא פרויקטים | L60: 25 | P60: =R60-Q60 -> 3382.3 | Q60: =SUBTOTAL(9,$F$2:F60) -> 103617.5 | R60: =SUBTOTAL(9,$G$2:G60) -> 106999.8

Sheet p14
A1: Prop ID | B1: Date | C1: Section | D1: Notes | E1: Type | F1: Amount | G1: Inflow | H1: He/She paid | I1: Method | J1: Reconciled | K1: Company | L1: Reciept | M1: Rental income | N1: Reported | O1: Report sent | P1: Balance | Q1: Total Amount | R1: Total Inflow
A2: P14 | B2: 44400 | C2: Advance for expenses | G2: 25000 | I2: t | J2: y | N2: Y | P2: =R2-Q2 -> 25000 | Q2: =SUBTOTAL(9,$F$2:F2) -> 0 | R2: =SUBTOTAL(9,$G$2:G2) -> 25000
A3: P14 | B3: 44403 | C3: Gas Connection - Lori Gas | F3: 150 | I3: cc | J3: y | N3: Y | P3: =R3-Q3 -> 24850 | Q3: =SUBTOTAL(9,$F$2:F3) -> 150 | R3: =SUBTOTAL(9,$G$2:G3) -> 25000
A4: P14 | B4: 44403 | C4: Locksmith | F4: 195 | I4: cc | J4: y | L4: 10700 | N4: Y | P4: =R4-Q4 -> 24655 | Q4: =SUBTOTAL(9,$F$2:F4) -> 345 | R4: =SUBTOTAL(9,$G$2:G4) -> 25000
A5: P14 | B5: 44404 | C5: Set up fee including VAT | F5: 5850 | I5: t | J5: y | N5: Y | P5: =R5-Q5 -> 18805 | Q5: =SUBTOTAL(9,$F$2:F5) -> 6195 | R5: =SUBTOTAL(9,$G$2:G5) -> 25000
A6: P14 | B6: 44414 | C6: Ikea Shop | F6: 10447 | I6: t | J6: y | K6: איקאה | L6: 152 | N6: Y | P6: =R6-Q6 -> 8358 | Q6: =SUBTOTAL(9,$F$2:F6) -> 16642 | R6: =SUBTOTAL(9,$G$2:G6) -> 25000
A7: P14 | B7: 44416 | C7: ido glas | F7: 800 | I7: t | J7: y | N7: Y | P7: =R7-Q7 -> 7558 | Q7: =SUBTOTAL(9,$F$2:F7) -> 17442 | R7: =SUBTOTAL(9,$G$2:G7) -> 25000
A8: P14 | B8: 44416 | C8: Down Payment for Glass in Bathrooms | F8: 7446 | I8: cc | J8: y | N8: Y | P8: =R8-Q8 -> 112 | Q8: =SUBTOTAL(9,$F$2:F8) -> 24888 | R8: =SUBTOTAL(9,$G$2:G8) -> 25000
A9: P14 | B9: 44417 | C9: Pandazzz - 3 Mattresses + Bedfram | F9: 296.6 | I9: cc | J9: y | L9: 8731 | N9: Y | P9: =R9-Q9 -> -184.6 | Q9: =SUBTOTAL(9,$F$2:F9) -> 25184.6 | R9: =SUBTOTAL(9,$G$2:G9) -> 25000
A10: P14 | B10: 44418 | C10: Dan Deal - Cleaning Supplies | F10: 48.8 | I10: cc | J10: y | L10: 5988 | N10: Y | P10: =R10-Q10 -> -233.4 | Q10: =SUBTOTAL(9,$F$2:F10) -> 25233.4 | R10: =SUBTOTAL(9,$G$2:G10) -> 25000
A11: P14 | B11: 44420 | C11: Politzer Supermarket - Cleaning Supplies | F11: 58.7 | I11: cc | J11: y | L11: 3252 | N11: Y | P11: =R11-Q11 -> -292.1 | Q11: =SUBTOTAL(9,$F$2:F11) -> 25292.1 | R11: =SUBTOTAL(9,$G$2:G11) -> 25000
A12: P14 | B12: 44420 | C12: Cleaning supplies | F12: 652 | I12: cc | J12: y | N12: Y | P12: =R12-Q12 -> -944.1 | Q12: =SUBTOTAL(9,$F$2:F12) -> 25944.1 | R12: =SUBTOTAL(9,$G$2:G12) -> 25000
A13: P14 | B13: 44421 | C13: Mezuzot - Klaf + Cover (5 Units) | F13: 89.6 | I13: cc | J13: y | L13: 3377 | N13: Y | P13: =R13-Q13 -> -1033.7 | Q13: =SUBTOTAL(9,$F$2:F13) -> 26033.7 | R13: =SUBTOTAL(9,$G$2:G13) -> 25000
A14: P14 | B14: 44421 | C14: Fox- housewares | F14: 855.03 | I14: cc | J14: y | L14: 931 | N14: Y | P14: =R14-Q14 -> -1888.73 | Q14: =SUBTOTAL(9,$F$2:F14) -> 26888.73 | R14: =SUBTOTAL(9,$G$2:G14) -> 25000
A15: P14 | B15: 44423 | C15: Laundry rack | F15: 50 | I15: cc | J15: y | L15: 9998 | N15: Y | P15: =R15-Q15 -> -1938.73 | Q15: =SUBTOTAL(9,$F$2:F15) -> 26938.73 | R15: =SUBTOTAL(9,$G$2:G15) -> 25000
A16: P14 | B16: 44423 | C16: Sheets | F16: 180 | I16: cc | J16: y | N16: Y | P16: =R16-Q16 -> -2118.73 | Q16: =SUBTOTAL(9,$F$2:F16) -> 27118.73 | R16: =SUBTOTAL(9,$G$2:G16) -> 25000
A17: P14 | B17: 44423 | C17: House supplies | F17: 190 | I17: cc | J17: y | L17: 9996 | N17: Y | P17: =R17-Q17 -> -2308.73 | Q17: =SUBTOTAL(9,$F$2:F17) -> 27308.73 | R17: =SUBTOTAL(9,$G$2:G17) -> 25000
A18: P14 | B18: 44423 | C18: Tap Installation + Hot Water Fix | F18: 421 | I18: t | J18: y | K18: דויד נתן | L18: 152 | N18: Y | O18: 44423 | P18: =R18-Q18 -> -2729.73 | Q18: =SUBTOTAL(9,$F$2:F18) -> 27729.73 | R18: =SUBTOTAL(9,$G$2:G18) -> 25000
A19: P14 | B19: 44425 | C19: Advance for expenses | G19: 10000 | I19: t | J19: y | N19: Y | P19: =R19-Q19 -> 7270.27 | Q19: =SUBTOTAL(9,$F$2:F19) -> 27729.73 | R19: =SUBTOTAL(9,$G$2:G19) -> 35000
A20: P14 | B20: 44430 | C20: Hot - August 2021 | F20: 109.62 | I20: cc | J20: y | N20: Y | P20: =R20-Q20 -> 7160.65 | Q20: =SUBTOTAL(9,$F$2:F20) -> 27839.35 | R20: =SUBTOTAL(9,$G$2:G20) -> 35000
A21: P14 | B21: 44438 | C21: Shower glass | F21: 3350 | N21: Y | P21: =R21-Q21 -> 3810.65 | Q21: =SUBTOTAL(9,$F$2:F21) -> 31189.35 | R21: =SUBTOTAL(9,$G$2:G21) -> 35000
A22: P14 | B22: 44441 | C22: Shower installation | F22: 1170 | I22: שק | J22: y | K22: מאי גלאס | L22: 227 | N22: Y | P22: =R22-Q22 -> 2640.65 | Q22: =SUBTOTAL(9,$F$2:F22) -> 32359.35 | R22: =SUBTOTAL(9,$G$2:G22) -> 35000
A23: P14 | B23: 44449 | C23: Cleaner August 2021 | F23: 160.49 | N23: Y | P23: =R23-Q23 -> 2480.16 | Q23: =SUBTOTAL(9,$F$2:F23) -> 32519.84 | R23: =SUBTOTAL(9,$G$2:G23) -> 35000
A24: P14 | B24: 44454 | C24: Cleaner Pension 2021 | F24: 29.32 | N24: Y | P24: =R24-Q24 -> 2450.84 | Q24: =SUBTOTAL(9,$F$2:F24) -> 32549.16 | R24: =SUBTOTAL(9,$G$2:G24) -> 35000
A25: P14 | B25: 44456 | C25: Handyman Furniture assembly | F25: 3568 | K25: אשר ברינבאום | L25: 972 | N25: Y | P25: =R25-Q25 -> -1117.16 | Q25: =SUBTOTAL(9,$F$2:F25) -> 36117.16 | R25: =SUBTOTAL(9,$G$2:G25) -> 35000
A26: P14 | B26: 44459 | C26: Bituach leumi Cleaner | F26: 16.56 | N26: Y | P26: =R26-Q26 -> -1133.72 | Q26: =SUBTOTAL(9,$F$2:F26) -> 36133.72 | R26: =SUBTOTAL(9,$G$2:G26) -> 35000
A27: P14 | B27: 44461 | C27: Hot - September 2021 | F27: 98.91 | I27: cc | J27: y | N27: Y | P27: =R27-Q27 -> -1232.63 | Q27: =SUBTOTAL(9,$F$2:F27) -> 36232.63 | R27: =SUBTOTAL(9,$G$2:G27) -> 35000
A28: P14 | B28: 44461 | C28: Cleaning service | F28: 690 | I28: t | J28: y | K28: מישיב סטניסלב | L28: 1279 | N28: Y | O28: 44463 | P28: =R28-Q28 -> -1922.63 | Q28: =SUBTOTAL(9,$F$2:F28) -> 36922.63 | R28: =SUBTOTAL(9,$G$2:G28) -> 35000
A29: P14 | B29: 44474 | C29: Advance for expenses | G29: 10000 | N29: Y | P29: =R29-Q29 -> 8077.37 | Q29: =SUBTOTAL(9,$F$2:F29) -> 36922.63 | R29: =SUBTOTAL(9,$G$2:G29) -> 45000
A30: P14 | B30: 44475 | C30: Management Fee | F30: 2457 | N30: Y | P30: =R30-Q30 -> 5620.37 | Q30: =SUBTOTAL(9,$F$2:F30) -> 39379.63 | R30: =SUBTOTAL(9,$G$2:G30) -> 45000
A31: P14 | B31: 44486 | C31: Hot - October 2021 | F31: 98.91 | I31: cc | J31: y | N31: Y | P31: =R31-Q31 -> 5521.46 | Q31: =SUBTOTAL(9,$F$2:F31) -> 39478.54 | R31: =SUBTOTAL(9,$G$2:G31) -> 45000
A32: P14 | B32: 44494 | C32: Gas bill | F32: 41.1 | K32: לורי גז | L32: 249659 | N32: Y | P32: =R32-Q32 -> 5480.36 | Q32: =SUBTOTAL(9,$F$2:F32) -> 39519.64 | R32: =SUBTOTAL(9,$G$2:G32) -> 45000
A33: P14 | B33: 44496 | C33: Meat pots | F33: 567 | N33: Y | P33: =R33-Q33 -> 4913.36 | Q33: =SUBTOTAL(9,$F$2:F33) -> 40086.64 | R33: =SUBTOTAL(9,$G$2:G33) -> 45000
A34: P14 | B34: 44516 | C34: Gas bill | F34: 35.4 | I34: cc | J34: y | K34: לורי גז | L34: 252548 | N34: Y | P34: =R34-Q34 -> 4877.96 | Q34: =SUBTOTAL(9,$F$2:F34) -> 40122.04 | R34: =SUBTOTAL(9,$G$2:G34) -> 45000
A35: P14 | B35: 44516 | C35: Hot - November 2021 | F35: 111.16 | I35: cc | J35: y | N35: Y | P35: =R35-Q35 -> 4766.8 | Q35: =SUBTOTAL(9,$F$2:F35) -> 40233.2 | R35: =SUBTOTAL(9,$G$2:G35) -> 45000
A36: P14 | B36: 44524 | C36: Plates and soup bowls | F36: 493.6 | I36: cc | J36: y | K36: Zara Home On line | N36: Y | P36: =R36-Q36 -> 4273.2 | Q36: =SUBTOTAL(9,$F$2:F36) -> 40726.8 | R36: =SUBTOTAL(9,$G$2:G36) -> 45000
A37: P14 | B37: 44528 | C37: Electric bill | F37: 601.23 | I37: cc | J37: y | K37: חברת חשמל | N37: Y | P37: =R37-Q37 -> 3671.97 | Q37: =SUBTOTAL(9,$F$2:F37) -> 41328.03 | R37: =SUBTOTAL(9,$G$2:G37) -> 45000
A38: P14 | B38: 44531 | C38: Silverware | D38: שולם על ידי ציונה | F38: 247.9 | N38: Y | P38: =R38-Q38 -> 3424.07 | Q38: =SUBTOTAL(9,$F$2:F38) -> 41575.93 | R38: =SUBTOTAL(9,$G$2:G38) -> 45000
A39: P14 | B39: 44539 | C39: Cleaning Nov 2021 | D39: Elena | F39: 301 | N39: Y | P39: =R39-Q39 -> 3123.07 | Q39: =SUBTOTAL(9,$F$2:F39) -> 41876.93 | R39: =SUBTOTAL(9,$G$2:G39) -> 45000
A40: P14 | B40: 44545 | C40: Pension cleaning Nov 2021 | D40: Elena | F40: 58 | N40: Y | P40: =R40-Q40 -> 3065.07 | Q40: =SUBTOTAL(9,$F$2:F40) -> 41934.93 | R40: =SUBTOTAL(9,$G$2:G40) -> 45000
A41: P14 | B41: 44546 | C41: Hot - December 2021 | F41: 118.91 | I41: cc | K41: Hot | N41: Y | P41: =R41-Q41 -> 2946.16 | Q41: =SUBTOTAL(9,$F$2:F41) -> 42053.84 | R41: =SUBTOTAL(9,$G$2:G41) -> 45000
A42: P14 | B42: 44550 | C42: Bituach Leumi cleaning Nov 2021 | D42: Elena | F42: 24 | N42: Y | P42: =R42-Q42 -> 2922.16 | Q42: =SUBTOTAL(9,$F$2:F42) -> 42077.84 | R42: =SUBTOTAL(9,$G$2:G42) -> 45000
A43: P14 | B43: 44550 | C43: Mip fees | F43: 6844.5 | N43: Y | P43: =R43-Q43 -> -3922.34 | Q43: =SUBTOTAL(9,$F$2:F43) -> 48922.34 | R43: =SUBTOTAL(9,$G$2:G43) -> 45000
A44: P14 | B44: 44550 | C44: Mip fees - the right account | G44: 6844.5 | N44: Y | P44: =R44-Q44 -> 2922.16 | Q44: =SUBTOTAL(9,$F$2:F44) -> 48922.34 | R44: =SUBTOTAL(9,$G$2:G44) -> 51844.5
A45: P14 | B45: 44577 | C45: Hot - January 2022 | F45: 118.91 | I45: cc | K45: Hot | N45: Y | P45: =R45-Q45 -> 2803.25 | Q45: =SUBTOTAL(9,$F$2:F45) -> 49041.25 | R45: =SUBTOTAL(9,$G$2:G45) -> 51844.5
A46: P14 | B46: 44584 | C46: Gas filling for air conditioner | F46: 600 | K46: שי תיקונים והתקנות | L46: 20 | N46: Y | P46: =R46-Q46 -> 2203.25 | Q46: =SUBTOTAL(9,$F$2:F46) -> 49641.25 | R46: =SUBTOTAL(9,$G$2:G46) -> 51844.5
A47: P14 | B47: 44588 | C47: Heater discount | F47: -10.6 | I47: cc | K47: שקם אלקטריק | N47: Y | P47: =R47-Q47 -> 2213.85 | Q47: =SUBTOTAL(9,$F$2:F47) -> 49630.65 | R47: =SUBTOTAL(9,$G$2:G47) -> 51844.5
A48: P14 | B48: 44588 | C48: Heater repair | F48: 530 | I48: cc | K48: שקם אלקטריק | N48: Y | P48: =R48-Q48 -> 1683.85 | Q48: =SUBTOTAL(9,$F$2:F48) -> 50160.65 | R48: =SUBTOTAL(9,$G$2:G48) -> 51844.5
A49: P14 | B49: 44607 | C49: Gas bill | F49: 56 | I49: cc | K49: לורי גז | L49: 255495 | N49: Y | P49: =R49-Q49 -> 1627.85 | Q49: =SUBTOTAL(9,$F$2:F49) -> 50216.65 | R49: =SUBTOTAL(9,$G$2:G49) -> 51844.5
A50: P14 | B50: 44608 | C50: Hot - February 2022 | F50: 118.91 | I50: cc | K50: Hot | N50: Y | O50: 44619 | P50: =R50-Q50 -> 1508.94 | Q50: =SUBTOTAL(9,$F$2:F50) -> 50335.56 | R50: =SUBTOTAL(9,$G$2:G50) -> 51844.5
A51: P14 | B51: 44608 | C51: Electric bill | F51: 144.04 | I51: cc | K51: חברת חשמל | N51: Y | P51: =R51-Q51 -> 1364.9 | Q51: =SUBTOTAL(9,$F$2:F51) -> 50479.6 | R51: =SUBTOTAL(9,$G$2:G51) -> 51844.5
A52: P14 | B52: 44621 | C52: Advance for expenses | G52: 5000 | N52: Y | P52: =R52-Q52 -> 6364.9 | Q52: =SUBTOTAL(9,$F$2:F52) -> 50479.6 | R52: =SUBTOTAL(9,$G$2:G52) -> 56844.5
A53: P14 | B53: 44622 | C53: Air conditioner instalation | F53: 4360 | K53: שי תיקונים והתקנות | N53: Y | P53: =R53-Q53 -> 2004.9 | Q53: =SUBTOTAL(9,$F$2:F53) -> 54839.6 | R53: =SUBTOTAL(9,$G$2:G53) -> 56844.5
A54: P14 | B54: 44623 | C54: Electric bill | F54: 1036.91 | K54: חברת חשמל | N54: Y | P54: =R54-Q54 -> 967.99 | Q54: =SUBTOTAL(9,$F$2:F54) -> 55876.51 | R54: =SUBTOTAL(9,$G$2:G54) -> 56844.5
A55: P14 | B55: 44628 | C55: Mip fees - the right account | F55: 2457 | N55: Y | P55: =R55-Q55 -> -1489.01 | Q55: =SUBTOTAL(9,$F$2:F55) -> 58333.51 | R55: =SUBTOTAL(9,$G$2:G55) -> 56844.5
A56: P14 | B56: 44628 | C56: Electric bill paid by Ness | G56: 1037 | K56: רבקה נס | N56: Y | P56: =R56-Q56 -> -452.01 | Q56: =SUBTOTAL(9,$F$2:F56) -> 58333.51 | R56: =SUBTOTAL(9,$G$2:G56) -> 57881.5
A57: P14 | B57: 44628 | C57: Management Fee | G57: 2457 | N57: Y | P57: =R57-Q57 -> 2004.99 | Q57: =SUBTOTAL(9,$F$2:F57) -> 58333.51 | R57: =SUBTOTAL(9,$G$2:G57) -> 60338.5
A58: P14 | B58: 44629 | C58: Bird netting and timer for dud shemesh | F58: 1580 | K58: שיפוצי ירושלים | L58: 155 | N58: Y | P58: =R58-Q58 -> 424.99 | Q58: =SUBTOTAL(9,$F$2:F58) -> 59913.51 | R58: =SUBTOTAL(9,$G$2:G58) -> 60338.5
A59: P14 | B59: 44636 | C59: Hot - March 2022 | F59: 118.91 | I59: cc | K59: Hot | N59: Y | P59: =R59-Q59 -> 306.08 | Q59: =SUBTOTAL(9,$F$2:F59) -> 60032.42 | R59: =SUBTOTAL(9,$G$2:G59) -> 60338.5
A60: P14 | B60: 44668 | C60: Hot - April 2022 | F60: 118.91 | I60: cc | K60: Hot | N60: Y | P60: =R60-Q60 -> 187.17 | Q60: =SUBTOTAL(9,$F$2:F60) -> 60151.33 | R60: =SUBTOTAL(9,$G$2:G60) -> 60338.5
A61: P14 | B61: 44689 | C61: Electric bill | F61: 765.49 | I61: cc | K61: חברת חשמל | N61: Y | P61: =R61-Q61 -> -578.32 | Q61: =SUBTOTAL(9,$F$2:F61) -> 60916.82 | R61: =SUBTOTAL(9,$G$2:G61) -> 60338.5
A62: P14 | B62: 44691 | C62: Electric bill paid by Ness | G62: 765.49 | I62: cc | K62: חברת חשמל | N62: Y | P62: =R62-Q62 -> 187.17 | Q62: =SUBTOTAL(9,$F$2:F62) -> 60916.82 | R62: =SUBTOTAL(9,$G$2:G62) -> 61103.99
A63: P14 | B63: 44697 | C63: Hot - May 2022 | F63: 118.91 | I63: cc | K63: Hot | N63: Y | P63: =R63-Q63 -> 68.26 | Q63: =SUBTOTAL(9,$F$2:F63) -> 61035.73 | R63: =SUBTOTAL(9,$G$2:G63) -> 61103.99
A64: P14 | B64: 44703 | C64: Gas bill | F64: 235.7 | I64: cc | J64: ציונה | K64: לורי גז | N64: Y | P64: =R64-Q64 -> -167.44 | Q64: =SUBTOTAL(9,$F$2:F64) -> 61271.43 | R64: =SUBTOTAL(9,$G$2:G64) -> 61103.99
A65: P14 | B65: 44728 | C65: Hot - June 2022 | F65: 118.91 | I65: cc | K65: Hot | N65: Y | O65: 44741 | P65: =R65-Q65 -> -286.35 | Q65: =SUBTOTAL(9,$F$2:F65) -> 61390.34 | R65: =SUBTOTAL(9,$G$2:G65) -> 61103.99
A66: P14 | B66: 44749 | C66: Advance for expenses | G66: 4989.9 | N66: Y | P66: =R66-Q66 -> 4703.55 | Q66: =SUBTOTAL(9,$F$2:F66) -> 61390.34 | R66: =SUBTOTAL(9,$G$2:G66) -> 66093.89
A67: P14 | B67: 44750 | C67: Hot - July 2022 | F67: 118.91 | I67: cc | K67: Hot | N67: Y | P67: =R67-Q67 -> 4584.64 | Q67: =SUBTOTAL(9,$F$2:F67) -> 61509.25 | R67: =SUBTOTAL(9,$G$2:G67) -> 66093.89
A68: P14 | B68: 44756 | C68: Advance - paid by Ross \ Campbell | G68: 10185 | N68: Y | P68: =R68-Q68 -> 14769.64 | Q68: =SUBTOTAL(9,$F$2:F68) -> 61509.25 | R68: =SUBTOTAL(9,$G$2:G68) -> 76278.89
A69: P14 | B69: 44770 | C69: Electric bill | F69: 1423.69 | I69: cc | K69: חברת חשמל | N69: Y | P69: =R69-Q69 -> 13345.95 | Q69: =SUBTOTAL(9,$F$2:F69) -> 62932.94 | R69: =SUBTOTAL(9,$G$2:G69) -> 76278.89
A70: P14 | B70: 44773 | C70: Cleaning | F70: 438.75 | I70: t | K70: אקו קלין הום | L70: 1410 | N70: Y | P70: =R70-Q70 -> 12907.2 | Q70: =SUBTOTAL(9,$F$2:F70) -> 63371.69 | R70: =SUBTOTAL(9,$G$2:G70) -> 76278.89
A71: P14 | B71: 44775 | C71: Cleaning supplies | F71: 181.9 | K71: פוליצר חדרה | L71: 90889 | N71: Y | P71: =R71-Q71 -> 12725.3 | Q71: =SUBTOTAL(9,$F$2:F71) -> 63553.59 | R71: =SUBTOTAL(9,$G$2:G71) -> 76278.89
A72: P14 | B72: 44789 | C72: Hot - August 2022 | F72: 118.91 | I72: cc | K72: Hot | N72: Y | P72: =R72-Q72 -> 12606.39 | Q72: =SUBTOTAL(9,$F$2:F72) -> 63672.5 | R72: =SUBTOTAL(9,$G$2:G72) -> 76278.89
A73: P14 | B73: 44808 | C73: linens | F73: 297 | K73: מועדון הכותנה | L73: 112000692 | N73: Y | P73: =R73-Q73 -> 12309.39 | Q73: =SUBTOTAL(9,$F$2:F73) -> 63969.5 | R73: =SUBTOTAL(9,$G$2:G73) -> 76278.89
A74: P14 | B74: 44809 | C74: Real Estate consulting fee - paid by Ross \ Campbell | F74: 799.11 | N74: Y | P74: =R74-Q74 -> 11510.28 | Q74: =SUBTOTAL(9,$F$2:F74) -> 64768.61 | R74: =SUBTOTAL(9,$G$2:G74) -> 76278.89
A75: P14 | B75: 44809 | C75: Advance - paid by Ross \ Campbell | G75: 4694 | N75: Y | P75: =R75-Q75 -> 16204.28 | Q75: =SUBTOTAL(9,$F$2:F75) -> 64768.61 | R75: =SUBTOTAL(9,$G$2:G75) -> 80972.89
A76: P14 | B76: 44812 | C76: Bituach Leumi cleaning August 2022 | D76: Elena | F76: 22 | N76: Y | P76: =R76-Q76 -> 16182.28 | Q76: =SUBTOTAL(9,$F$2:F76) -> 64790.61 | R76: =SUBTOTAL(9,$G$2:G76) -> 80972.89
A77: P14 | B77: 44812 | C77: Pension cleaning August 2022 | D77: Elena | F77: 56 | N77: Y | P77: =R77-Q77 -> 16126.28 | Q77: =SUBTOTAL(9,$F$2:F77) -> 64846.61 | R77: =SUBTOTAL(9,$G$2:G77) -> 80972.89
A78: P14 | B78: 44812 | C78: Cleaning August 2022 | D78: Elena | F78: 271 | N78: Y | P78: =R78-Q78 -> 15855.28 | Q78: =SUBTOTAL(9,$F$2:F78) -> 65117.61 | R78: =SUBTOTAL(9,$G$2:G78) -> 80972.89
A79: P14 | B79: 44813 | C79: Wall painting correction | D79: תיקון צבע בקיר | F79: 400 | N79: Y | P79: =R79-Q79 -> 15455.28 | Q79: =SUBTOTAL(9,$F$2:F79) -> 65517.61 | R79: =SUBTOTAL(9,$G$2:G79) -> 80972.89
A80: P14 | B80: 44820 | C80: Hot - September 2022 | F80: 118.91 | I80: cc | K80: Hot | N80: Y | P80: =R80-Q80 -> 15336.37 | Q80: =SUBTOTAL(9,$F$2:F80) -> 65636.52 | R80: =SUBTOTAL(9,$G$2:G80) -> 80972.89
A81: P14 | B81: 44840 | C81: Gas bill | F81: 40.8 | I81: cc | K81: לורי גז | L81: 265513 | N81: Y | P81: =R81-Q81 -> 15295.57 | Q81: =SUBTOTAL(9,$F$2:F81) -> 65677.32 | R81: =SUBTOTAL(9,$G$2:G81) -> 80972.89
A82: P14 | B82: 44840 | C82: Electric bill | F82: 70.09 | I82: cc | K82: חברת חשמל | L82: 471279720 | N82: Y | P82: =R82-Q82 -> 15225.48 | Q82: =SUBTOTAL(9,$F$2:F82) -> 65747.41 | R82: =SUBTOTAL(9,$G$2:G82) -> 80972.89
A83: P14 | B83: 44840 | C83: TV | F83: 1799 | I83: CC | K83: ברימאג | N83: Y | P83: =R83-Q83 -> 13426.48 | Q83: =SUBTOTAL(9,$F$2:F83) -> 67546.41 | R83: =SUBTOTAL(9,$G$2:G83) -> 80972.89
A84: P14 | B84: 44850 | C84: Hot - October 2022 | F84: 118.91 | I84: cc | K84: Hot | N84: Y | P84: =R84-Q84 -> 13307.57 | Q84: =SUBTOTAL(9,$F$2:F84) -> 67665.32 | R84: =SUBTOTAL(9,$G$2:G84) -> 80972.89
A85: P14 | B85: 44868 | C85: Bituach Leumi cleaning Octotber 2022 | D85: Elena | F85: 24 | N85: Y | P85: =R85-Q85 -> 13283.57 | Q85: =SUBTOTAL(9,$F$2:F85) -> 67689.32 | R85: =SUBTOTAL(9,$G$2:G85) -> 80972.89
A86: P14 | B86: 44868 | C86: Pension cleaning October 2022 | D86: Elena | F86: 60 | N86: Y | P86: =R86-Q86 -> 13223.57 | Q86: =SUBTOTAL(9,$F$2:F86) -> 67749.32 | R86: =SUBTOTAL(9,$G$2:G86) -> 80972.89
A87: P14 | B87: 44868 | C87: Cleaning October 2022 | D87: Elena | F87: 293 | N87: Y | P87: =R87-Q87 -> 12930.57 | Q87: =SUBTOTAL(9,$F$2:F87) -> 68042.32 | R87: =SUBTOTAL(9,$G$2:G87) -> 80972.89
A88: P14 | B88: 44869 | C88: Refund of deposit minus electricity bill | D88: החזר פקדון בניכוי חשמל | F88: 6367.06 | N88: Y | P88: =R88-Q88 -> 6563.51 | Q88: =SUBTOTAL(9,$F$2:F88) -> 74409.38 | R88: =SUBTOTAL(9,$G$2:G88) -> 80972.89
A89: P14 | B89: 44881 | C89: Hot - November 2022 | F89: 118.91 | I89: cc | K89: Hot | N89: Y | P89: =R89-Q89 -> 6444.6 | Q89: =SUBTOTAL(9,$F$2:F89) -> 74528.29 | R89: =SUBTOTAL(9,$G$2:G89) -> 80972.89
A90: P14 | B90: 44903 | C90: Hot - December 2022 | F90: 118.91 | I90: cc | K90: Hot | N90: Y | P90: =R90-Q90 -> 6325.69 | Q90: =SUBTOTAL(9,$F$2:F90) -> 74647.2 | R90: =SUBTOTAL(9,$G$2:G90) -> 80972.89
A91: P14 | B91: 44909 | C91: Towels and a blanket | F91: 399 | I91: cc | K91: מועדון הכותנה | L91: 112001633 | N91: Y | P91: =R91-Q91 -> 5926.69 | Q91: =SUBTOTAL(9,$F$2:F91) -> 75046.2 | R91: =SUBTOTAL(9,$G$2:G91) -> 80972.89
A92: P14 | B92: 44923 | C92: Electric bill | F92: 937.23 | I92: cc | K92: חברת חשמל | N92: Y | O92: 44924 | P92: =R92-Q92 -> 4989.46 | Q92: =SUBTOTAL(9,$F$2:F92) -> 75983.43 | R92: =SUBTOTAL(9,$G$2:G92) -> 80972.89
A93: P14 | B93: 44934 | C93: Hot - January 2023 | F93: 118.91 | I93: cc | K93: Hot | N93: Y | P93: =R93-Q93 -> 4870.55 | Q93: =SUBTOTAL(9,$F$2:F93) -> 76102.34 | R93: =SUBTOTAL(9,$G$2:G93) -> 80972.89
A94: P14 | B94: 44963 | C94: Installation of 4 ceiling fans and 4 ceiling lights | F94: 1591 | I94: t | K94: שיפוצי ירושלים | L94: 271 | N94: Y | P94: =R94-Q94 -> 3279.55 | Q94: =SUBTOTAL(9,$F$2:F94) -> 77693.34 | R94: =SUBTOTAL(9,$G$2:G94) -> 80972.89
A95: P14 | B95: 44963 | C95: Remove and plaster/paint over a/c piping in hallway | D95: =450*1.17 -> 526.5 | F95: =2012-F94 -> 421 | I95: t | K95: שיפוצי ירושלים | L95: 271 | N95: Y | P95: =R95-Q95 -> 2858.55 | Q95: =SUBTOTAL(9,$F$2:F95) -> 78114.34 | R95: =SUBTOTAL(9,$G$2:G95) -> 80972.89
A96: P14 | B96: 44973 | C96: Hot - February 2023 | F96: 118.91 | I96: cc | K96: Hot | N96: Y | P96: =R96-Q96 -> 2739.64 | Q96: =SUBTOTAL(9,$F$2:F96) -> 78233.25 | R96: =SUBTOTAL(9,$G$2:G96) -> 80972.89
A97: P14 | B97: 45001 | C97: Hot - March 2023 | F97: 118.91 | I97: cc | K97: Hot | N97: Y | P97: =R97-Q97 -> 2620.73 | Q97: =SUBTOTAL(9,$F$2:F97) -> 78352.16 | R97: =SUBTOTAL(9,$G$2:G97) -> 80972.89
A98: P14 | B98: 45008 | C98: Cleaning supplies | F98: 65.7 | I98: cc | K98: פוליצר פרדס חנה | N98: Y | P98: =R98-Q98 -> 2555.03 | Q98: =SUBTOTAL(9,$F$2:F98) -> 78417.86 | R98: =SUBTOTAL(9,$G$2:G98) -> 80972.89
A99: P14 | B99: 45029 | C99: Cleaning March 2023 | F99: 468 | I99: t | K99: סטניסלב מישייב | L99: 3822 | N99: Y | O99: 45029 | P99: =R99-Q99 -> 2087.03 | Q99: =SUBTOTAL(9,$F$2:F99) -> 78885.86 | R99: =SUBTOTAL(9,$G$2:G99) -> 80972.89
A100: P14 | B100: 45032 | C100: Hot - April 2023 | F100: 118.91 | I100: cc | K100: Hot | N100: Y | P100: =R100-Q100 -> 1968.12 | Q100: =SUBTOTAL(9,$F$2:F100) -> 79004.77 | R100: =SUBTOTAL(9,$G$2:G100) -> 80972.89
...

Sheet C15
A1: Prop ID | B1: Date | C1: Section | D1: Notes | E1: Type | F1: Amount | G1: Inflow | H1: He/She paid | I1: Method | J1: Reconciled | K1: Company | L1: Reciept | M1: Rental income | N1: Reported | O1: Report sent | P1: Balance | Q1: Total Amount | R1: Total Inflow
A2: C15 | B2: 44986 | C2: Keys | F2: 25 | I2: cc | K2: חיים מנעולים | L2: 11746-2 | N2: Y | P2: =R2-Q2 -> -25 | Q2: =SUBTOTAL(9,$F$2:F2) -> 25 | R2: =SUBTOTAL(9,$G$2:G2) -> 0
A3: C15 | B3: 45005 | C3: Cylinder for the front door | F3: 129 | I3: cc | K3: חומרי בניין דוד מלכה | L3: 6683 | N3: Y | P3: =R3-Q3 -> -154 | Q3: =SUBTOTAL(9,$F$2:F3) -> 154 | R3: =SUBTOTAL(9,$G$2:G3) -> 0
A4: C15 | B4: 45008 | C4: Keys | F4: 140 | I4: cc | K4: חיים מנעולים | L4: 11778-2 | N4: Y | P4: =R4-Q4 -> -294 | Q4: =SUBTOTAL(9,$F$2:F4) -> 294 | R4: =SUBTOTAL(9,$G$2:G4) -> 0
A5: C15 | B5: 45019 | C5: Replacement of front door cylinder | D5: אושר | E5: החלפת צילינדר דלת כניסה | F5: 250 | I5: t | N5: Y | P5: =R5-Q5 -> -544 | Q5: =SUBTOTAL(9,$F$2:F5) -> 544 | R5: =SUBTOTAL(9,$G$2:G5) -> 0
A6: C15 | B6: 45050 | C6: Leak repair | D6: אושר | E6: תיקון נזילה | F6: 150 | I6: t | N6: Y | P6: =R6-Q6 -> -694 | Q6: =SUBTOTAL(9,$F$2:F6) -> 694 | R6: =SUBTOTAL(9,$G$2:G6) -> 0
A7: C15 | B7: 45082 | C7: Exterminator termites ans fire ants | F7: 1800 | I7: t | K7: ישי הדברות | L7: 111 | N7: Y | P7: =R7-Q7 -> -2494 | Q7: =SUBTOTAL(9,$F$2:F7) -> 2494 | R7: =SUBTOTAL(9,$G$2:G7) -> 0
A8: C15 | B8: 45083 | C8: Mesh window repair + broken parking light fixture | D8: אושר | E8: תיקון חלון רשת + גוף תאורה שבור חנייה | F8: 250 | I8: t | N8: Y | P8: =R8-Q8 -> -2744 | Q8: =SUBTOTAL(9,$F$2:F8) -> 2744 | R8: =SUBTOTAL(9,$G$2:G8) -> 0
A9: C15 | B9: 45084 | C9: מטהר מים וברז מזיגה | F9: 990 | I9: cc | K9: אקווה ספרינג | L9: 8712 | N9: Y | O9: 45090 | P9: =R9-Q9 -> -3734 | Q9: =SUBTOTAL(9,$F$2:F9) -> 3734 | R9: =SUBTOTAL(9,$G$2:G9) -> 0
A10: C15 | B10: 45105 | C10: Advance | G10: 5000 | N10: Y | P10: =R10-Q10 -> 1266 | Q10: =SUBTOTAL(9,$F$2:F10) -> 3734 | R10: =SUBTOTAL(9,$G$2:G10) -> 5000
A11: C15 | B11: 45116 | C11: Leak repair and dosh head and hose replacement and window lock repair | D11: אושר | E11: תיקון נזילה + החלפת ראש דוש וצינור + תיקון נעילה חלון | F11: 280 | I11: t | N11: Y | P11: =R11-Q11 -> 986 | Q11: =SUBTOTAL(9,$F$2:F11) -> 4014 | R11: =SUBTOTAL(9,$G$2:G11) -> 5000
A12: C15 | B12: 45116 | C12: Upper shower sink leak repair + niagara leak repair | D12: אושר | E12: תיקון נזילה כיור מקלחת עליונה + תיקון נזילה ניאגרה + מצוף ניאגרה | F12: 330 | I12: t | N12: Y | P12: =R12-Q12 -> 656 | Q12: =SUBTOTAL(9,$F$2:F12) -> 4344 | R12: =SUBTOTAL(9,$G$2:G12) -> 5000
A13: C15 | B13: 45124 | C13: Cleaning supplies | F13: 47.8 | I13: cc | K13: טיב טעם | L13: 72818 | N13: Y | P13: =R13-Q13 -> 608.2 | Q13: =SUBTOTAL(9,$F$2:F13) -> 4391.8 | R13: =SUBTOTAL(9,$G$2:G13) -> 5000
A14: C15 | B14: 45137 | C14: Kitchen supplies | F14: 982 | I14: cc | K14: איקאה | L14: 59471 | N14: Y | P14: =R14-Q14 -> -373.8 | Q14: =SUBTOTAL(9,$F$2:F14) -> 5373.8 | R14: =SUBTOTAL(9,$G$2:G14) -> 5000
A15: C15 | B15: 45140 | C15: Mugs | F15: 71.76 | I15: cc | K15: פוקס | L15: 302254 | N15: Y | P15: =R15-Q15 -> -445.56 | Q15: =SUBTOTAL(9,$F$2:F15) -> 5445.56 | R15: =SUBTOTAL(9,$G$2:G15) -> 5000
A16: C15 | B16: 45151 | C16: A tool for cutlery | F16: 13.8 | I16: cc | K16: זול סטוק | L16: 1380886 | N16: Y | P16: =R16-Q16 -> -459.36 | Q16: =SUBTOTAL(9,$F$2:F16) -> 5459.36 | R16: =SUBTOTAL(9,$G$2:G16) -> 5000
A17: C15 | B17: 45151 | C17: Cleaning supplies | F17: 117.9 | I17: cc | K17: שופרסל דיל | L17: 95048174811 | N17: Y | P17: =R17-Q17 -> -577.26 | Q17: =SUBTOTAL(9,$F$2:F17) -> 5577.26 | R17: =SUBTOTAL(9,$G$2:G17) -> 5000
A18: C15 | B18: 45155 | C18: Air conditioner technician | F18: 250 | I18: t | K18: גביר רון | N18: Y | P18: =R18-Q18 -> -827.26 | Q18: =SUBTOTAL(9,$F$2:F18) -> 5827.26 | R18: =SUBTOTAL(9,$G$2:G18) -> 5000
A19: C15 | B19: 45155 | C19: Cleaning supplies | D19: החזר לסנדי | F19: 60 | I19: t | K19: חומרי בניין דוד מלכה | L19: 20076 | N19: Y | P19: =R19-Q19 -> -887.26 | Q19: =SUBTOTAL(9,$F$2:F19) -> 5887.26 | R19: =SUBTOTAL(9,$G$2:G19) -> 5000
A20: C15 | B20: 45162 | C20: Cleaning supplies | F20: 65.6 | I20: cc | K20: טיב טעם | L20: 91974 | N20: Y | P20: =R20-Q20 -> -952.86 | Q20: =SUBTOTAL(9,$F$2:F20) -> 5952.86 | R20: =SUBTOTAL(9,$G$2:G20) -> 5000
A21: C15 | B21: 45166 | C21: Plumber | F21: 670 | I21: t | K21: אמבולנס לאינסטלציה | L21: 567 | N21: Y | P21: =R21-Q21 -> -1622.86 | Q21: =SUBTOTAL(9,$F$2:F21) -> 6622.86 | R21: =SUBTOTAL(9,$G$2:G21) -> 5000
A22: C15 | B22: 45173 | C22: Hole repair in the wall - sealing + spillage + paint | D22: תיקון חור בקיר - איטום + שפכטל + צבע | F22: 1100 | I22: t | N22: Y | P22: =R22-Q22 -> -2722.86 | Q22: =SUBTOTAL(9,$F$2:F22) -> 7722.86 | R22: =SUBTOTAL(9,$G$2:G22) -> 5000
A23: C15 | B23: 45181 | C23: Laundry service | F23: 952 | I23: cc | K23: לה סויטה | L23: 2506 | N23: Y | P23: =R23-Q23 -> -3674.86 | Q23: =SUBTOTAL(9,$F$2:F23) -> 8674.86 | R23: =SUBTOTAL(9,$G$2:G23) -> 5000
A24: C15 | B24: 45190 | C24: צינור לכיור | F24: 94.05 | I24: cc | K24: חומרי בניין דוד מלכה ובניו | L24: 27824 | N24: Y | P24: =R24-Q24 -> -3768.91 | Q24: =SUBTOTAL(9,$F$2:F24) -> 8768.91 | R24: =SUBTOTAL(9,$G$2:G24) -> 5000
A25: C15 | B25: 45202 | C25: Leak repair | D25: אושר | E25: תיקון נזילה, סיפון נירוסטה | F25: 150 | I25: t | N25: Y | P25: =R25-Q25 -> -3918.91 | Q25: =SUBTOTAL(9,$F$2:F25) -> 8918.91 | R25: =SUBTOTAL(9,$G$2:G25) -> 5000
A26: C15 | B26: 45202 | C26: הגעלת כלי מטבח | D26: אבישי | F26: 125 | I26: t | N26: Y | P26: =R26-Q26 -> -4043.91 | Q26: =SUBTOTAL(9,$F$2:F26) -> 9043.91 | R26: =SUBTOTAL(9,$G$2:G26) -> 5000
A27: C15 | B27: 45214 | C27: Cleaning August 2023 | F27: 2948 | I27: t | K27: סטניסלב מישייב | L27: 4526 | N27: Y | O27: 45174 | P27: =R27-Q27 -> -6991.91 | Q27: =SUBTOTAL(9,$F$2:F27) -> 11991.91 | R27: =SUBTOTAL(9,$G$2:G27) -> 5000
A28: C15 | B28: 45214 | C28: Replacing ceramics in the master shower | F28: 1755 | I28: t | K28: חאמד הלאל | L28: 262 | N28: Y | P28: =R28-Q28 -> -8746.91 | Q28: =SUBTOTAL(9,$F$2:F28) -> 13746.91 | R28: =SUBTOTAL(9,$G$2:G28) -> 5000
A29: C15 | B29: 45215 | C29: Advance | G29: 12000 | N29: Y | P29: =R29-Q29 -> 3253.09 | Q29: =SUBTOTAL(9,$F$2:F29) -> 13746.91 | R29: =SUBTOTAL(9,$G$2:G29) -> 17000
A30: C15 | B30: 45249 | C30: Sewage clog release | F30: 585 | I30: t | K30: בורה שירותי ביוב ואינסטלציה | L30: 841 | N30: Y | P30: =R30-Q30 -> 2668.09 | Q30: =SUBTOTAL(9,$F$2:F30) -> 14331.91 | R30: =SUBTOTAL(9,$G$2:G30) -> 17000
A31: C15 | B31: 45271 | C31: Management MIP | G31: 11421.54 | N31: Y | P31: =R31-Q31 -> 14089.63 | Q31: =SUBTOTAL(9,$F$2:F31) -> 14331.91 | R31: =SUBTOTAL(9,$G$2:G31) -> 28421.54
A32: C15 | B32: 45272 | C32: Management MIP - the right account | F32: 11421.54 | I32: t | N32: Y | P32: =R32-Q32 -> 2668.09 | Q32: =SUBTOTAL(9,$F$2:F32) -> 25753.45 | R32: =SUBTOTAL(9,$G$2:G32) -> 28421.54
A33: C15 | B33: 45292 | C33: Handyman | F33: 468 | I33: t | K33: אשר בירנבאום | L33: 1322 | N33: Y | P33: =R33-Q33 -> 2200.09 | Q33: =SUBTOTAL(9,$F$2:F33) -> 26221.45 | R33: =SUBTOTAL(9,$G$2:G33) -> 28421.54
A34: C15 | B34: 45315 | C34: Plumber - evaltuation of the issue with camera | F34: 2574 | I34: t | K34: דוד ביטון | L34: 13719 | N34: Y | P34: =R34-Q34 -> -373.91 | Q34: =SUBTOTAL(9,$F$2:F34) -> 28795.45 | R34: =SUBTOTAL(9,$G$2:G34) -> 28421.54
A35: C15 | B35: 45335 | C35: Plumber - repair | F35: 3276 | I35: t | K35: דוד ביטון | L35: 13793 | N35: Y | O35: 45355 | P35: =R35-Q35 -> -3649.91 | Q35: =SUBTOTAL(9,$F$2:F35) -> 32071.45 | R35: =SUBTOTAL(9,$G$2:G35) -> 28421.54
A36: C15 | B36: 45358 | C36: Advance | G36: 10000 | N36: Y | P36: =R36-Q36 -> 6350.09 | Q36: =SUBTOTAL(9,$F$2:F36) -> 32071.45 | R36: =SUBTOTAL(9,$G$2:G36) -> 38421.54
A37: C15 | B37: 45427 | C37: Lockshmith | F37: 62 | I37: c6 | K37: חיים מנעולים | L37: 125324 | N37: Y | P37: =R37-Q37 -> 6288.09 | Q37: =SUBTOTAL(9,$F$2:F37) -> 32133.45 | R37: =SUBTOTAL(9,$G$2:G37) -> 38421.54
A38: C15 | B38: 45435 | C38: Plumber | H38: 5265 | K38: דוד ביטון | N38: Y | P38: =R38-Q38 -> 6288.09 | Q38: =SUBTOTAL(9,$F$2:F38) -> 32133.45 | R38: =SUBTOTAL(9,$G$2:G38) -> 38421.54
A39: C15 | B39: 45474 | C39: Instaling tap + fixing Niagara | D39: OSHER | F39: 400 | I39: t | N39: Y | P39: =R39-Q39 -> 5888.09 | Q39: =SUBTOTAL(9,$F$2:F39) -> 32533.45 | R39: =SUBTOTAL(9,$G$2:G39) -> 38421.54
A40: C15 | B40: 45475 | C40: Handyman supplies | F40: 480 | I40: cc | K40: חומרי בניין מלכה ובניו ‎ | L40: 50647 | N40: Y | P40: =R40-Q40 -> 5408.09 | Q40: =SUBTOTAL(9,$F$2:F40) -> 33013.45 | R40: =SUBTOTAL(9,$G$2:G40) -> 38421.54
A41: C15 | B41: 45476 | C41: Wooden table - taking apart and away | D41: OSHER | F41: 300 | I41: t | N41: Y | P41: =R41-Q41 -> 5108.09 | Q41: =SUBTOTAL(9,$F$2:F41) -> 33313.45 | R41: =SUBTOTAL(9,$G$2:G41) -> 38421.54
A42: C15 | B42: 45480 | C42: Fixing the Niagara + sealing niagara sewage pipe | D42: OSHER | F42: 300 | I42: t | N42: Y | P42: =R42-Q42 -> 4808.09 | Q42: =SUBTOTAL(9,$F$2:F42) -> 33613.45 | R42: =SUBTOTAL(9,$G$2:G42) -> 38421.54
A43: C15 | B43: 45481 | C43: Repairs + painting outside | D43: OSHER | F43: 450 | I43: t | N43: Y | P43: =R43-Q43 -> 4358.09 | Q43: =SUBTOTAL(9,$F$2:F43) -> 34063.45 | R43: =SUBTOTAL(9,$G$2:G43) -> 38421.54
A44: C15 | B44: 45487 | C44: Cleaning 06.2024 | F44: 737 | I44: t | K44: קלין סטס | L44: 1565 | N44: Y | P44: =R44-Q44 -> 3621.09 | Q44: =SUBTOTAL(9,$F$2:F44) -> 34800.45 | R44: =SUBTOTAL(9,$G$2:G44) -> 38421.54
A45: C15 | B45: 45489 | C45: Handyman supplies | F45: 160 | I45: cc | K45: חומרי בניין מלכה ובניו ‎ | L45: 52246 | N45: Y | P45: =R45-Q45 -> 3461.09 | Q45: =SUBTOTAL(9,$F$2:F45) -> 34960.45 | R45: =SUBTOTAL(9,$G$2:G45) -> 38421.54
A46: C15 | B46: 45493 | C46: Instaling washing dryer | D46: OSHER | F46: 250 | I46: t | N46: Y | P46: =R46-Q46 -> 3211.09 | Q46: =SUBTOTAL(9,$F$2:F46) -> 35210.45 | R46: =SUBTOTAL(9,$G$2:G46) -> 38421.54
A47: C15 | B47: 45495 | C47: plumber | H47: 14391 | K47: דוד ביטון | L47: 40264 | N47: Y | P47: =R47-Q47 -> 3211.09 | Q47: =SUBTOTAL(9,$F$2:F47) -> 35210.45 | R47: =SUBTOTAL(9,$G$2:G47) -> 38421.54
A48: C15 | B48: 45502 | C48: Exterminator | F48: 600 | I48: t | K48: ישי הדברות | L48: 557 | N48: Y | P48: =R48-Q48 -> 2611.09 | Q48: =SUBTOTAL(9,$F$2:F48) -> 35810.45 | R48: =SUBTOTAL(9,$G$2:G48) -> 38421.54
A49: C15 | B49: 45515 | C49: Plumber | F49: 500 | I49: t | K49: דוד ביטון | L49: 40282 | N49: Y | O49: 45523 | P49: =R49-Q49 -> 2111.09 | Q49: =SUBTOTAL(9,$F$2:F49) -> 36310.45 | R49: =SUBTOTAL(9,$G$2:G49) -> 38421.54
A50: C15 | B50: 45539 | C50: Cleaning 08.2024 | F50: 1053 | I50: t | K50: קלין סטס | L50: 1926 | N50: Y | P50: =R50-Q50 -> 1058.09 | Q50: =SUBTOTAL(9,$F$2:F50) -> 37363.45 | R50: =SUBTOTAL(9,$G$2:G50) -> 38421.54
A51: C15 | B51: 45539 | C51: Lights | F51: 1514 | I51: cc | K51: חשמל ישיר קיסריה | L51: 8863 | N51: Y | P51: =R51-Q51 -> -455.91 | Q51: =SUBTOTAL(9,$F$2:F51) -> 38877.45 | R51: =SUBTOTAL(9,$G$2:G51) -> 38421.54
A52: C15 | B52: 45552 | C52: Insulation & Sealing | F52: 1170 | I52: t | K52: אריה מרדכי | N52: Y | O52: 45564 | P52: =R52-Q52 -> -1625.91 | Q52: =SUBTOTAL(9,$F$2:F52) -> 40047.45 | R52: =SUBTOTAL(9,$G$2:G52) -> 38421.54
A53: C15 | B53: 45565 | C53: Laundry service | F53: 349 | I53: cc | K53: לה סוויטה | N53: Y | P53: =R53-Q53 -> -1974.91 | Q53: =SUBTOTAL(9,$F$2:F53) -> 40396.45 | R53: =SUBTOTAL(9,$G$2:G53) -> 38421.54
A54: C15 | B54: 45573 | C54: Cleaning 09.2024 | D54: David 7 hrs | F54: 495 | N54: Y | P54: =R54-Q54 -> -2469.91 | Q54: =SUBTOTAL(9,$F$2:F54) -> 40891.45 | R54: =SUBTOTAL(9,$G$2:G54) -> 38421.54
A55: C15 | B55: 45573 | C55: Bituch Leumi Cleaning September 2024 | D55: David | F55: 36 | N55: Y | P55: =R55-Q55 -> -2505.91 | Q55: =SUBTOTAL(9,$F$2:F55) -> 40927.45 | R55: =SUBTOTAL(9,$G$2:G55) -> 38421.54
A56: C15 | B56: 45581 | C56: Advance | G56: 5000 | N56: Y | P56: =R56-Q56 -> 2494.09 | Q56: =SUBTOTAL(9,$F$2:F56) -> 40927.45 | R56: =SUBTOTAL(9,$G$2:G56) -> 43421.54
A57: C15 | B57: 45593 | C57: Cleaning 09.2024 | F57: 526.5 | I57: t | K57: קלין סטס | L57: 2117 | N57: Y | P57: =R57-Q57 -> 1967.59 | Q57: =SUBTOTAL(9,$F$2:F57) -> 41453.95 | R57: =SUBTOTAL(9,$G$2:G57) -> 43421.54
A58: C15 | B58: 45601 | C58: Cealing fan | H58: 3900 | K58: טכנולייט | L58: 548418 | N58: Y | P58: =R58-Q58 -> 1967.59 | Q58: =SUBTOTAL(9,$F$2:F58) -> 41453.95 | R58: =SUBTOTAL(9,$G$2:G58) -> 43421.54
A59: C15 | B59: 45613 | C59: Advance | G59: 5000 | N59: Y | P59: =R59-Q59 -> 6967.59 | Q59: =SUBTOTAL(9,$F$2:F59) -> 41453.95 | R59: =SUBTOTAL(9,$G$2:G59) -> 48421.54
A60: C15 | B60: 45630 | C60: Leak & blockage repair | D60: OSHER | F60: 250 | N60: Y | P60: =R60-Q60 -> 6717.59 | Q60: =SUBTOTAL(9,$F$2:F60) -> 41703.95 | R60: =SUBTOTAL(9,$G$2:G60) -> 48421.54
A61: C15 | B61: 45661 | C61: Installing Kitchen Tap | D61: OSHER | F61: 250 | I61: t | N61: Y | P61: =R61-Q61 -> 6467.59 | Q61: =SUBTOTAL(9,$F$2:F61) -> 41953.95 | R61: =SUBTOTAL(9,$G$2:G61) -> 48421.54
A62: C15 | B62: 45662 | C62: Cleaning 12.2024 | D62: David 5 hrs | F62: 360 | I62: t | N62: Y | P62: =R62-Q62 -> 6107.59 | Q62: =SUBTOTAL(9,$F$2:F62) -> 42313.95 | R62: =SUBTOTAL(9,$G$2:G62) -> 48421.54
A63: C15 | B63: 45662 | C63: Bituch Leumi cleaning 12.2024 | D63: David | F63: 26 | I63: t | N63: Y | P63: =R63-Q63 -> 6081.59 | Q63: =SUBTOTAL(9,$F$2:F63) -> 42339.95 | R63: =SUBTOTAL(9,$G$2:G63) -> 48421.54
